{
  "type": "FeatureCollection",
  "name": "PLANNED",
  "features": [
    {
      "type": "Feature",
      "geometry": {
        "type": "Point",
        "coordinates": [
          145.951906,
          -17.652463
        ]
      },
      "properties": {
        "EVENT_ID": "24FN5577",
        "TYPE": "PLANNED",
        "CUSTOMERS_AFFECTED": "4",
        "REASON": "The loss of supply is to replace power poles and improve the electricity network",
        "STATUS": "Crews working on-site",
        "START": "8:30AM 18 May 2024",
        "EST_FIX_TIME": "4:00PM 18 May 2024",
        "STREETS": "INNISFAIL JAPOON RD, UTCHEE CREEK RD",
        "SUBURBS": "MENA CREEK, UTCHEE CREEK"
      }
    },
    {
      "type": "Feature",
      "geometry": {
        "type": "Point",
        "coordinates": [
          146.331519,
          -18.526706
        ]
      },
      "properties": {
        "EVENT_ID": "24NQ7319",
        "TYPE": "PLANNED",
        "CUSTOMERS_AFFECTED": "4",
        "REASON": "The loss of supply is to connect new customers to the electricity network",
        "STATUS": "Crews working on-site",
        "START": "12:30PM 17 May 2024",
        "EST_FIX_TIME": "3:30PM 30 May 2024",
        "STREETS": "DUNGENESS RD, KEAST ST",
        "SUBURBS": "LUCINDA"
      }
    },
    {
      "type": "Feature",
      "geometry": {
        "type": "Point",
        "coordinates": [
          151.820415,
          -26.41737
        ]
      },
      "properties": {
        "EVENT_ID": "24WB5240",
        "TYPE": "PLANNED",
        "CUSTOMERS_AFFECTED": "5",
        "REASON": "The loss of supply is to connect new customers to the electricity network",
        "STATUS": "Crews working on-site",
        "START": "8:30AM 18 May 2024",
        "EST_FIX_TIME": "2:30PM 18 May 2024",
        "STREETS": "BUNYA HWY",
        "SUBURBS": "WOOROOLIN"
      }
    }
  ],
  "company": "Ergon",
  "state": "Current",
  "extracted": "1716006603.677358"
}
