{
  "type": "FeatureCollection",
  "name": "PLANNED",
  "features": [
    {
      "type": "Feature",
      "geometry": {
        "type": "Point",
        "coordinates": [
          151.224324,
          -23.878823
        ]
      },
      "properties": {
        "EVENT_ID": "24CA6087",
        "TYPE": "PLANNED",
        "CUSTOMERS_AFFECTED": "16",
        "REASON": "The loss of supply is to allow maintenance of the electricity network",
        "STATUS": "Work scheduled",
        "START": "8:30PM 19 May 2024",
        "EST_FIX_TIME": "3:30AM 20 May 2024",
        "STREETS": "DAWSON HWY, HARVEY RD",
        "SUBURBS": "CLINTON, GLADSTONE"
      }
    },
    {
      "type": "Feature",
      "geometry": {
        "type": "Point",
        "coordinates": [
          146.331519,
          -18.526706
        ]
      },
      "properties": {
        "EVENT_ID": "24NQ7319",
        "TYPE": "PLANNED",
        "CUSTOMERS_AFFECTED": "4",
        "REASON": "The loss of supply is to connect new customers to the electricity network",
        "STATUS": "Crews working on-site",
        "START": "12:30PM 17 May 2024",
        "EST_FIX_TIME": "3:30PM 30 May 2024",
        "STREETS": "DUNGENESS RD, KEAST ST",
        "SUBURBS": "LUCINDA"
      }
    },
    {
      "type": "Feature",
      "geometry": {
        "type": "Point",
        "coordinates": [
          152.704763,
          -25.539045
        ]
      },
      "properties": {
        "EVENT_ID": "24WB5249",
        "TYPE": "PLANNED",
        "CUSTOMERS_AFFECTED": "27",
        "REASON": "The loss of supply is to replace power poles and improve the electricity network",
        "STATUS": "Crews working on-site",
        "START": "12:30PM 19 May 2024",
        "EST_FIX_TIME": "5:30PM 19 May 2024",
        "STREETS": "BAZAAR ST, MACALISTER ST, RICHMOND ST, WHARF ST",
        "SUBURBS": "MARYBOROUGH"
      }
    },
    {
      "type": "Feature",
      "geometry": {
        "type": "Point",
        "coordinates": [
          152.351873,
          -24.871263
        ]
      },
      "properties": {
        "EVENT_ID": "24WB5324",
        "TYPE": "PLANNED",
        "CUSTOMERS_AFFECTED": "71",
        "REASON": "The loss of supply is to allow maintenance of the electricity network",
        "STATUS": "Crews working on-site",
        "START": "7:30AM 19 May 2024",
        "EST_FIX_TIME": "5:00PM 19 May 2024",
        "STREETS": "BAROLIN ST, BOURBONG ST, TARGO ST, WOONDOOMA ST, WOONGARRA ST",
        "SUBURBS": "BUNDABERG, BUNDABERG CENTRAL"
      }
    }
  ],
  "company": "Ergon",
  "state": "Current",
  "extracted": "1716099601.175437"
}
