{
  "type": "FeatureCollection",
  "name": "PLANNED",
  "features": [
    {
      "type": "Feature",
      "geometry": {
        "type": "Point",
        "coordinates": [
          148.250812,
          -20.01231
        ]
      },
      "properties": {
        "EVENT_ID": "24NQ5133",
        "TYPE": "PLANNED",
        "CUSTOMERS_AFFECTED": "6",
        "REASON": "The loss of supply is to replace power poles and improve the electricity network",
        "STATUS": "Crews working on-site",
        "START": "9:51AM 17 Mar 2024",
        "EST_FIX_TIME": "5:30PM 17 Mar 2024",
        "STREETS": "GEORGE ST, GREGORY ST",
        "SUBURBS": "BOWEN"
      }
    }
  ],
  "company": "Ergon",
  "state": "Current",
  "extracted": "1710658201.217586"
}
