{
  "type": "FeatureCollection",
  "name": "PLANNED",
  "features": [
    {
      "type": "Feature",
      "geometry": {
        "type": "Point",
        "coordinates": [
          148.847336,
          -20.973532
        ]
      },
      "properties": {
        "EVENT_ID": "24MK3920",
        "TYPE": "PLANNED",
        "CUSTOMERS_AFFECTED": "316",
        "REASON": "The loss of supply is to allow emergency maintenance of the electricity network",
        "STATUS": "Crews working on-site",
        "START": "8:12AM 23 May 2024",
        "EST_FIX_TIME": "5:30PM 23 May 2024",
        "STREETS": "AMBRYM ST, BOGGA RD, BRUCE HWY, BUTHURRA STATION RD, CHURCH ST, CLANSIDE RD, CLIFFES RD, CLYDE MCLEANS RD, FAIRCHILDS RD, FERRIS RD, GEEBERGA BUTHURRA RD, GIFFORDS RD, HOLDINGS RD, HOWLANDS RD, J JOHNSONS RD, JANSENS RD, JIM MCLEANS RD, JOHNSONS RD, KOLIJO MT PELION RD, LANDING RD, LITTLE BOGGA RD, LONG MILE RD, MACKENZIES RD, MCDERMOTTS RD, MCKAYS RD, MCLEANS RD, MIRANI MOUNT OSSA RD, MOUNT OSSA RD, MOUNT OSSA SEAFORTH RD, MOUNT PELION RD, MT OSSA MIRANI RD, MT OSSA SCHOOL RD, MULHERINS RD, NARPI RD, ONE MILE CREEK RD, PACES RD, PAUL BURGER RD, PRATTS RD, ST HELENS BEACH RD, STARKEYS RD, SURPRISE CREEK RD, TOOMAS RD, TREVEYS RD, WATTS RD, WILLS RD",
        "SUBURBS": "BUTHURRA, CALEN, KOLIJO, KUTTABUL, MACKAY, MIRANI, MOUNT CHARLTON, MOUNT OSSA, MOUNT PELION, SEAFORTH"
      }
    },
    {
      "type": "Feature",
      "geometry": {
        "type": "Point",
        "coordinates": [
          146.331519,
          -18.526706
        ]
      },
      "properties": {
        "EVENT_ID": "24NQ7319",
        "TYPE": "PLANNED",
        "CUSTOMERS_AFFECTED": "4",
        "REASON": "The loss of supply is to connect new customers to the electricity network",
        "STATUS": "Crews working on-site",
        "START": "12:30PM 17 May 2024",
        "EST_FIX_TIME": "3:30PM 30 May 2024",
        "STREETS": "DUNGENESS RD, KEAST ST",
        "SUBURBS": "LUCINDA"
      }
    }
  ],
  "company": "Ergon",
  "state": "Current",
  "extracted": "1716449101.673062"
}
