{
  "type": "FeatureCollection",
  "name": "PLANNED",
  "features": [
    {
      "type": "Feature",
      "geometry": {
        "type": "Point",
        "coordinates": [
          149.170241,
          -21.097701
        ]
      },
      "properties": {
        "EVENT_ID": "24MK2817",
        "TYPE": "PLANNED",
        "CUSTOMERS_AFFECTED": "79",
        "REASON": "The loss of supply is to allow maintenance of the electricity network",
        "STATUS": "Crews working on-site",
        "START": "9:11AM 04 Apr 2024",
        "EST_FIX_TIME": "4:30PM 04 Apr 2024",
        "STREETS": "AVOCADO CT, AZALEA CT, CASSIA ST, ILLAWARA CT, KURRAJONG CT, MANSFIELD DR, WARATAH ST",
        "SUBURBS": "BEACONSFIELD"
      }
    },
    {
      "type": "Feature",
      "geometry": {
        "type": "Point",
        "coordinates": [
          149.0494,
          -21.168022
        ]
      },
      "properties": {
        "EVENT_ID": "24MK2893",
        "TYPE": "PLANNED",
        "CUSTOMERS_AFFECTED": "151",
        "REASON": "The loss of supply is to allow maintenance of the electricity network",
        "STATUS": "Crews working on-site",
        "START": "8:09AM 04 Apr 2024",
        "EST_FIX_TIME": "4:30PM 04 Apr 2024",
        "STREETS": "GERARD CT, GRACIE CT, GREENMOUNT RD, JAMES MUSCAT DR, JOSTINE ST, MELISSA CRES, PAULINE ST, STEVIC ST, WAYNE ST",
        "SUBURBS": "GREENMOUNT, WALKERSTON"
      }
    },
    {
      "type": "Feature",
      "geometry": {
        "type": "Point",
        "coordinates": [
          139.490392,
          -20.701177
        ]
      },
      "properties": {
        "EVENT_ID": "24NQ6135",
        "TYPE": "PLANNED",
        "CUSTOMERS_AFFECTED": "22",
        "REASON": "The loss of supply is to upgrade equipment to meet customer demand for electricity and to improve reliability of supply in the area",
        "STATUS": "Crews working on-site",
        "START": "8:14AM 04 Apr 2024",
        "EST_FIX_TIME": "4:00PM 04 Apr 2024",
        "STREETS": "LABUAN ST",
        "SUBURBS": "SOLDIERS HILL"
      }
    },
    {
      "type": "Feature",
      "geometry": {
        "type": "Point",
        "coordinates": [
          151.181685,
          -27.509909
        ]
      },
      "properties": {
        "EVENT_ID": "24SW6031",
        "TYPE": "PLANNED",
        "CUSTOMERS_AFFECTED": "37",
        "REASON": "The loss of supply is to replace power poles and improve the electricity network",
        "STATUS": "Crews working on-site",
        "START": "8:51AM 04 Apr 2024",
        "EST_FIX_TIME": "4:30PM 04 Apr 2024",
        "STREETS": "BOUNDARY RD, DALBY CECIL PLAINS RD, LEICHHARDT LANE, TAYLOR ST, TOOWOOMBA CECIL PLAINS RD, WARFIELD AVE, WILKINS RD",
        "SUBURBS": "CECIL PLAINS"
      }
    }
  ],
  "company": "Ergon",
  "state": "Current",
  "extracted": "1712211001.341315"
}
