{
  "type": "FeatureCollection",
  "name": "PLANNED",
  "features": [
    {
      "type": "Feature",
      "geometry": {
        "type": "Point",
        "coordinates": [
          149.170241,
          -21.097701
        ]
      },
      "properties": {
        "EVENT_ID": "24MK2817",
        "TYPE": "PLANNED",
        "CUSTOMERS_AFFECTED": "79",
        "REASON": "The loss of supply is to allow maintenance of the electricity network",
        "STATUS": "Crews working on-site",
        "START": "9:11AM 04 Apr 2024",
        "EST_FIX_TIME": "5:30PM 04 Apr 2024",
        "STREETS": "AVOCADO CT, AZALEA CT, CASSIA ST, ILLAWARA CT, KURRAJONG CT, MANSFIELD DR, WARATAH ST",
        "SUBURBS": "BEACONSFIELD"
      }
    },
    {
      "type": "Feature",
      "geometry": {
        "type": "Point",
        "coordinates": [
          149.0494,
          -21.168022
        ]
      },
      "properties": {
        "EVENT_ID": "24MK2893",
        "TYPE": "PLANNED",
        "CUSTOMERS_AFFECTED": "151",
        "REASON": "The loss of supply is to allow maintenance of the electricity network",
        "STATUS": "Crews working on-site",
        "START": "8:09AM 04 Apr 2024",
        "EST_FIX_TIME": "5:30PM 04 Apr 2024",
        "STREETS": "GERARD CT, GRACIE CT, GREENMOUNT RD, JAMES MUSCAT DR, JOSTINE ST, MELISSA CRES, PAULINE ST, STEVIC ST, WAYNE ST",
        "SUBURBS": "GREENMOUNT, WALKERSTON"
      }
    }
  ],
  "company": "Ergon",
  "state": "Current",
  "extracted": "1712214301.34086"
}
