{
  "type": "FeatureCollection",
  "name": "PLANNED",
  "features": [
    {
      "type": "Feature",
      "geometry": {
        "type": "Point",
        "coordinates": [
          148.822647,
          -21.091816
        ]
      },
      "properties": {
        "EVENT_ID": "24MK4078",
        "TYPE": "PLANNED",
        "CUSTOMERS_AFFECTED": "82",
        "REASON": "The loss of supply is to allow maintenance of the electricity network",
        "STATUS": "Crews working on-site",
        "START": "9:00AM 26 May 2024",
        "EST_FIX_TIME": "6:45PM 26 May 2024",
        "STREETS": "BRADSHAWS RD, COYNES RD, GARNHAM MORROWS RD, GEEBERGA BUTHURRA RD, MCFAULS RD, MORRIS RD, MOUNT MARTIN GAP RD, MOUNT MARTIN LOOP RD, MOUNT MARTIN RD, MOUNT TOBY RD, SUGARLOAF RD",
        "SUBURBS": "KUTTABUL, MOUNT MARTIN"
      }
    },
    {
      "type": "Feature",
      "geometry": {
        "type": "Point",
        "coordinates": [
          146.331519,
          -18.526706
        ]
      },
      "properties": {
        "EVENT_ID": "24NQ7319",
        "TYPE": "PLANNED",
        "CUSTOMERS_AFFECTED": "4",
        "REASON": "The loss of supply is to connect new customers to the electricity network",
        "STATUS": "Crews working on-site",
        "START": "12:30PM 17 May 2024",
        "EST_FIX_TIME": "3:30PM 30 May 2024",
        "STREETS": "DUNGENESS RD, KEAST ST",
        "SUBURBS": "LUCINDA"
      }
    }
  ],
  "company": "Ergon",
  "state": "Current",
  "extracted": "1716711001.078417"
}
