{
  "type": "FeatureCollection",
  "name": "PLANNED",
  "features": [
    {
      "type": "Feature",
      "geometry": {
        "type": "Point",
        "coordinates": [
          151.957392,
          -27.542557
        ]
      },
      "properties": {
        "EVENT_ID": "24SW6561",
        "TYPE": "PLANNED",
        "CUSTOMERS_AFFECTED": "156",
        "REASON": "The loss of supply is to replace power poles and improve the electricity network",
        "STATUS": "Crews working on-site",
        "START": "9:08PM 09 Apr 2024",
        "EST_FIX_TIME": "4:00AM 10 Apr 2024",
        "STREETS": "ABELIA ST, ELWORTHY ST, EUGENIA ST, HUME ST, KOOMBARRA ST, NORTH ST, RUTHVEN ST, VENTURE ST, WOLSELEY ST",
        "SUBURBS": "HARLAXTON, NORTH TOOWOOMBA, TOOWOOMBA"
      }
    }
  ],
  "company": "Ergon",
  "state": "Current",
  "extracted": "1712662206.089093"
}
