{
  "type": "FeatureCollection",
  "name": "PLANNED",
  "features": [
    {
      "type": "Feature",
      "geometry": {
        "type": "Point",
        "coordinates": [
          146.331519,
          -18.526706
        ]
      },
      "properties": {
        "EVENT_ID": "24NQ5670",
        "TYPE": "PLANNED",
        "CUSTOMERS_AFFECTED": "4",
        "REASON": "The loss of supply is to allow maintenance of the electricity network",
        "STATUS": "Crews working on-site",
        "START": "9:00AM 15 Apr 2024",
        "EST_FIX_TIME": "3:00PM 19 Apr 2024",
        "STREETS": "DUNGENESS RD, KEAST ST",
        "SUBURBS": "LUCINDA"
      }
    },
    {
      "type": "Feature",
      "geometry": {
        "type": "Point",
        "coordinates": [
          151.28392,
          -27.789694
        ]
      },
      "properties": {
        "EVENT_ID": "24SW6735",
        "TYPE": "PLANNED",
        "CUSTOMERS_AFFECTED": "17",
        "REASON": "The loss of supply is to upgrade equipment to meet customer demand for electricity and to improve reliability of supply in the area",
        "STATUS": "Rescheduled",
        "START": "10:00PM 17 Apr 2024",
        "EST_FIX_TIME": "5:00AM 18 Apr 2024",
        "STREETS": "BOSTOCK RD",
        "SUBURBS": "LEMONTREE"
      }
    },
    {
      "type": "Feature",
      "geometry": {
        "type": "Point",
        "coordinates": [
          151.948304,
          -27.582911
        ]
      },
      "properties": {
        "EVENT_ID": "24SW6790",
        "TYPE": "PLANNED",
        "CUSTOMERS_AFFECTED": "80",
        "REASON": "The loss of supply is to replace power poles and improve the electricity network",
        "STATUS": "Work scheduled",
        "START": "11:00PM 17 Apr 2024",
        "EST_FIX_TIME": "2:00AM 18 Apr 2024",
        "STREETS": "BALANGA CT, DORA ST, MERRYL ST, PIERCE ST, RUTHVEN ST",
        "SUBURBS": "SOUTH TOOWOOMBA, TOOWOOMBA"
      }
    }
  ],
  "company": "Ergon",
  "state": "Current",
  "extracted": "1713345908.033524"
}
