{
  "type": "FeatureCollection",
  "name": "PLANNED",
  "features": [
    {
      "type": "Feature",
      "geometry": {
        "type": "Point",
        "coordinates": [
          145.397836,
          -16.465206
        ]
      },
      "properties": {
        "EVENT_ID": "24FN3060",
        "TYPE": "PLANNED",
        "CUSTOMERS_AFFECTED": "8",
        "REASON": "The loss of supply is to replace power poles and improve the electricity network",
        "STATUS": "Crews working on-site",
        "START": "9:36AM 22 Apr 2024",
        "EST_FIX_TIME": "4:30PM 22 Apr 2024",
        "STREETS": "BONNIE DOON RD, EAGLE CL, SANTAROSSA RD",
        "SUBURBS": "BONNIE DOON, MOSSMAN"
      }
    },
    {
      "type": "Feature",
      "geometry": {
        "type": "Point",
        "coordinates": [
          146.023859,
          -18.263499
        ]
      },
      "properties": {
        "EVENT_ID": "24FN4811",
        "TYPE": "PLANNED",
        "CUSTOMERS_AFFECTED": "40",
        "REASON": "The loss of supply is to replace power poles and improve the electricity network",
        "STATUS": "Crews working on-site",
        "START": "8:30AM 22 Apr 2024",
        "EST_FIX_TIME": "4:00PM 22 Apr 2024",
        "STREETS": "BOWEN ST, LIVERPOOL ST, SCOTT ST, VICTORIA ST",
        "SUBURBS": "CARDWELL"
      }
    },
    {
      "type": "Feature",
      "geometry": {
        "type": "Point",
        "coordinates": [
          151.957085,
          -27.560581
        ]
      },
      "properties": {
        "EVENT_ID": "24SW7992",
        "TYPE": "PLANNED",
        "CUSTOMERS_AFFECTED": "3",
        "REASON": "The loss of supply is to upgrade equipment to meet customer demand for electricity and to improve reliability of supply in the area",
        "STATUS": "Work scheduled",
        "START": "8:30PM 22 Apr 2024",
        "EST_FIX_TIME": "1:30AM 23 Apr 2024",
        "STREETS": "BELL ST",
        "SUBURBS": "TOOWOOMBA, TOOWOOMBA CITY"
      }
    }
  ],
  "company": "Ergon",
  "state": "Current",
  "extracted": "1713763201.609841"
}
