{
  "type": "FeatureCollection",
  "name": "PLANNED",
  "features": [
    {
      "type": "Feature",
      "geometry": {
        "type": "Point",
        "coordinates": [
          145.75629,
          -16.931491
        ]
      },
      "properties": {
        "EVENT_ID": "24FN2940",
        "TYPE": "PLANNED",
        "CUSTOMERS_AFFECTED": "239",
        "REASON": "The loss of supply is to replace power poles and improve the electricity network",
        "STATUS": "Crews working on-site",
        "START": "10:30PM 21 Mar 2024",
        "EST_FIX_TIME": "4:30AM 22 Mar 2024",
        "STREETS": "ALLAN ST, AUMULLER ST, CREEDY ST, EARL ST, MULGRAVE RD, O'LEARY ST, SCOTT ST",
        "SUBURBS": "BUNGALOW, CAIRNS, WESTCOURT"
      }
    },
    {
      "type": "Feature",
      "geometry": {
        "type": "Point",
        "coordinates": [
          148.941545,
          -21.125662
        ]
      },
      "properties": {
        "EVENT_ID": "24MK2396",
        "TYPE": "PLANNED",
        "CUSTOMERS_AFFECTED": "216",
        "REASON": "The loss of supply is to replace power poles and improve the electricity network",
        "STATUS": "Work scheduled",
        "START": "11:00PM 21 Mar 2024",
        "EST_FIX_TIME": "6:00AM 22 Mar 2024",
        "STREETS": "ANZAC AVE, BRAND RD, COBENS RD, DELACHANTOS RD, DEVEREUX CREEK RD, DOYLES RD, FORDYCES RD, GREENMOUNT ST, GRIFFITHS RD, HAMPDEN CT, HEATHWOOD CT, HELENS CT, MACKAY EUNGELLA RD, MARIAN HAMPDEN RD, MARIAN-HAMPDEN RD, MARION ST, MILTONS LOOKOUT RD, MIRANI BOLDON RD, NEWBURY MOUNT VINCE RD, NEWMANS RD, OLD HAMPDEN RD, PEACHS RD, STAYTES RD, SWANS RD, TIRENDIS RD, VICKERS RD, WRIGHTS RD",
        "SUBURBS": "BALNAGOWAN, DEVEREUX CREEK, HAMPDEN, MACKAY, MARIAN, MIRANI, PLEYSTOWE"
      }
    },
    {
      "type": "Feature",
      "geometry": {
        "type": "Point",
        "coordinates": [
          148.943134,
          -21.16033
        ]
      },
      "properties": {
        "EVENT_ID": "24MK2466",
        "TYPE": "PLANNED",
        "CUSTOMERS_AFFECTED": "19",
        "REASON": "The loss of supply is to replace power poles and improve the electricity network",
        "STATUS": "Work scheduled",
        "START": "11:00PM 21 Mar 2024",
        "EST_FIX_TIME": "6:00AM 22 Mar 2024",
        "STREETS": "CLAIRES RD, MARIAN ETON RD",
        "SUBURBS": "MARIAN"
      }
    }
  ],
  "company": "Ergon",
  "state": "Current",
  "extracted": "1711022403.701375"
}
