{
  "type": "FeatureCollection",
  "name": "PLANNED",
  "features": [
    {
      "type": "Feature",
      "geometry": {
        "type": "Point",
        "coordinates": [
          139.491508,
          -20.699237
        ]
      },
      "properties": {
        "EVENT_ID": "24NQ7590",
        "TYPE": "PLANNED",
        "CUSTOMERS_AFFECTED": "2",
        "REASON": "The loss of supply is to replace power poles and improve the electricity network",
        "STATUS": "Work scheduled",
        "START": "12:00PM 05 Jun 2024",
        "EST_FIX_TIME": "2:00PM 05 Jun 2024",
        "STREETS": "URQUHART ST",
        "SUBURBS": "SOLDIERS HILL"
      }
    },
    {
      "type": "Feature",
      "geometry": {
        "type": "Point",
        "coordinates": [
          139.489293,
          -20.697703
        ]
      },
      "properties": {
        "EVENT_ID": "24NQ7592",
        "TYPE": "PLANNED",
        "CUSTOMERS_AFFECTED": "2",
        "REASON": "The loss of supply is to replace power poles and improve the electricity network",
        "STATUS": "Work scheduled",
        "START": "2:00PM 05 Jun 2024",
        "EST_FIX_TIME": "5:00PM 05 Jun 2024",
        "STREETS": "ABAU ST",
        "SUBURBS": "SOLDIERS HILL"
      }
    },
    {
      "type": "Feature",
      "geometry": {
        "type": "Point",
        "coordinates": [
          152.531318,
          -25.24877
        ]
      },
      "properties": {
        "EVENT_ID": "24WB5711",
        "TYPE": "PLANNED",
        "CUSTOMERS_AFFECTED": "14",
        "REASON": "The loss of supply is to replace power poles and improve the electricity network",
        "STATUS": "Work scheduled",
        "START": "12:30PM 05 Jun 2024",
        "EST_FIX_TIME": "2:30PM 05 Jun 2024",
        "STREETS": "PACIFIC HAVEN CCT",
        "SUBURBS": "PACIFIC HAVEN"
      }
    }
  ],
  "company": "Ergon",
  "state": "Current",
  "extracted": "1717548304.117299"
}
