{
  "type": "FeatureCollection",
  "name": "PLANNED",
  "features": [
    {
      "type": "Feature",
      "geometry": {
        "type": "Point",
        "coordinates": [
          150.754489,
          -23.144929
        ]
      },
      "properties": {
        "EVENT_ID": "24CA3543",
        "TYPE": "PLANNED",
        "CUSTOMERS_AFFECTED": "18",
        "REASON": "The loss of supply is to replace power poles and improve the electricity network",
        "STATUS": "Crews working on-site",
        "START": "7:30AM 14 Mar 2024",
        "EST_FIX_TIME": "4:30PM 14 Mar 2024",
        "STREETS": "DOLPHIN CRES, SWORDFISH AVE",
        "SUBURBS": "TARANGANBA"
      }
    }
  ],
  "company": "Ergon",
  "state": "Current",
  "extracted": "1710403501.304899"
}
