{
  "type": "FeatureCollection",
  "name": "PLANNED",
  "features": [
    {
      "type": "Feature",
      "geometry": {
        "type": "Point",
        "coordinates": [
          149.159124,
          -21.118577
        ]
      },
      "properties": {
        "EVENT_ID": "24MK4271",
        "TYPE": "PLANNED",
        "CUSTOMERS_AFFECTED": "33",
        "REASON": "The loss of supply is to allow maintenance of the electricity network",
        "STATUS": "Work scheduled",
        "START": "10:00PM 29 May 2024",
        "EST_FIX_TIME": "5:00AM 30 May 2024",
        "STREETS": "PHILLIP ST",
        "SUBURBS": "MOUNT PLEASANT"
      }
    },
    {
      "type": "Feature",
      "geometry": {
        "type": "Point",
        "coordinates": [
          149.159509,
          -21.11793
        ]
      },
      "properties": {
        "EVENT_ID": "24MK4274",
        "TYPE": "PLANNED",
        "CUSTOMERS_AFFECTED": "5",
        "REASON": "The loss of supply is to allow maintenance of the electricity network",
        "STATUS": "Work scheduled",
        "START": "10:00PM 29 May 2024",
        "EST_FIX_TIME": "5:00AM 30 May 2024",
        "STREETS": "PHILLIP ST",
        "SUBURBS": "MOUNT PLEASANT"
      }
    },
    {
      "type": "Feature",
      "geometry": {
        "type": "Point",
        "coordinates": [
          146.331519,
          -18.526706
        ]
      },
      "properties": {
        "EVENT_ID": "24NQ7319",
        "TYPE": "PLANNED",
        "CUSTOMERS_AFFECTED": "4",
        "REASON": "The loss of supply is to connect new customers to the electricity network",
        "STATUS": "Crews working on-site",
        "START": "12:30PM 17 May 2024",
        "EST_FIX_TIME": "3:30PM 30 May 2024",
        "STREETS": "DUNGENESS RD, KEAST ST",
        "SUBURBS": "LUCINDA"
      }
    },
    {
      "type": "Feature",
      "geometry": {
        "type": "Point",
        "coordinates": [
          146.798398,
          -19.29923
        ]
      },
      "properties": {
        "EVENT_ID": "24NQ8324",
        "TYPE": "PLANNED",
        "CUSTOMERS_AFFECTED": "69",
        "REASON": "The loss of supply is to upgrade equipment to meet customer demand for electricity and to improve reliability of supply in the area",
        "STATUS": "Crews working on-site",
        "START": "9:04PM 29 May 2024",
        "EST_FIX_TIME": "3:00AM 30 May 2024",
        "STREETS": "BOWEN RD, CRAFTSMAN ST, LOVE LANE, O'CONNOR ST, SNELHAM ST, WELSH ST",
        "SUBURBS": "ROSSLEA"
      }
    }
  ],
  "company": "Ergon",
  "state": "Current",
  "extracted": "1716983401.45063"
}
