{
  "type": "FeatureCollection",
  "name": "PLANNED",
  "features": [
    {
      "type": "Feature",
      "geometry": {
        "type": "Point",
        "coordinates": [
          149.275913,
          -21.362213
        ]
      },
      "properties": {
        "EVENT_ID": "24MK3989",
        "TYPE": "PLANNED",
        "CUSTOMERS_AFFECTED": "57",
        "REASON": "The loss of supply is to upgrade equipment to meet customer demand for electricity and to improve reliability of supply in the area",
        "STATUS": "Crews working on-site",
        "START": "9:04AM 24 May 2024",
        "EST_FIX_TIME": "4:30PM 24 May 2024",
        "STREETS": "GRASSTREE BEACH RD, GRASSTREE RD, IRONSIDES RD, SARINA BEACH RD",
        "SUBURBS": "ALLIGATOR CREEK, GRASSTREE BEACH, SARINA"
      }
    },
    {
      "type": "Feature",
      "geometry": {
        "type": "Point",
        "coordinates": [
          146.331519,
          -18.526706
        ]
      },
      "properties": {
        "EVENT_ID": "24NQ7319",
        "TYPE": "PLANNED",
        "CUSTOMERS_AFFECTED": "4",
        "REASON": "The loss of supply is to connect new customers to the electricity network",
        "STATUS": "Crews working on-site",
        "START": "12:30PM 17 May 2024",
        "EST_FIX_TIME": "3:30PM 30 May 2024",
        "STREETS": "DUNGENESS RD, KEAST ST",
        "SUBURBS": "LUCINDA"
      }
    }
  ],
  "company": "Ergon",
  "state": "Current",
  "extracted": "1716532203.453665"
}
