{
  "type": "FeatureCollection",
  "name": "PLANNED",
  "features": [
    {
      "type": "Feature",
      "geometry": {
        "type": "Point",
        "coordinates": [
          145.405709,
          -16.423695
        ]
      },
      "properties": {
        "EVENT_ID": "24FN0433",
        "TYPE": "PLANNED",
        "CUSTOMERS_AFFECTED": "2",
        "REASON": "The loss of supply is to replace power poles and improve the electricity network",
        "STATUS": "Crews working on-site",
        "START": "9:04AM 11 Mar 2024",
        "EST_FIX_TIME": "1:00PM 11 Mar 2024",
        "STREETS": "ANDREWS ST",
        "SUBURBS": "NEWELL"
      }
    },
    {
      "type": "Feature",
      "geometry": {
        "type": "Point",
        "coordinates": [
          145.471761,
          -17.260672
        ]
      },
      "properties": {
        "EVENT_ID": "24FN3157",
        "TYPE": "PLANNED",
        "CUSTOMERS_AFFECTED": "9",
        "REASON": "The loss of supply is to replace power poles and improve the electricity network",
        "STATUS": "Crews working on-site",
        "START": "10:30AM 11 Mar 2024",
        "EST_FIX_TIME": "3:30PM 11 Mar 2024",
        "STREETS": "CANOPUS CCT",
        "SUBURBS": "ATHERTON"
      }
    },
    {
      "type": "Feature",
      "geometry": {
        "type": "Point",
        "coordinates": [
          146.263794,
          -18.622522
        ]
      },
      "properties": {
        "EVENT_ID": "24NQ5093",
        "TYPE": "PLANNED",
        "CUSTOMERS_AFFECTED": "9",
        "REASON": "The loss of supply is to upgrade equipment to meet customer demand for electricity and to improve reliability of supply in the area",
        "STATUS": "Work scheduled",
        "START": "12:00PM 11 Mar 2024",
        "EST_FIX_TIME": "4:00PM 11 Mar 2024",
        "STREETS": "FIVE MILE RD, FOUR MILE RD",
        "SUBURBS": "BRAEMEADOWS"
      }
    }
  ],
  "company": "Ergon",
  "state": "Current",
  "extracted": "1710121201.587672"
}
