{
  "type": "FeatureCollection",
  "name": "PLANNED",
  "features": [
    {
      "type": "Feature",
      "geometry": {
        "type": "Point",
        "coordinates": [
          151.937223,
          -27.529631
        ]
      },
      "properties": {
        "EVENT_ID": "24SW9204",
        "TYPE": "PLANNED",
        "CUSTOMERS_AFFECTED": "54",
        "REASON": "The loss of supply is to connect new customers to the electricity network",
        "STATUS": "Crews working on-site",
        "START": "8:30AM 22 Jun 2024",
        "EST_FIX_TIME": "5:00PM 22 Jun 2024",
        "STREETS": "CHOPIN ST, HOLBERTON ST, JONATHAN ST",
        "SUBURBS": "ROCKVILLE"
      }
    }
  ],
  "company": "Ergon",
  "state": "Current",
  "extracted": "1719038702.748028"
}
