{
  "type": "FeatureCollection",
  "name": "PLANNED",
  "features": [
    {
      "type": "Feature",
      "geometry": {
        "type": "Point",
        "coordinates": [
          149.0865,
          -21.226793
        ]
      },
      "properties": {
        "EVENT_ID": "24MK4245",
        "TYPE": "PLANNED",
        "CUSTOMERS_AFFECTED": "43",
        "REASON": "The loss of supply is to upgrade equipment to meet customer demand for electricity and to improve reliability of supply in the area",
        "STATUS": "Crews working on-site",
        "START": "9:02AM 10 Jun 2024",
        "EST_FIX_TIME": "5:00PM 10 Jun 2024",
        "STREETS": "GRIMAS RD, WALKERSTON HOMEBUSH RD, WALKERSTON-HOMEBUSH RD",
        "SUBURBS": "HOMEBUSH, PALMYRA, SANDIFORD, WALKERSTON"
      }
    },
    {
      "type": "Feature",
      "geometry": {
        "type": "Point",
        "coordinates": [
          149.43412,
          -21.716372
        ]
      },
      "properties": {
        "EVENT_ID": "24MK4579",
        "TYPE": "PLANNED",
        "CUSTOMERS_AFFECTED": "2",
        "REASON": "The loss of supply is to connect new customers to the electricity network",
        "STATUS": "Crews working on-site",
        "START": "8:00AM 10 Jun 2024",
        "EST_FIX_TIME": "2:30PM 14 Jun 2024",
        "STREETS": "NOTCH POINT RD",
        "SUBURBS": "ILBILBIE"
      }
    },
    {
      "type": "Feature",
      "geometry": {
        "type": "Point",
        "coordinates": [
          147.801326,
          -20.562816
        ]
      },
      "properties": {
        "EVENT_ID": "24NQ8806",
        "TYPE": "PLANNED",
        "CUSTOMERS_AFFECTED": "2",
        "REASON": "The loss of supply is to replace power poles and improve the electricity network",
        "STATUS": "Crews working on-site",
        "START": "6:00AM 10 Jun 2024",
        "EST_FIX_TIME": "6:00PM 12 Jun 2024",
        "STREETS": "SCOTTVILLE RD",
        "SUBURBS": "COLLINSVILLE"
      }
    },
    {
      "type": "Feature",
      "geometry": {
        "type": "Point",
        "coordinates": [
          152.671127,
          -25.246362
        ]
      },
      "properties": {
        "EVENT_ID": "24WB5688",
        "TYPE": "PLANNED",
        "CUSTOMERS_AFFECTED": "11",
        "REASON": "The loss of supply is to allow maintenance of the electricity network",
        "STATUS": "Crews working on-site",
        "START": "8:00AM 10 Jun 2024",
        "EST_FIX_TIME": "5:00PM 10 Jun 2024",
        "STREETS": "KINGFISHER PDE, LORIKEET AVE, MARK AVE",
        "SUBURBS": "TOOGOOM"
      }
    }
  ],
  "company": "Ergon",
  "state": "Current",
  "extracted": "1718002200.511763"
}
