{
  "type": "FeatureCollection",
  "name": "PLANNED",
  "features": [
    {
      "type": "Feature",
      "geometry": {
        "type": "Point",
        "coordinates": [
          145.945567,
          -18.188254
        ]
      },
      "properties": {
        "EVENT_ID": "24FN3342",
        "TYPE": "PLANNED",
        "CUSTOMERS_AFFECTED": "2",
        "REASON": "The loss of supply is to replace power poles and improve the electricity network",
        "STATUS": "Crews working on-site",
        "START": "4:14PM 16 Mar 2024",
        "EST_FIX_TIME": "5:30PM 16 Mar 2024",
        "STREETS": "BRUCE HWY",
        "SUBURBS": "KENNEDY"
      }
    }
  ],
  "company": "Ergon",
  "state": "Current",
  "extracted": "1710572405.534757"
}
