{
  "type": "FeatureCollection",
  "name": "PLANNED",
  "features": [
    {
      "type": "Feature",
      "geometry": {
        "type": "Point",
        "coordinates": [
          151.983825,
          -26.668414
        ]
      },
      "properties": {
        "EVENT_ID": "24WB0473",
        "TYPE": "PLANNED",
        "CUSTOMERS_AFFECTED": "59",
        "REASON": "The loss of supply is to connect new customers to the electricity network",
        "STATUS": "Crews working on-site",
        "START": "8:42AM 09 Mar 2024",
        "EST_FIX_TIME": "2:30PM 09 Mar 2024",
        "STREETS": "AVOCA PL, BOONENNE CT, COOYAR CT, HIBISCUS CT, MILLIS WAY, OLEANDER ST",
        "SUBURBS": "NANANGO"
      }
    }
  ],
  "company": "Ergon",
  "state": "Current",
  "extracted": "1709955004.284381"
}
