{
  "type": "FeatureCollection",
  "name": "PLANNED",
  "features": [
    {
      "type": "Feature",
      "geometry": {
        "type": "Point",
        "coordinates": [
          145.776804,
          -16.925253
        ]
      },
      "properties": {
        "EVENT_ID": "24FN6439",
        "TYPE": "PLANNED",
        "CUSTOMERS_AFFECTED": "30",
        "REASON": "The loss of supply is to allow maintenance of the electricity network",
        "STATUS": "Work scheduled",
        "START": "10:00PM 25 Jun 2024",
        "EST_FIX_TIME": "1:00AM 26 Jun 2024",
        "STREETS": "GRAFTON ST, SPENCE ST",
        "SUBURBS": "CAIRNS"
      }
    },
    {
      "type": "Feature",
      "geometry": {
        "type": "Point",
        "coordinates": [
          147.438237,
          -19.527565
        ]
      },
      "properties": {
        "EVENT_ID": "24NQ9754",
        "TYPE": "PLANNED",
        "CUSTOMERS_AFFECTED": "2",
        "REASON": "The loss of supply is to connect new customers to the electricity network",
        "STATUS": "Crews working on-site",
        "START": "8:30AM 25 Jun 2024",
        "EST_FIX_TIME": "2:00PM 02 Jul 2024",
        "STREETS": "BURSTALL RD",
        "SUBURBS": "AYR"
      }
    }
  ],
  "company": "Ergon",
  "state": "Current",
  "extracted": "1719313501.281519"
}
