{
  "type": "FeatureCollection",
  "name": "PLANNED",
  "features": [
    {
      "type": "Feature",
      "geometry": {
        "type": "Point",
        "coordinates": [
          148.701682,
          -20.802678
        ]
      },
      "properties": {
        "EVENT_ID": "24MK3104",
        "TYPE": "PLANNED",
        "CUSTOMERS_AFFECTED": "14",
        "REASON": "The loss of supply is to upgrade equipment to meet customer demand for electricity and to improve reliability of supply in the area",
        "STATUS": "Crews working on-site",
        "START": "8:39AM 05 May 2024",
        "EST_FIX_TIME": "3:00PM 05 May 2024",
        "STREETS": "COMELLIS RD, STURMAS RD, WINTONS RD",
        "SUBURBS": "WAGOORA, YALBOROO"
      }
    },
    {
      "type": "Feature",
      "geometry": {
        "type": "Point",
        "coordinates": [
          139.506077,
          -20.697005
        ]
      },
      "properties": {
        "EVENT_ID": "24NQ7533",
        "TYPE": "PLANNED",
        "CUSTOMERS_AFFECTED": "97",
        "REASON": "The loss of supply is to allow emergency maintenance of the electricity network",
        "STATUS": "Crews working on-site",
        "START": "8:49AM 05 May 2024",
        "EST_FIX_TIME": "2:00PM 05 May 2024",
        "STREETS": "ACTIVITY RD, BARNES ST, CAMERON WAY, COMMERCIAL RD, DAVIS RD, ENGINEERING RD, INDUSTRIAL AVE, LANSKEY RD, PROGRESS RD, RICHARDSON RD, RYAN RD",
        "SUBURBS": "LANSKEY, RYAN, SUNSET"
      }
    },
    {
      "type": "Feature",
      "geometry": {
        "type": "Point",
        "coordinates": [
          152.098545,
          -27.091975
        ]
      },
      "properties": {
        "EVENT_ID": "24SW7374",
        "TYPE": "PLANNED",
        "CUSTOMERS_AFFECTED": "20",
        "REASON": "The loss of supply is to allow emergency maintenance of the electricity network",
        "STATUS": "Crews working on-site",
        "START": "9:00AM 05 May 2024",
        "EST_FIX_TIME": "2:00PM 05 May 2024",
        "STREETS": "ANDURAMBA RANGE RD, BOWEN RD, HAWKINS RD, HEATHER RD, MARSHALL RD, MCGREEVY RD, NUKINENDA RD, PETTIE RD, WATERHOLE GULLY RD",
        "SUBURBS": "ANDURAMBA, CROWS NEST, NUKINENDA, PIERCES CREEK"
      }
    }
  ],
  "company": "Ergon",
  "state": "Current",
  "extracted": "1714875901.136347"
}
