{
  "type": "FeatureCollection",
  "name": "PLANNED",
  "features": [
    {
      "type": "Feature",
      "geometry": {
        "type": "Point",
        "coordinates": [
          145.748428,
          -16.914592
        ]
      },
      "properties": {
        "EVENT_ID": "24FN4359",
        "TYPE": "PLANNED",
        "CUSTOMERS_AFFECTED": "2",
        "REASON": "The loss of supply is to allow maintenance of the electricity network",
        "STATUS": "Crews working on-site",
        "START": "6:41AM 10 Apr 2024",
        "EST_FIX_TIME": "7:30AM 11 Apr 2024",
        "STREETS": "ANDERSON ST",
        "SUBURBS": "MANUNDA"
      }
    },
    {
      "type": "Feature",
      "geometry": {
        "type": "Point",
        "coordinates": [
          143.919471,
          -21.690507
        ]
      },
      "properties": {
        "EVENT_ID": "24NQ6227",
        "TYPE": "PLANNED",
        "CUSTOMERS_AFFECTED": "100",
        "REASON": "The loss of supply is to allow maintenance of the electricity network",
        "STATUS": "Crews working on-site",
        "START": "8:30AM 10 Apr 2024",
        "EST_FIX_TIME": "5:00PM 10 Apr 2024",
        "STREETS": "ABBOTTSFORD STATION, AIREWORTH STATION, ANTRIM STATION, BARENYA STATION, BRANGA DOWNS STATION, BUNDELLA STATION, BURSLEM STATION, CULLODEN STATION, DALMUIR STATION, DUNROSSIE STATION, ELDORADO STATION, ELTON DOWNS STATION, ENSAY STATION, EVERSLEIGH STATION, GUE STATION, HILLVIEW STATION, INVERNESS STATION, LIMBRI DOWNS STATION, MALAKOFF STATION, MANUKA ST, MARANIE STATION, MARIONVALE STATION, MAROOMBA STATION, MOONBY DOWNS STATION, MUGWEE STATION, NARGON STATION, ORIELTON STATION, ROCKWOOD STATION, ROSSIEVALE STATION, SANDALWOOD STATION, STAMFORD DOWNS STATION, STAMFORD RES, STAMFORD SDNG, STANLEY DOWNS STATION, STAR DOWNS STATION, SUTTON DOWNS STATION, TANGORIN STATION, THORNVILLE STATION, TRURO STATION, WAVERLEY STATION, WEANBAH STATION, WINTON RD, WYOMING STATION",
        "SUBURBS": "CORFIELD, HUGHENDEN, MUTTABURRA, STAMFORD"
      }
    },
    {
      "type": "Feature",
      "geometry": {
        "type": "Point",
        "coordinates": [
          139.551552,
          -20.715318
        ]
      },
      "properties": {
        "EVENT_ID": "24NQ6423",
        "TYPE": "PLANNED",
        "CUSTOMERS_AFFECTED": "6",
        "REASON": "The loss of supply is to upgrade equipment to meet customer demand for electricity and to improve reliability of supply in the area",
        "STATUS": "Crews working on-site",
        "START": "8:03AM 10 Apr 2024",
        "EST_FIX_TIME": "5:00PM 10 Apr 2024",
        "STREETS": "BARKLY HWY",
        "SUBURBS": "MOUNT ISA"
      }
    }
  ],
  "company": "Ergon",
  "state": "Current",
  "extracted": "1712731201.238562"
}
