{
  "type": "FeatureCollection",
  "name": "PLANNED",
  "features": [
    {
      "type": "Feature",
      "geometry": {
        "type": "Point",
        "coordinates": [
          150.86067,
          -24.106237
        ]
      },
      "properties": {
        "EVENT_ID": "24CA3775",
        "TYPE": "PLANNED",
        "CUSTOMERS_AFFECTED": "60",
        "REASON": "The loss of supply is to replace power poles and improve the electricity network",
        "STATUS": "Crews working on-site",
        "START": "8:30AM 02 Apr 2024",
        "EST_FIX_TIME": "3:00PM 02 Apr 2024",
        "STREETS": "AYRDRIE RD, BLACKS RD, CATFISH RD, DAWSON HWY, DUCK HOLES RD, FIG TREE RD, GALLOWAY PLAINS RD, HARPER CREEK RD, INVERNESS RD, MT ALMA RD, ODGENS RD, POTTER RD, REDSHIRT RD, SPECIMEN HILL RD",
        "SUBURBS": "BILOELA, CALLIOPE, DUMGREE"
      }
    },
    {
      "type": "Feature",
      "geometry": {
        "type": "Point",
        "coordinates": [
          150.292984,
          -23.872013
        ]
      },
      "properties": {
        "EVENT_ID": "24CA4411",
        "TYPE": "PLANNED",
        "CUSTOMERS_AFFECTED": "11",
        "REASON": "The loss of supply is to replace power poles and improve the electricity network",
        "STATUS": "Crews working on-site",
        "START": "9:00AM 02 Apr 2024",
        "EST_FIX_TIME": "4:00PM 02 Apr 2024",
        "STREETS": "BUNERBA SCHOOL RD, BURNETT HWY, DULULU BUNERBA RD, JAMESONS LANE, OFF BURNETT HWY",
        "SUBURBS": "DULULU"
      }
    },
    {
      "type": "Feature",
      "geometry": {
        "type": "Point",
        "coordinates": [
          151.870083,
          -27.569297
        ]
      },
      "properties": {
        "EVENT_ID": "24SW6207",
        "TYPE": "PLANNED",
        "CUSTOMERS_AFFECTED": "73",
        "REASON": "The loss of supply is to upgrade equipment to meet customer demand for electricity and to improve reliability of supply in the area",
        "STATUS": "Crews working on-site",
        "START": "10:03AM 02 Apr 2024",
        "EST_FIX_TIME": "2:00PM 04 Apr 2024",
        "STREETS": "BARKLA RD, BOUNDARY ST, CAROLANN ST, CARYS RD, DEUBLE RD, DEVINE RD, DRAYTON WELLCAMP RD, E DREW RD, EUSTON RD, HARVEY RD, HURSLEY RD, LAURA CT, OESTREICH RD",
        "SUBURBS": "CRANLEY, GLENVALE, TOOWOOMBA, WELLCAMP"
      }
    },
    {
      "type": "Feature",
      "geometry": {
        "type": "Point",
        "coordinates": [
          152.679023,
          -25.52033
        ]
      },
      "properties": {
        "EVENT_ID": "24WB4153",
        "TYPE": "PLANNED",
        "CUSTOMERS_AFFECTED": "5",
        "REASON": "The loss of supply is to allow maintenance of the electricity network",
        "STATUS": "Crews working on-site",
        "START": "8:27AM 02 Apr 2024",
        "EST_FIX_TIME": "4:00PM 02 Apr 2024",
        "STREETS": "ALDRIDGE ST, KENT ST",
        "SUBURBS": "MARYBOROUGH"
      }
    }
  ],
  "company": "Ergon",
  "state": "Current",
  "extracted": "1712033701.451897"
}
