{
  "type": "FeatureCollection",
  "name": "PLANNED",
  "features": [
    {
      "type": "Feature",
      "geometry": {
        "type": "Point",
        "coordinates": [
          149.170241,
          -21.097701
        ]
      },
      "properties": {
        "EVENT_ID": "24MK2817",
        "TYPE": "PLANNED",
        "CUSTOMERS_AFFECTED": "79",
        "REASON": "The loss of supply is to allow maintenance of the electricity network",
        "STATUS": "Crews working on-site",
        "START": "9:11AM 04 Apr 2024",
        "EST_FIX_TIME": "5:30PM 04 Apr 2024",
        "STREETS": "AVOCADO CT, AZALEA CT, CASSIA ST, ILLAWARA CT, KURRAJONG CT, MANSFIELD DR, WARATAH ST",
        "SUBURBS": "BEACONSFIELD"
      }
    }
  ],
  "company": "Ergon",
  "state": "Current",
  "extracted": "1712215201.06636"
}
