{
  "type": "FeatureCollection",
  "name": "PLANNED",
  "features": [
    {
      "type": "Feature",
      "geometry": {
        "type": "Point",
        "coordinates": [
          150.574848,
          -23.724004
        ]
      },
      "properties": {
        "EVENT_ID": "24CA5921",
        "TYPE": "PLANNED",
        "CUSTOMERS_AFFECTED": "199",
        "REASON": "The loss of supply is to replace power poles and improve the electricity network",
        "STATUS": "Crews working on-site",
        "START": "3:30PM 10 May 2024",
        "EST_FIX_TIME": "5:30PM 10 May 2024",
        "STREETS": "BODERO RD, BRUCE HWY, BRUCE ST, BULL FROG LANE, BYCROFT RD, COWIE RD, GOODSALL RD, HIGH ST, JOHN ST, KIRK RD, MAGAZINE RD, MILL ST, MOUNT HOPEFUL RD, OFF BRUCE HWY, OLD COACH RD, PORT ALMA RD, RAILWAY RES, ROBERTS RD, SCHOOL ST, SIX MILE RD, SOUTH ULAM RD, SPRINGS RD, TOONDA RD, TOONDA ST, ULAM CONNECTION RD, UPPER ULAM RD",
        "SUBURBS": "BAJOOL"
      }
    },
    {
      "type": "Feature",
      "geometry": {
        "type": "Point",
        "coordinates": [
          148.840067,
          -21.008125
        ]
      },
      "properties": {
        "EVENT_ID": "24MK3563",
        "TYPE": "PLANNED",
        "CUSTOMERS_AFFECTED": "90",
        "REASON": "The loss of supply is to replace power poles and improve the electricity network",
        "STATUS": "Crews working on-site",
        "START": "8:30AM 10 May 2024",
        "EST_FIX_TIME": "3:30PM 10 May 2024",
        "STREETS": "BRUCE HWY, BUTHURRA STATION RD, FAIRCHILDS RD, GEEBERGA BUTHURRA RD, GIFFORDS RD, MCKAYS RD, MCLEANS RD, NARPI RD, PACES RD, STARKEYS RD, WATTS RD",
        "SUBURBS": "BUTHURRA, KUTTABUL, MACKAY, MOUNT CHARLTON, MOUNT OSSA"
      }
    },
    {
      "type": "Feature",
      "geometry": {
        "type": "Point",
        "coordinates": [
          146.331519,
          -18.526706
        ]
      },
      "properties": {
        "EVENT_ID": "24NQ7260",
        "TYPE": "PLANNED",
        "CUSTOMERS_AFFECTED": "4",
        "REASON": "The loss of supply is to connect new customers to the electricity network",
        "STATUS": "Crews working on-site",
        "START": "7:42AM 07 May 2024",
        "EST_FIX_TIME": "3:30PM 14 May 2024",
        "STREETS": "DUNGENESS RD, KEAST ST",
        "SUBURBS": "LUCINDA"
      }
    },
    {
      "type": "Feature",
      "geometry": {
        "type": "Point",
        "coordinates": [
          147.41197,
          -19.593087
        ]
      },
      "properties": {
        "EVENT_ID": "24NQ7949",
        "TYPE": "PLANNED",
        "CUSTOMERS_AFFECTED": "3",
        "REASON": "The loss of supply is to allow emergency maintenance of the electricity network",
        "STATUS": "Crews working on-site",
        "START": "9:16AM 10 May 2024",
        "EST_FIX_TIME": "4:00PM 10 May 2024",
        "STREETS": "KILRIE RD",
        "SUBURBS": "AYR"
      }
    }
  ],
  "company": "Ergon",
  "state": "Current",
  "extracted": "1715319600.448404"
}
