{
  "type": "FeatureCollection",
  "name": "PLANNED",
  "features": [
    {
      "type": "Feature",
      "geometry": {
        "type": "Point",
        "coordinates": [
          145.600449,
          -16.907916
        ]
      },
      "properties": {
        "EVENT_ID": "24FN6367",
        "TYPE": "PLANNED",
        "CUSTOMERS_AFFECTED": "24",
        "REASON": "The loss of supply is to allow maintenance of the electricity network",
        "STATUS": "Crews working on-site",
        "START": "8:31AM 09 Jun 2024",
        "EST_FIX_TIME": "5:30PM 09 Jun 2024",
        "STREETS": "CEDAR PARK RD, FOREST CL, GANYAN DR",
        "SUBURBS": "CLOHESY RIVER, SPEEWAH"
      }
    },
    {
      "type": "Feature",
      "geometry": {
        "type": "Point",
        "coordinates": [
          149.156219,
          -21.172204
        ]
      },
      "properties": {
        "EVENT_ID": "24MK4527",
        "TYPE": "PLANNED",
        "CUSTOMERS_AFFECTED": "3",
        "REASON": "The loss of supply is to allow maintenance of the electricity network",
        "STATUS": "Crews working on-site",
        "START": "8:00AM 09 Jun 2024",
        "EST_FIX_TIME": "5:00PM 09 Jun 2024",
        "STREETS": "MAGGIOLO DR",
        "SUBURBS": "PAGET"
      }
    },
    {
      "type": "Feature",
      "geometry": {
        "type": "Point",
        "coordinates": [
          151.93011,
          -27.562697
        ]
      },
      "properties": {
        "EVENT_ID": "24SW9234",
        "TYPE": "PLANNED",
        "CUSTOMERS_AFFECTED": "7",
        "REASON": "The loss of supply is to upgrade equipment to meet customer demand for electricity and to improve reliability of supply in the area",
        "STATUS": "Crews working on-site",
        "START": "8:30AM 09 Jun 2024",
        "EST_FIX_TIME": "4:30PM 09 Jun 2024",
        "STREETS": "ANZAC AVE, HURSLEY RD",
        "SUBURBS": "NEWTOWN"
      }
    }
  ],
  "company": "Ergon",
  "state": "Current",
  "extracted": "1717916100.980132"
}
