{
  "type": "FeatureCollection",
  "name": "PLANNED",
  "features": [
    {
      "type": "Feature",
      "geometry": {
        "type": "Point",
        "coordinates": [
          151.957085,
          -27.560581
        ]
      },
      "properties": {
        "EVENT_ID": "24SW7992",
        "TYPE": "PLANNED",
        "CUSTOMERS_AFFECTED": "3",
        "REASON": "The loss of supply is to upgrade equipment to meet customer demand for electricity and to improve reliability of supply in the area",
        "STATUS": "Work scheduled",
        "START": "8:30PM 22 Apr 2024",
        "EST_FIX_TIME": "1:30AM 23 Apr 2024",
        "STREETS": "BELL ST",
        "SUBURBS": "TOOWOOMBA, TOOWOOMBA CITY"
      }
    }
  ],
  "company": "Ergon",
  "state": "Current",
  "extracted": "1713779102.766386"
}
