{
  "type": "FeatureCollection",
  "name": "PLANNED",
  "features": [
    {
      "type": "Feature",
      "geometry": {
        "type": "Point",
        "coordinates": [
          146.036406,
          -17.52165
        ]
      },
      "properties": {
        "EVENT_ID": "24FN7043",
        "TYPE": "PLANNED",
        "CUSTOMERS_AFFECTED": "3",
        "REASON": "The loss of supply is to replace power poles and improve the electricity network",
        "STATUS": "Crews working on-site",
        "START": "7:50AM 21 Jun 2024",
        "EST_FIX_TIME": "4:30PM 21 Jun 2024",
        "STREETS": "TIERNEY ST",
        "SUBURBS": "INNISFAIL ESTATE"
      }
    },
    {
      "type": "Feature",
      "geometry": {
        "type": "Point",
        "coordinates": [
          145.06569,
          -20.068646
        ]
      },
      "properties": {
        "EVENT_ID": "24NQ8670",
        "TYPE": "PLANNED",
        "CUSTOMERS_AFFECTED": "188",
        "REASON": "The loss of supply is to allow maintenance of the electricity network",
        "STATUS": "Work scheduled",
        "START": "4:30PM 21 Jun 2024",
        "EST_FIX_TIME": "4:40PM 21 Jun 2024",
        "STREETS": "AMARINA PARK STATION, AMARRA STATION, AMESS ST, BAHR RD, BALLABAY STATION, BROOKDALE STATION, CAPE RD, CAPEVILLE STATION, CARGOON STATION, CLAYHOLE STATION, CORNELIA STATION, CREEK ST, CUBA PLAINS STATION, ELLENVALE STATION, FELSPAR STATION, FLINDERS HWY, GILMORE ST, GLENCOE STATION, GOLDSBOROUGH STATION, GREGORY SPRINGS RD, GRENFELL DOWNS STATION, JESSIE SPRINGS RD, JUNCTION CREEK STATION, LOLWORTH STATION, LOW HOLM STATION, MACKAY ST, MAIN ST, MCARTHUR ST, MELVIN ST, MILL ST, MILRAY RD, MOUNT STEWART STATION, NEWBURGH STATION, NULLA NULLA STATION, OAKVALE STATION, OLD CAPE RD, PAN ST, PATERSON ST, PEAGHAM ST, PERRONE STATION, PILCHER RD, REEDY SPRINGS STATION, SPRINGFERN STATION, TALAVERA STATION, TAYLOR ST, THE BROOK STATION, TWELVE MILE RD, URALLA STATION, WANDOVALE RD, WILUNA STATION",
        "SUBURBS": "BALFES CREEK, BASALT, GREENVALE, PENTLAND"
      }
    },
    {
      "type": "Feature",
      "geometry": {
        "type": "Point",
        "coordinates": [
          145.565666,
          -20.550714
        ]
      },
      "properties": {
        "EVENT_ID": "24NQ8671",
        "TYPE": "PLANNED",
        "CUSTOMERS_AFFECTED": "76",
        "REASON": "The loss of supply is to allow maintenance of the electricity network",
        "STATUS": "Work scheduled",
        "START": "4:30PM 21 Jun 2024",
        "EST_FIX_TIME": "4:40PM 21 Jun 2024",
        "STREETS": "ALLAN HILLS STATION, ALLANDALE STATION, BACK ST, CREEK ST, ESPLANADE ST, ESTLAND RD, FLINDERS HWY, GLEN HOUGHTON RD, GLEN HOUGHTON STATION, HELENSLEE STATION, HOME ST, IBIS DR, LAUDERDALE STATION, MILRAY RD, MILRAY STATION, RAILWAY ST, RED RD, RIVERVIEW STATION, STONINGTON STATION",
        "SUBURBS": "HOMESTEAD, PENTLAND"
      }
    },
    {
      "type": "Feature",
      "geometry": {
        "type": "Point",
        "coordinates": [
          147.426467,
          -19.665664
        ]
      },
      "properties": {
        "EVENT_ID": "24NQ9254",
        "TYPE": "PLANNED",
        "CUSTOMERS_AFFECTED": "7",
        "REASON": "The loss of supply is to replace power poles and improve the electricity network",
        "STATUS": "Crews working on-site",
        "START": "7:28AM 21 Jun 2024",
        "EST_FIX_TIME": "4:30PM 21 Jun 2024",
        "STREETS": "FIFTEENTH AVE, FIRST ST, SEVENTEENTH AVE",
        "SUBURBS": "HOME HILL"
      }
    }
  ],
  "company": "Ergon",
  "state": "Current",
  "extracted": "1718949301.444051"
}
