{
  "type": "FeatureCollection",
  "name": "PLANNED",
  "features": [
    {
      "type": "Feature",
      "geometry": {
        "type": "Point",
        "coordinates": [
          150.745544,
          -23.138645
        ]
      },
      "properties": {
        "EVENT_ID": "24CA3693",
        "TYPE": "PLANNED",
        "CUSTOMERS_AFFECTED": "2",
        "REASON": "The loss of supply is to allow maintenance of the electricity network",
        "STATUS": "Work scheduled",
        "START": "1:00PM 13 Mar 2024",
        "EST_FIX_TIME": "5:00PM 13 Mar 2024",
        "STREETS": "PFAFF ST",
        "SUBURBS": "YEPPOON"
      }
    },
    {
      "type": "Feature",
      "geometry": {
        "type": "Point",
        "coordinates": [
          145.083294,
          -15.298852
        ]
      },
      "properties": {
        "EVENT_ID": "24FN2741",
        "TYPE": "PLANNED",
        "CUSTOMERS_AFFECTED": "2",
        "REASON": "The loss of supply is to replace power poles and improve the electricity network",
        "STATUS": "Work scheduled",
        "START": "1:00PM 13 Mar 2024",
        "EST_FIX_TIME": "3:00PM 13 Mar 2024",
        "STREETS": "HOPE VALE RD",
        "SUBURBS": "HOPE VALE"
      }
    },
    {
      "type": "Feature",
      "geometry": {
        "type": "Point",
        "coordinates": [
          151.957085,
          -27.560581
        ]
      },
      "properties": {
        "EVENT_ID": "24SW5250",
        "TYPE": "PLANNED",
        "CUSTOMERS_AFFECTED": "2",
        "REASON": "The loss of supply is to upgrade equipment to meet customer demand for electricity and to improve reliability of supply in the area",
        "STATUS": "Work scheduled",
        "START": "9:00PM 13 Mar 2024",
        "EST_FIX_TIME": "4:00AM 14 Mar 2024",
        "STREETS": "BELL ST",
        "SUBURBS": "TOOWOOMBA, TOOWOOMBA CITY"
      }
    }
  ],
  "company": "Ergon",
  "state": "Current",
  "extracted": "1710295207.44854"
}
