{
  "type": "FeatureCollection",
  "name": "PLANNED",
  "features": [
    {
      "type": "Feature",
      "geometry": {
        "type": "Point",
        "coordinates": [
          151.244446,
          -23.838221
        ]
      },
      "properties": {
        "EVENT_ID": "25CA3468",
        "TYPE": "PLANNED",
        "CUSTOMERS_AFFECTED": "50",
        "REASON": "The loss of supply is to replace power poles and improve the electricity network",
        "STATUS": "Crews working on-site",
        "START": "8:00AM 09 Mar 2025",
        "EST_FIX_TIME": "3:30PM 09 Mar 2025",
        "STREETS": "DREWE ST, HANSON RD, MORGAN ST, ROOKSBY ST, TRANBERG ST",
        "SUBURBS": "GLADSTONE, GLADSTONE CENTRAL"
      }
    },
    {
      "type": "Feature",
      "geometry": {
        "type": "Point",
        "coordinates": [
          151.246111,
          -23.8399
        ]
      },
      "properties": {
        "EVENT_ID": "25CA4018",
        "TYPE": "PLANNED",
        "CUSTOMERS_AFFECTED": "20",
        "REASON": "The loss of supply is to replace power poles and improve the electricity network",
        "STATUS": "Crews working on-site",
        "START": "8:03AM 09 Mar 2025",
        "EST_FIX_TIME": "3:30PM 09 Mar 2025",
        "STREETS": "DREWE ST, HANSON RD, KINGDON ST",
        "SUBURBS": "GLADSTONE, GLADSTONE CENTRAL"
      }
    },
    {
      "type": "Feature",
      "geometry": {
        "type": "Point",
        "coordinates": [
          150.627224,
          -26.748006
        ]
      },
      "properties": {
        "EVENT_ID": "25SW3525",
        "TYPE": "PLANNED",
        "CUSTOMERS_AFFECTED": "76",
        "REASON": "The loss of supply is to allow emergency maintenance of the electricity network",
        "STATUS": "Crews working on-site",
        "START": "8:30AM 09 Mar 2025",
        "EST_FIX_TIME": "3:00PM 09 Mar 2025",
        "STREETS": "ATKINS ST, EVANS ST, FRASER ST, GLASSON ST, HYPATIA ST, TURNER ST, WHEELER ST, WINDMILL RD, WOOD ST",
        "SUBURBS": "CHINCHILLA"
      }
    },
    {
      "type": "Feature",
      "geometry": {
        "type": "Point",
        "coordinates": [
          150.627442,
          -26.750771
        ]
      },
      "properties": {
        "EVENT_ID": "25SW3535",
        "TYPE": "PLANNED",
        "CUSTOMERS_AFFECTED": "47",
        "REASON": "The loss of supply is to allow emergency maintenance of the electricity network",
        "STATUS": "Crews working on-site",
        "START": "8:30AM 09 Mar 2025",
        "EST_FIX_TIME": "2:30PM 09 Mar 2025",
        "STREETS": "ATKINS ST, DICKMAN ST, EVANS ST, WINDMILL RD, ZELLER ST",
        "SUBURBS": "CHINCHILLA"
      }
    }
  ],
  "company": "Ergon",
  "state": "Current",
  "extracted": "1741495201.694499"
}
