{
  "type": "FeatureCollection",
  "name": "PLANNED",
  "features": [
    {
      "type": "Feature",
      "geometry": {
        "type": "Point",
        "coordinates": [
          152.18073,
          -25.330587
        ]
      },
      "properties": {
        "EVENT_ID": "24WB5836",
        "TYPE": "PLANNED",
        "CUSTOMERS_AFFECTED": "64",
        "REASON": "The loss of supply is to upgrade equipment to meet customer demand for electricity and to improve reliability of supply in the area",
        "STATUS": "Crews working on-site",
        "START": "9:01AM 18 Jun 2024",
        "EST_FIX_TIME": "5:30PM 18 Jun 2024",
        "STREETS": "AGNESVALE RD, BERRIES RD, BIGGENDEN RD, EUREKA RD, FAINTS RD, ISIS HWY, NORTH SOUTH RD, RENDALLS RD, SAWMILL RD",
        "SUBURBS": "APPLE TREE CREEK, CHILDERS, EUREKA, GOLDEN FLEECE, ISIS CENTRAL, KULLOGUM"
      }
    },
    {
      "type": "Feature",
      "geometry": {
        "type": "Point",
        "coordinates": [
          152.144261,
          -25.292038
        ]
      },
      "properties": {
        "EVENT_ID": "24WB5837",
        "TYPE": "PLANNED",
        "CUSTOMERS_AFFECTED": "19",
        "REASON": "The loss of supply is to upgrade equipment to meet customer demand for electricity and to improve reliability of supply in the area",
        "STATUS": "Crews working on-site",
        "START": "1:32PM 18 Jun 2024",
        "EST_FIX_TIME": "5:30PM 18 Jun 2024",
        "STREETS": "EUREKA STATION RD, GUPPYS RD, RENDALLS RD",
        "SUBURBS": "EUREKA"
      }
    }
  ],
  "company": "Ergon",
  "state": "Current",
  "extracted": "1718695501.448828"
}
