{
  "type": "FeatureCollection",
  "name": "PLANNED",
  "features": [
    {
      "type": "Feature",
      "geometry": {
        "type": "Point",
        "coordinates": [
          145.92643,
          -17.34375
        ]
      },
      "properties": {
        "EVENT_ID": "24FN5540",
        "TYPE": "PLANNED",
        "CUSTOMERS_AFFECTED": "10",
        "REASON": "The loss of supply is to replace power poles and improve the electricity network",
        "STATUS": "Crews working on-site",
        "START": "1:52PM 15 May 2024",
        "EST_FIX_TIME": "4:30PM 15 May 2024",
        "STREETS": "COUNCIL LANE, PEEVER RD",
        "SUBURBS": "BABINDA"
      }
    },
    {
      "type": "Feature",
      "geometry": {
        "type": "Point",
        "coordinates": [
          148.993997,
          -20.908813
        ]
      },
      "properties": {
        "EVENT_ID": "24MK3729",
        "TYPE": "PLANNED",
        "CUSTOMERS_AFFECTED": "342",
        "REASON": "The loss of supply is to allow maintenance of the electricity network",
        "STATUS": "Crews working on-site",
        "START": "7:30AM 15 May 2024",
        "EST_FIX_TIME": "4:30PM 15 May 2024",
        "STREETS": "ADAMSON ST, BALL BAY RD, BLUE BEACH BVD, BUORO ST, CAPE HILLSBOROUGH RD, COCONUT GR, EVERETT ST, GELA RD, HALIDAY BAY RD, HEADLAND DR, KIPPEN DR, MASON ST, MILKINS ST, OLIVER ST, SIVYER ST, SMITH ST, STURGEON ST, WARD ESP",
        "SUBURBS": "BALL BAY, HALIDAY BAY"
      }
    },
    {
      "type": "Feature",
      "geometry": {
        "type": "Point",
        "coordinates": [
          149.295402,
          -21.63291
        ]
      },
      "properties": {
        "EVENT_ID": "24MK3814",
        "TYPE": "PLANNED",
        "CUSTOMERS_AFFECTED": "4",
        "REASON": "The loss of supply is to replace power poles and improve the electricity network",
        "STATUS": "Crews working on-site",
        "START": "9:05AM 15 May 2024",
        "EST_FIX_TIME": "4:30PM 15 May 2024",
        "STREETS": "ROCKY DAM RD, SMART RD",
        "SUBURBS": "KOUMALA, MOUNT CHRISTIAN"
      }
    },
    {
      "type": "Feature",
      "geometry": {
        "type": "Point",
        "coordinates": [
          146.331519,
          -18.526706
        ]
      },
      "properties": {
        "EVENT_ID": "24NQ7260",
        "TYPE": "PLANNED",
        "CUSTOMERS_AFFECTED": "4",
        "REASON": "The loss of supply is to connect new customers to the electricity network",
        "STATUS": "Crews working on-site",
        "START": "7:42AM 07 May 2024",
        "EST_FIX_TIME": "3:30PM 17 May 2024",
        "STREETS": "DUNGENESS RD, KEAST ST",
        "SUBURBS": "LUCINDA"
      }
    }
  ],
  "company": "Ergon",
  "state": "Current",
  "extracted": "1715754001.206986"
}
