{
  "type": "FeatureCollection",
  "name": "PLANNED",
  "features": [
    {
      "type": "Feature",
      "geometry": {
        "type": "Point",
        "coordinates": [
          148.770746,
          -21.143954
        ]
      },
      "properties": {
        "EVENT_ID": "25MK0392",
        "TYPE": "PLANNED",
        "CUSTOMERS_AFFECTED": "26",
        "REASON": "The loss of supply is to connect new customers to the electricity network",
        "STATUS": "Crews working on-site",
        "START": "8:30AM 07 Mar 2025",
        "EST_FIX_TIME": "3:30PM 07 Mar 2025",
        "STREETS": "CAPPELLOS RD, DUNWOLD LUMBURRA RD, GARGETT DUMP RD, MACKAY EUNGELLA RD, OWENS CREEK RD",
        "SUBURBS": "GARGETT, OWENS CREEK"
      }
    },
    {
      "type": "Feature",
      "geometry": {
        "type": "Point",
        "coordinates": [
          149.137121,
          -21.269474
        ]
      },
      "properties": {
        "EVENT_ID": "25MK2041",
        "TYPE": "PLANNED",
        "CUSTOMERS_AFFECTED": "7",
        "REASON": "The loss of supply is to remove vegetation growing near powerlines",
        "STATUS": "Crews working on-site",
        "START": "10:00AM 07 Mar 2025",
        "EST_FIX_TIME": "3:30PM 07 Mar 2025",
        "STREETS": "BRUCE HWY, MARWOOD SUNNYSIDE RD",
        "SUBURBS": "CHELONA, MACKAY"
      }
    }
  ],
  "company": "Ergon",
  "state": "Current",
  "extracted": "1741324504.307237"
}
