{
  "type": "FeatureCollection",
  "name": "PLANNED",
  "features": [
    {
      "type": "Feature",
      "geometry": {
        "type": "Point",
        "coordinates": [
          146.331519,
          -18.526706
        ]
      },
      "properties": {
        "EVENT_ID": "24NQ5670",
        "TYPE": "PLANNED",
        "CUSTOMERS_AFFECTED": "4",
        "REASON": "The loss of supply is to allow maintenance of the electricity network",
        "STATUS": "Crews working on-site",
        "START": "9:00AM 15 Apr 2024",
        "EST_FIX_TIME": "3:00PM 19 Apr 2024",
        "STREETS": "DUNGENESS RD, KEAST ST",
        "SUBURBS": "LUCINDA"
      }
    },
    {
      "type": "Feature",
      "geometry": {
        "type": "Point",
        "coordinates": [
          146.959863,
          -19.391392
        ]
      },
      "properties": {
        "EVENT_ID": "24NQ5789",
        "TYPE": "PLANNED",
        "CUSTOMERS_AFFECTED": "2",
        "REASON": "The loss of supply is to connect new customers to the electricity network",
        "STATUS": "Crews working on-site",
        "START": "8:30AM 16 Apr 2024",
        "EST_FIX_TIME": "5:30PM 16 Apr 2024",
        "STREETS": "WILLIAMS RD",
        "SUBURBS": "ALLIGATOR CREEK"
      }
    },
    {
      "type": "Feature",
      "geometry": {
        "type": "Point",
        "coordinates": [
          147.406308,
          -19.574162
        ]
      },
      "properties": {
        "EVENT_ID": "24NQ6638",
        "TYPE": "PLANNED",
        "CUSTOMERS_AFFECTED": "19",
        "REASON": "The loss of supply is to allow maintenance of the electricity network",
        "STATUS": "Work scheduled",
        "START": "11:00PM 16 Apr 2024",
        "EST_FIX_TIME": "4:00AM 17 Apr 2024",
        "STREETS": "EDWARDS ST, QUEEN ST",
        "SUBURBS": "AYR"
      }
    },
    {
      "type": "Feature",
      "geometry": {
        "type": "Point",
        "coordinates": [
          150.755361,
          -25.298666
        ]
      },
      "properties": {
        "EVENT_ID": "24WB4339",
        "TYPE": "PLANNED",
        "CUSTOMERS_AFFECTED": "86",
        "REASON": "The loss of supply is to upgrade equipment to meet customer demand for electricity and to improve reliability of supply in the area",
        "STATUS": "Crews working on-site",
        "START": "9:30AM 16 Apr 2024",
        "EST_FIX_TIME": "5:30PM 16 Apr 2024",
        "STREETS": "BARRAM RD, CALROSSIE RD, CHELTENHAM RD, COONAMBULA RD, DAREEN RD, EIDSVOLD THEODORE RD, EIDSVOLD-CRACOW RD, GLENCOE RD, MONTO RD, OAK PARK RD, OAKEY CREEK RD, OLD RAWBELLE RD, RAWBELLE RD, REDBANK RD, REDMOUNT RD, ROCKYBAR RD, SLOSS RD, SPRING GLY, ST JOHNS-GOLDFIELD RD, TELEMARK RD, TIREEN RD, TOLO RD, WATHONGA RD",
        "SUBURBS": "COONAMBULA, EIDSVOLD, EIDSVOLD WEST"
      }
    }
  ],
  "company": "Ergon",
  "state": "Current",
  "extracted": "1713250501.212684"
}
