{
  "type": "FeatureCollection",
  "name": "PLANNED",
  "features": [
    {
      "type": "Feature",
      "geometry": {
        "type": "Point",
        "coordinates": [
          150.745343,
          -23.112349
        ]
      },
      "properties": {
        "EVENT_ID": "24CA5340",
        "TYPE": "PLANNED",
        "CUSTOMERS_AFFECTED": "2",
        "REASON": "The loss of supply is to replace power poles and improve the electricity network",
        "STATUS": "Crews working on-site",
        "START": "1:57PM 26 Apr 2024",
        "EST_FIX_TIME": "4:30PM 26 Apr 2024",
        "STREETS": "GREER ST",
        "SUBURBS": "MEIKLEVILLE HILL"
      }
    },
    {
      "type": "Feature",
      "geometry": {
        "type": "Point",
        "coordinates": [
          149.959768,
          -24.719652
        ]
      },
      "properties": {
        "EVENT_ID": "24CA5504",
        "TYPE": "PLANNED",
        "CUSTOMERS_AFFECTED": "44",
        "REASON": "The loss of supply is to connect new customers to the electricity network",
        "STATUS": "Crews working on-site",
        "START": "8:30AM 26 Apr 2024",
        "EST_FIX_TIME": "3:30PM 26 Apr 2024",
        "STREETS": "BECKERS RD, BEHRENDORFFS RD, BURNSIDE-MCLELLANS RD, DAWSON HWY, KIANGA RIVER RD, MALONEYS RD, NIPAN-RIVER RD, RIVER RD, THEODORE BARALABA RD, THEODORE MOURA RD",
        "SUBURBS": "KIANGA, MOURA, THEODORE"
      }
    },
    {
      "type": "Feature",
      "geometry": {
        "type": "Point",
        "coordinates": [
          148.822647,
          -21.091816
        ]
      },
      "properties": {
        "EVENT_ID": "24MK3411",
        "TYPE": "PLANNED",
        "CUSTOMERS_AFFECTED": "80",
        "REASON": "The loss of supply is to allow maintenance of the electricity network",
        "STATUS": "Crews working on-site",
        "START": "9:00AM 26 Apr 2024",
        "EST_FIX_TIME": "4:00PM 26 Apr 2024",
        "STREETS": "BRADSHAWS RD, COYNES RD, GARNHAM MORROWS RD, GEEBERGA BUTHURRA RD, MCFAULS RD, MORRIS RD, MOUNT MARTIN GAP RD, MOUNT MARTIN LOOP RD, MOUNT MARTIN RD, MOUNT TOBY RD, SUGARLOAF RD",
        "SUBURBS": "KUTTABUL, MOUNT MARTIN"
      }
    },
    {
      "type": "Feature",
      "geometry": {
        "type": "Point",
        "coordinates": [
          146.789271,
          -19.25912
        ]
      },
      "properties": {
        "EVENT_ID": "24NQ6745",
        "TYPE": "PLANNED",
        "CUSTOMERS_AFFECTED": "2",
        "REASON": "The loss of supply is to replace power poles and improve the electricity network",
        "STATUS": "Crews working on-site",
        "START": "11:56AM 26 Apr 2024",
        "EST_FIX_TIME": "4:00PM 26 Apr 2024",
        "STREETS": "HAROLD ST",
        "SUBURBS": "WEST END"
      }
    }
  ],
  "company": "Ergon",
  "state": "Current",
  "extracted": "1714108201.072678"
}
