{
  "type": "FeatureCollection",
  "name": "PLANNED",
  "features": [
    {
      "type": "Feature",
      "geometry": {
        "type": "Point",
        "coordinates": [
          152.717467,
          -25.54245
        ]
      },
      "properties": {
        "EVENT_ID": "24WB4865",
        "TYPE": "PLANNED",
        "CUSTOMERS_AFFECTED": "17",
        "REASON": "The loss of supply is to allow maintenance of the electricity network",
        "STATUS": "Crews working on-site",
        "START": "7:05AM 01 May 2024",
        "EST_FIX_TIME": "6:00PM 01 May 2024",
        "STREETS": "DUNDAS ST, MAY ST, MIRAMONT ST",
        "SUBURBS": "GRANVILLE"
      }
    },
    {
      "type": "Feature",
      "geometry": {
        "type": "Point",
        "coordinates": [
          152.721514,
          -25.546403
        ]
      },
      "properties": {
        "EVENT_ID": "24WB4870",
        "TYPE": "PLANNED",
        "CUSTOMERS_AFFECTED": "5",
        "REASON": "The loss of supply is to allow maintenance of the electricity network",
        "STATUS": "Crews working on-site",
        "START": "7:04AM 01 May 2024",
        "EST_FIX_TIME": "6:00PM 01 May 2024",
        "STREETS": "HOFFMAN ST, PULLER ST",
        "SUBURBS": "GRANVILLE"
      }
    }
  ],
  "company": "Ergon",
  "state": "Current",
  "extracted": "1714549801.072405"
}
