{
  "type": "FeatureCollection",
  "name": "PLANNED",
  "features": [
    {
      "type": "Feature",
      "geometry": {
        "type": "Point",
        "coordinates": [
          150.637939,
          -23.652163
        ]
      },
      "properties": {
        "EVENT_ID": "24CA5222",
        "TYPE": "PLANNED",
        "CUSTOMERS_AFFECTED": "53",
        "REASON": "The loss of supply is to replace power poles and improve the electricity network",
        "STATUS": "Crews working on-site",
        "START": "5:56PM 27 Apr 2024",
        "EST_FIX_TIME": "6:56PM 27 Apr 2024",
        "STREETS": "BRUCE HWY, BRUCE ST, HIGH ST, JOHN ST, MAGAZINE RD, MILL ST, OFF BRUCE HWY, RAILWAY RES, SIX MILE RD, SOUTH ULAM RD",
        "SUBURBS": "BAJOOL"
      }
    },
    {
      "type": "Feature",
      "geometry": {
        "type": "Point",
        "coordinates": [
          142.75018,
          -20.469853
        ]
      },
      "properties": {
        "EVENT_ID": "24NQ6414",
        "TYPE": "PLANNED",
        "CUSTOMERS_AFFECTED": "4",
        "REASON": "The loss of supply is to replace power poles and improve the electricity network",
        "STATUS": "Crews working on-site",
        "START": "8:30AM 27 Apr 2024",
        "EST_FIX_TIME": "6:00PM 27 Apr 2024",
        "STREETS": "ARTESIAN DOWNS STATION, GRACEDALE STATION, LILYVALE STATION, MORUNGLE STATION",
        "SUBURBS": "MAXWELTON"
      }
    }
  ],
  "company": "Ergon",
  "state": "Current",
  "extracted": "1714205101.281147"
}
