{
  "type": "FeatureCollection",
  "name": "PLANNED",
  "features": [
    {
      "type": "Feature",
      "geometry": {
        "type": "Point",
        "coordinates": [
          150.586776,
          -23.724004
        ]
      },
      "properties": {
        "EVENT_ID": "24CA4551",
        "TYPE": "PLANNED",
        "CUSTOMERS_AFFECTED": "175",
        "REASON": "The loss of supply is to replace power poles and improve the electricity network",
        "STATUS": "Crews working on-site",
        "START": "8:30AM 14 Apr 2024",
        "EST_FIX_TIME": "4:30PM 14 Apr 2024",
        "STREETS": "BODERO RD, BRUCE HWY, BULL FROG LANE, BYCROFT RD, COWIE RD, GOODSALL RD, HIGH ST, KIRK RD, MAGAZINE RD, MILL ST, MOUNT HOPEFUL RD, OFF BRUCE HWY, OLD COACH RD, PORT ALMA RD, ROBERTS RD, SCHOOL ST, SISALANA RD, SIX MILE RD, SOUTH ULAM RD, SPRINGS RD, TOONDA RD, TOONDA ST, ULAM CONNECTION RD, UPPER ULAM RD",
        "SUBURBS": "BAJOOL, MARMOR"
      }
    },
    {
      "type": "Feature",
      "geometry": {
        "type": "Point",
        "coordinates": [
          148.238127,
          -20.003016
        ]
      },
      "properties": {
        "EVENT_ID": "24NQ6474",
        "TYPE": "PLANNED",
        "CUSTOMERS_AFFECTED": "190",
        "REASON": "The loss of supply is to allow maintenance of the electricity network",
        "STATUS": "Crews working on-site",
        "START": "9:30AM 14 Apr 2024",
        "EST_FIX_TIME": "4:30PM 14 Apr 2024",
        "STREETS": "ALLAN PL, BANKSIA ST, BOWEN HILL, CARLETON ST, DANIEL ST, DARWEN ST, GREGORY ST, HERBERT ST, MCDOUGAL ST, PHILIP ST, RICHMOND RD, SALISBURY CRES, SCOTT ST, TYNWALD AVE",
        "SUBURBS": "BOWEN"
      }
    },
    {
      "type": "Feature",
      "geometry": {
        "type": "Point",
        "coordinates": [
          152.483862,
          -25.151949
        ]
      },
      "properties": {
        "EVENT_ID": "24WB4049",
        "TYPE": "PLANNED",
        "CUSTOMERS_AFFECTED": "948",
        "REASON": "The loss of supply is to upgrade equipment to meet customer demand for electricity and to improve reliability of supply in the area",
        "STATUS": "Work scheduled",
        "START": "5:00PM 14 Apr 2024",
        "EST_FIX_TIME": "5:30PM 14 Apr 2024",
        "STREETS": "ACACIA ST, BLACKS RD, BROADLANDS RD, BROLGA CL, BURRUM ST, BURRUMBA DR, BUXTON RD, CHARLTON ST, CORAL SEA DR, CURLEW ST, CYPRESS ST, DARVILLE RD, DEVILS ELBOW RD, DOLPHIN CT, DOUGLAS DR, DRAPERS DR, DUGONG CT, EAGLE RD, EMU CT, ESPLANADE, FIRST AVE, FRIZZELLS RD, GREEN CT, GREGORY ST, HAKEA ST, HENRY CT, HOMANN ST, HONEYEATER CT, HOWARD ST, HULL ST, HUME ST, IRENE RATCLIFFE DR, ISIS JUNCTION RD, ISIS ST, JABIRU CT, JARRETTS RD, KINKUNA DR, KOOKABURRA WAY, LAGOON CT, LORIKEET AVE, MOLLER ST, OCEAN VIEW DR, OLD WOODGATE RD, ORIOLE CT, OSPREY DR, OYSTERCATCHER ST, PALM CT, PANDANUS CT, PAPERBARK CT, PELICAN WAY, PIONEER RD, POWERS ST, RIVER DR, RIVER RD, ROSELLA WAY, SCHOONER CT, SECOND AVE, SMITH ST, STELEY ST, SUNDEW CT, SUNSET AVE, THE ESPLANADE, THEODOLITE CREEK DR, TRAVIS ST, WALLUM ST, WATKINS ST, WHALE CT, WHARF ST, WHIPBIRD CT, WOODGATE RD",
        "SUBURBS": "BUXTON, CHILDERS, GOODWOOD, ISIS RIVER, WOODGATE, WOODGATE BEACH"
      }
    }
  ],
  "company": "Ergon",
  "state": "Current",
  "extracted": "1713076501.12227"
}
