{
  "type": "FeatureCollection",
  "name": "PLANNED",
  "features": [
    {
      "type": "Feature",
      "geometry": {
        "type": "Point",
        "coordinates": [
          145.748428,
          -16.914592
        ]
      },
      "properties": {
        "EVENT_ID": "24FN4359",
        "TYPE": "PLANNED",
        "CUSTOMERS_AFFECTED": "2",
        "REASON": "The loss of supply is to allow maintenance of the electricity network",
        "STATUS": "Crews working on-site",
        "START": "6:41AM 10 Apr 2024",
        "EST_FIX_TIME": "7:30AM 11 Apr 2024",
        "STREETS": "ANDERSON ST",
        "SUBURBS": "MANUNDA"
      }
    }
  ],
  "company": "Ergon",
  "state": "Current",
  "extracted": "1712741101.85777"
}
