{
  "type": "FeatureCollection",
  "name": "PLANNED",
  "features": [
    {
      "type": "Feature",
      "geometry": {
        "type": "Point",
        "coordinates": [
          149.281379,
          -21.678019
        ]
      },
      "properties": {
        "EVENT_ID": "24MK2457",
        "TYPE": "PLANNED",
        "CUSTOMERS_AFFECTED": "151",
        "REASON": "The loss of supply is to replace power poles and improve the electricity network",
        "STATUS": "Crews working on-site",
        "START": "9:00AM 23 Mar 2024",
        "EST_FIX_TIME": "5:30PM 23 Mar 2024",
        "STREETS": "BRUCE HWY, CAMPBELLS RD, CRAIG RD, HARRIS RD, HATFIELD RD, PRICE RD, R WILLIAMS RD, RAND RD, ROCKY DAM RD, SANGIORGIO RD, SMART RD, TEDLANDS RD, THOMPSON RD, TURNORS PADDOCK RD, WOOD RD",
        "SUBURBS": "KOUMALA, MOUNT CHRISTIAN"
      }
    }
  ],
  "company": "Ergon",
  "state": "Current",
  "extracted": "1711176302.629741"
}
