{
  "type": "FeatureCollection",
  "name": "PLANNED",
  "features": [
    {
      "type": "Feature",
      "geometry": {
        "type": "Point",
        "coordinates": [
          146.331519,
          -18.526706
        ]
      },
      "properties": {
        "EVENT_ID": "24NQ7319",
        "TYPE": "PLANNED",
        "CUSTOMERS_AFFECTED": "4",
        "REASON": "The loss of supply is to connect new customers to the electricity network",
        "STATUS": "Crews working on-site",
        "START": "12:30PM 17 May 2024",
        "EST_FIX_TIME": "3:30PM 06 Jun 2024",
        "STREETS": "DUNGENESS RD, KEAST ST",
        "SUBURBS": "LUCINDA"
      }
    },
    {
      "type": "Feature",
      "geometry": {
        "type": "Point",
        "coordinates": [
          152.32089,
          -24.889279
        ]
      },
      "properties": {
        "EVENT_ID": "24WB5481",
        "TYPE": "PLANNED",
        "CUSTOMERS_AFFECTED": "30",
        "REASON": "The loss of supply is to connect new customers to the electricity network",
        "STATUS": "Work scheduled",
        "START": "8:30PM 03 Jun 2024",
        "EST_FIX_TIME": "2:30AM 04 Jun 2024",
        "STREETS": "AERODROME RD, FAIRCLOTH CRES, HEIDKE ST, TAKALVAN ST",
        "SUBURBS": "AVOCA, BUNDABERG, KENSINGTON"
      }
    }
  ],
  "company": "Ergon",
  "state": "Current",
  "extracted": "1717404601.305755"
}
