{
  "type": "FeatureCollection",
  "name": "PLANNED",
  "features": [
    {
      "type": "Feature",
      "geometry": {
        "type": "Point",
        "coordinates": [
          149.14692,
          -21.17661
        ]
      },
      "properties": {
        "EVENT_ID": "24MK2810",
        "TYPE": "PLANNED",
        "CUSTOMERS_AFFECTED": "215",
        "REASON": "The loss of supply is to allow maintenance of the electricity network",
        "STATUS": "Crews working on-site",
        "START": "8:30AM 28 Mar 2024",
        "EST_FIX_TIME": "5:30PM 28 Mar 2024",
        "STREETS": "BATH AVE, BECKETT CT, BERKSHIRE LANE, CARMELA CT, CHURCHILL AVE, DICKENS AVE, DOWNING ST, HASTINGS ST, MARLBOROUGH ST, RALEIGH ST, TUDOR CT",
        "SUBURBS": "OORALEA"
      }
    },
    {
      "type": "Feature",
      "geometry": {
        "type": "Point",
        "coordinates": [
          139.486923,
          -20.738729
        ]
      },
      "properties": {
        "EVENT_ID": "24NQ6073",
        "TYPE": "PLANNED",
        "CUSTOMERS_AFFECTED": "142",
        "REASON": "The loss of supply is to allow maintenance of the electricity network",
        "STATUS": "Crews working on-site",
        "START": "8:05AM 28 Mar 2024",
        "EST_FIX_TIME": "4:00PM 28 Mar 2024",
        "STREETS": "NANDINA ST, NINETEENTH AVE, OPAL ST, RAILWAY AVE, TWENTY-FIRST AVE, TWENTYFIRST AVE, TWENTYTHIRD AVE",
        "SUBURBS": "HAPPY VALLEY, PARKSIDE"
      }
    }
  ],
  "company": "Ergon",
  "state": "Current",
  "extracted": "1711605605.021619"
}
