{
  "type": "FeatureCollection",
  "name": "PLANNED",
  "features": [
    {
      "type": "Feature",
      "geometry": {
        "type": "Point",
        "coordinates": [
          148.728963,
          -21.198159
        ]
      },
      "properties": {
        "EVENT_ID": "24MK3047",
        "TYPE": "PLANNED",
        "CUSTOMERS_AFFECTED": "231",
        "REASON": "The loss of supply is to replace power poles and improve the electricity network",
        "STATUS": "Crews working on-site",
        "START": "7:33AM 21 Apr 2024",
        "EST_FIX_TIME": "3:23PM 21 Apr 2024",
        "STREETS": "BRADFORDS RD, DUNWOLD CATTLE CREEK RD, ELSIE NASH ST, GARGETT-MIA MIA RD, HEAD MENKINS RD, HEAD VASSALLOS RD, HEADS RD, L SHEWS RD, LUCAS PADDOCK RD, LUSCOMBES RD, MACKAY EUNGELLA RD, MIA MIA ST, NEILSEN OMANDS RD, OMAND NEILSON RD, PINNACLE SEPTIMUS RD, PINNACLE ST, PINNACLE STATION RD, PUP CREEK RD, RAILWAY ST, SCOTTS RD, SEPTIMUS CATTLE CREEK RD, SEPTIMUS RD, WALKER FINNS RD, WILLIAMS RD",
        "SUBURBS": "GARGETT, PINNACLE, SEPTIMUS"
      }
    }
  ],
  "company": "Ergon",
  "state": "Current",
  "extracted": "1713684001.47749"
}
