{
  "type": "FeatureCollection",
  "name": "PLANNED",
  "features": [
    {
      "type": "Feature",
      "geometry": {
        "type": "Point",
        "coordinates": [
          146.036406,
          -17.52165
        ]
      },
      "properties": {
        "EVENT_ID": "24FN7043",
        "TYPE": "PLANNED",
        "CUSTOMERS_AFFECTED": "3",
        "REASON": "The loss of supply is to replace power poles and improve the electricity network",
        "STATUS": "Crews working on-site",
        "START": "7:50AM 21 Jun 2024",
        "EST_FIX_TIME": "5:00PM 21 Jun 2024",
        "STREETS": "TIERNEY ST",
        "SUBURBS": "INNISFAIL ESTATE"
      }
    }
  ],
  "company": "Ergon",
  "state": "Current",
  "extracted": "1718951414.29439"
}
