{
  "type": "FeatureCollection",
  "name": "PLANNED",
  "features": [
    {
      "type": "Feature",
      "geometry": {
        "type": "Point",
        "coordinates": [
          150.490773,
          -23.38149
        ]
      },
      "properties": {
        "EVENT_ID": "24CA5618",
        "TYPE": "PLANNED",
        "CUSTOMERS_AFFECTED": "42",
        "REASON": "The loss of supply is to upgrade equipment to meet customer demand for electricity and to improve reliability of supply in the area",
        "STATUS": "Crews working on-site",
        "START": "8:30AM 08 Jun 2024",
        "EST_FIX_TIME": "4:30PM 08 Jun 2024",
        "STREETS": "HARROW ST, NORTH EXTD ST, NORTH ST, PENNYCUICK ST",
        "SUBURBS": "ROCKHAMPTON, WANDAL, WEST ROCKHAMPTON"
      }
    },
    {
      "type": "Feature",
      "geometry": {
        "type": "Point",
        "coordinates": [
          142.221918,
          -10.577265
        ]
      },
      "properties": {
        "EVENT_ID": "24FN6538",
        "TYPE": "PLANNED",
        "CUSTOMERS_AFFECTED": "75",
        "REASON": "The loss of supply is to allow emergency maintenance of the electricity network",
        "STATUS": "Crews working on-site",
        "START": "8:00AM 08 Jun 2024",
        "EST_FIX_TIME": "4:30PM 08 Jun 2024",
        "STREETS": "APLIN RD, BOWIE CRES, LOBAN ST, SAILOR CRES, WAIBEN ESP",
        "SUBURBS": "THURSDAY ISLAND"
      }
    },
    {
      "type": "Feature",
      "geometry": {
        "type": "Point",
        "coordinates": [
          149.077601,
          -21.15927
        ]
      },
      "properties": {
        "EVENT_ID": "24MK4250",
        "TYPE": "PLANNED",
        "CUSTOMERS_AFFECTED": "7",
        "REASON": "The loss of supply is to upgrade equipment to meet customer demand for electricity and to improve reliability of supply in the area",
        "STATUS": "Crews working on-site",
        "START": "9:00AM 08 Jun 2024",
        "EST_FIX_TIME": "4:30PM 08 Jun 2024",
        "STREETS": "MACKAY EUNGELLA RD, PALMS RD, PEAK DOWNS HWY",
        "SUBURBS": "WALKERSTON"
      }
    }
  ],
  "company": "Ergon",
  "state": "Current",
  "extracted": "1717827600.354267"
}
