{
  "type": "FeatureCollection",
  "name": "PLANNED",
  "features": [
    {
      "type": "Feature",
      "geometry": {
        "type": "Point",
        "coordinates": [
          150.754489,
          -23.144929
        ]
      },
      "properties": {
        "EVENT_ID": "24CA3543",
        "TYPE": "PLANNED",
        "CUSTOMERS_AFFECTED": "18",
        "REASON": "The loss of supply is to replace power poles and improve the electricity network",
        "STATUS": "Crews working on-site",
        "START": "7:30AM 14 Mar 2024",
        "EST_FIX_TIME": "4:30PM 14 Mar 2024",
        "STREETS": "DOLPHIN CRES, SWORDFISH AVE",
        "SUBURBS": "TARANGANBA"
      }
    },
    {
      "type": "Feature",
      "geometry": {
        "type": "Point",
        "coordinates": [
          148.641447,
          -20.351501
        ]
      },
      "properties": {
        "EVENT_ID": "24MK2379",
        "TYPE": "PLANNED",
        "CUSTOMERS_AFFECTED": "226",
        "REASON": "The loss of supply is to replace power poles and improve the electricity network",
        "STATUS": "Crews working on-site",
        "START": "8:45AM 14 Mar 2024",
        "EST_FIX_TIME": "5:15PM 14 Mar 2024",
        "STREETS": "AITKEN RD, BECK RD, BRANDY CREEK RD, BROWN RD, BUSHRANGER DR, CAMM RD, CATTLEYARD CT, DUVAL RD, FORESTRY RD, JANSEN RD, MOUNT MARLOW RISE, PLEMENUK RD, REMMINGTON CL, RIFLE RANGE RD, SHUTE HARBOUR RD, SWAGMANS LANE, WINCHESTER CT",
        "SUBURBS": "BRANDY CREEK, MOUNT JULIAN, MOUNT MARLOW, PRESTON"
      }
    }
  ],
  "company": "Ergon",
  "state": "Current",
  "extracted": "1710400801.06805"
}
