{
  "type": "FeatureCollection",
  "name": "PLANNED",
  "features": [
    {
      "type": "Feature",
      "geometry": {
        "type": "Point",
        "coordinates": [
          148.847336,
          -20.973532
        ]
      },
      "properties": {
        "EVENT_ID": "24MK3920",
        "TYPE": "PLANNED",
        "CUSTOMERS_AFFECTED": "205",
        "REASON": "The loss of supply is to allow emergency maintenance of the electricity network",
        "STATUS": "Crews working on-site",
        "START": "8:12AM 23 May 2024",
        "EST_FIX_TIME": "6:00PM 23 May 2024",
        "STREETS": "BRUCE HWY, BUTHURRA STATION RD, CLANSIDE RD, CLIFFES RD, CLYDE MCLEANS RD, FAIRCHILDS RD, GEEBERGA BUTHURRA RD, GIFFORDS RD, HOWLANDS RD, J JOHNSONS RD, JANSENS RD, JIM MCLEANS RD, JOHNSONS RD, LONG MILE RD, MACKENZIES RD, MCKAYS RD, MCLEANS RD, MOUNT OSSA RD, MOUNT OSSA SEAFORTH RD, MT OSSA SCHOOL RD, MULHERINS RD, NARPI RD, PACES RD, PAUL BURGER RD, PRATTS RD, ST HELENS BEACH RD, STARKEYS RD, SURPRISE CREEK RD, TREVEYS RD, WATTS RD",
        "SUBURBS": "BUTHURRA, CALEN, KUTTABUL, MACKAY, MOUNT CHARLTON, MOUNT OSSA, SEAFORTH"
      }
    },
    {
      "type": "Feature",
      "geometry": {
        "type": "Point",
        "coordinates": [
          146.331519,
          -18.526706
        ]
      },
      "properties": {
        "EVENT_ID": "24NQ7319",
        "TYPE": "PLANNED",
        "CUSTOMERS_AFFECTED": "4",
        "REASON": "The loss of supply is to connect new customers to the electricity network",
        "STATUS": "Crews working on-site",
        "START": "12:30PM 17 May 2024",
        "EST_FIX_TIME": "3:30PM 30 May 2024",
        "STREETS": "DUNGENESS RD, KEAST ST",
        "SUBURBS": "LUCINDA"
      }
    }
  ],
  "company": "Ergon",
  "state": "Current",
  "extracted": "1716450303.826079"
}
