{
  "type": "FeatureCollection",
  "name": "PLANNED",
  "features": [
    {
      "type": "Feature",
      "geometry": {
        "type": "Point",
        "coordinates": [
          150.683289,
          -23.174263
        ]
      },
      "properties": {
        "EVENT_ID": "24CA7113",
        "TYPE": "PLANNED",
        "CUSTOMERS_AFFECTED": "4",
        "REASON": "The loss of supply is to replace power poles and improve the electricity network",
        "STATUS": "Crews working on-site",
        "START": "10:43AM 07 Jun 2024",
        "EST_FIX_TIME": "4:30PM 07 Jun 2024",
        "STREETS": "WHITES RD",
        "SUBURBS": "BONDOOLA"
      }
    },
    {
      "type": "Feature",
      "geometry": {
        "type": "Point",
        "coordinates": [
          152.09386,
          -28.163923
        ]
      },
      "properties": {
        "EVENT_ID": "24SW8961",
        "TYPE": "PLANNED",
        "CUSTOMERS_AFFECTED": "51",
        "REASON": "The loss of supply is to connect new customers to the electricity network",
        "STATUS": "Crews working on-site",
        "START": "8:32AM 07 Jun 2024",
        "EST_FIX_TIME": "3:30PM 07 Jun 2024",
        "STREETS": "ALLENS RD, BOURKES RD, CRUSHER RD, CUNNINGHAM HWY, FREESTONE RD, GLEESONS RD, HAMMOND RD, JENSEN RD, KAYS RD, MCBAINS RD, PERQUINS RD",
        "SUBURBS": "FREESTONE, SLADEVALE"
      }
    },
    {
      "type": "Feature",
      "geometry": {
        "type": "Point",
        "coordinates": [
          152.348693,
          -24.871258
        ]
      },
      "properties": {
        "EVENT_ID": "24WB5710",
        "TYPE": "PLANNED",
        "CUSTOMERS_AFFECTED": "26",
        "REASON": "The loss of supply is to allow maintenance of the electricity network",
        "STATUS": "Work scheduled",
        "START": "10:30PM 07 Jun 2024",
        "EST_FIX_TIME": "2:30AM 08 Jun 2024",
        "STREETS": "ELECTRA ST, GEORGE ST, MARYBOROUGH ST",
        "SUBURBS": "BUNDABERG, BUNDABERG CENTRAL"
      }
    }
  ],
  "company": "Ergon",
  "state": "Current",
  "extracted": "1717737001.49088"
}
