{
  "type": "FeatureCollection",
  "name": "PLANNED",
  "features": [
    {
      "type": "Feature",
      "geometry": {
        "type": "Point",
        "coordinates": [
          145.747831,
          -16.98774
        ]
      },
      "properties": {
        "EVENT_ID": "24FN2614",
        "TYPE": "PLANNED",
        "CUSTOMERS_AFFECTED": "248",
        "REASON": "The loss of supply is to replace power poles and improve the electricity network",
        "STATUS": "Crews working on-site",
        "START": "10:14PM 27 Mar 2024",
        "EST_FIX_TIME": "6:00AM 28 Mar 2024",
        "STREETS": "BOHEMIA CT, BRUCE HWY, BURNETT ST, COOMBS ST, DILLON CL, DILLON ST, DUNDEE CL, FRANGIPANNI ST, FRETWELL RD, GIFFIN RD, GREENACRES CL, JOHNSON RD, KINGSLEY CL, LEFTWICH ST, MISSION RD, PITTSBURG ST, PROGRESS RD, THE GREENS CL, WHITTON ST",
        "SUBURBS": "MOUNT SHERIDAN, WHITE ROCK"
      }
    },
    {
      "type": "Feature",
      "geometry": {
        "type": "Point",
        "coordinates": [
          146.761572,
          -19.273309
        ]
      },
      "properties": {
        "EVENT_ID": "24NQ5787",
        "TYPE": "PLANNED",
        "CUSTOMERS_AFFECTED": "17",
        "REASON": "The loss of supply is to replace power poles and improve the electricity network",
        "STATUS": "Crews working on-site",
        "START": "10:00PM 27 Mar 2024",
        "EST_FIX_TIME": "4:00AM 28 Mar 2024",
        "STREETS": "BAYSWATER RD",
        "SUBURBS": "GARBUTT"
      }
    },
    {
      "type": "Feature",
      "geometry": {
        "type": "Point",
        "coordinates": [
          146.749483,
          -19.271394
        ]
      },
      "properties": {
        "EVENT_ID": "24NQ5790",
        "TYPE": "PLANNED",
        "CUSTOMERS_AFFECTED": "7",
        "REASON": "The loss of supply is to replace power poles and improve the electricity network",
        "STATUS": "Crews working on-site",
        "START": "10:00PM 27 Mar 2024",
        "EST_FIX_TIME": "4:00AM 28 Mar 2024",
        "STREETS": "BAYSWATER RD",
        "SUBURBS": "GARBUTT"
      }
    },
    {
      "type": "Feature",
      "geometry": {
        "type": "Point",
        "coordinates": [
          152.352251,
          -24.87115
        ]
      },
      "properties": {
        "EVENT_ID": "24WB3881",
        "TYPE": "PLANNED",
        "CUSTOMERS_AFFECTED": "62",
        "REASON": "The loss of supply is to replace power poles and improve the electricity network",
        "STATUS": "Crews working on-site",
        "START": "9:14PM 27 Mar 2024",
        "EST_FIX_TIME": "3:00AM 28 Mar 2024",
        "STREETS": "BOURBONG ST, TARGO ST, WOONGARRA ST",
        "SUBURBS": "BUNDABERG, BUNDABERG CENTRAL"
      }
    }
  ],
  "company": "Ergon",
  "state": "Current",
  "extracted": "1711544404.657671"
}
