{
  "type": "FeatureCollection",
  "name": "PLANNED",
  "features": [
    {
      "type": "Feature",
      "geometry": {
        "type": "Point",
        "coordinates": [
          139.489293,
          -20.697703
        ]
      },
      "properties": {
        "EVENT_ID": "24NQ7592",
        "TYPE": "PLANNED",
        "CUSTOMERS_AFFECTED": "2",
        "REASON": "The loss of supply is to replace power poles and improve the electricity network",
        "STATUS": "Work scheduled",
        "START": "2:00PM 05 Jun 2024",
        "EST_FIX_TIME": "5:00PM 05 Jun 2024",
        "STREETS": "ABAU ST",
        "SUBURBS": "SOLDIERS HILL"
      }
    }
  ],
  "company": "Ergon",
  "state": "Current",
  "extracted": "1717554602.05387"
}
