{
  "type": "FeatureCollection",
  "name": "PLANNED",
  "features": [
    {
      "type": "Feature",
      "geometry": {
        "type": "Point",
        "coordinates": [
          145.677818,
          -16.77049
        ]
      },
      "properties": {
        "EVENT_ID": "25FN2557",
        "TYPE": "PLANNED",
        "CUSTOMERS_AFFECTED": "2",
        "REASON": "The loss of supply is to allow maintenance of the electricity network",
        "STATUS": "Crews working on-site",
        "START": "10:53AM 10 Mar 2025",
        "EST_FIX_TIME": "3:30PM 10 Mar 2025",
        "STREETS": "ST CRISPIN ST",
        "SUBURBS": "CLIFTON BEACH"
      }
    },
    {
      "type": "Feature",
      "geometry": {
        "type": "Point",
        "coordinates": [
          147.426903,
          -19.613749
        ]
      },
      "properties": {
        "EVENT_ID": "25NQ3030",
        "TYPE": "PLANNED",
        "CUSTOMERS_AFFECTED": "5",
        "REASON": "The loss of supply is to allow maintenance of the electricity network",
        "STATUS": "Crews working on-site",
        "START": "2:17PM 10 Mar 2025",
        "EST_FIX_TIME": "4:00PM 10 Mar 2025",
        "STREETS": "KILRIE RD, MCDESME RD",
        "SUBURBS": "AYR, MCDESME"
      }
    },
    {
      "type": "Feature",
      "geometry": {
        "type": "Point",
        "coordinates": [
          140.504226,
          -20.709805
        ]
      },
      "properties": {
        "EVENT_ID": "25NQ3243",
        "TYPE": "PLANNED",
        "CUSTOMERS_AFFECTED": "27",
        "REASON": "The loss of supply is to replace power poles and improve the electricity network",
        "STATUS": "Crews working on-site",
        "START": "8:38AM 10 Mar 2025",
        "EST_FIX_TIME": "3:00PM 10 Mar 2025",
        "STREETS": "LEICHHARDT ST, MCKINLAY ST",
        "SUBURBS": "CLONCURRY"
      }
    }
  ],
  "company": "Ergon",
  "state": "Current",
  "extracted": "1741581300.240992"
}
