{
  "type": "FeatureCollection",
  "name": "PLANNED",
  "features": [
    {
      "type": "Feature",
      "geometry": {
        "type": "Point",
        "coordinates": [
          145.422487,
          -16.990915
        ]
      },
      "properties": {
        "EVENT_ID": "24FN4035",
        "TYPE": "PLANNED",
        "CUSTOMERS_AFFECTED": "72",
        "REASON": "The loss of supply is to allow maintenance of the electricity network",
        "STATUS": "Crews working on-site",
        "START": "9:30PM 18 Apr 2024",
        "EST_FIX_TIME": "10:30PM 18 Apr 2024",
        "STREETS": "BYRNES ST, JACOBSEN ST, MIDDLEMISS ST, RAILWAY AVE, WALSH ST",
        "SUBURBS": "MAREEBA"
      }
    },
    {
      "type": "Feature",
      "geometry": {
        "type": "Point",
        "coordinates": [
          145.757347,
          -16.934585
        ]
      },
      "properties": {
        "EVENT_ID": "24FN4323",
        "TYPE": "PLANNED",
        "CUSTOMERS_AFFECTED": "290",
        "REASON": "The loss of supply is to replace power poles and improve the electricity network",
        "STATUS": "Work scheduled",
        "START": "10:30PM 18 Apr 2024",
        "EST_FIX_TIME": "4:30AM 19 Apr 2024",
        "STREETS": "ASCOT AVE, BARRETT ST, BROWN ST, EARL ST, EDGAR ST, FREDERICK ST, HANNAM ST, MULGRAVE RD, SCOTT ST, SPENCE ST, WELLINGTON ST",
        "SUBURBS": "BUNGALOW, CAIRNS, WESTCOURT"
      }
    },
    {
      "type": "Feature",
      "geometry": {
        "type": "Point",
        "coordinates": [
          146.331519,
          -18.526706
        ]
      },
      "properties": {
        "EVENT_ID": "24NQ5670",
        "TYPE": "PLANNED",
        "CUSTOMERS_AFFECTED": "4",
        "REASON": "The loss of supply is to allow maintenance of the electricity network",
        "STATUS": "Crews working on-site",
        "START": "9:00AM 15 Apr 2024",
        "EST_FIX_TIME": "3:00PM 19 Apr 2024",
        "STREETS": "DUNGENESS RD, KEAST ST",
        "SUBURBS": "LUCINDA"
      }
    }
  ],
  "company": "Ergon",
  "state": "Current",
  "extracted": "1713441301.213952"
}
