{
  "type": "FeatureCollection",
  "name": "PLANNED",
  "features": [
    {
      "type": "Feature",
      "geometry": {
        "type": "Point",
        "coordinates": [
          151.244446,
          -23.838221
        ]
      },
      "properties": {
        "EVENT_ID": "25CA3468",
        "TYPE": "PLANNED",
        "CUSTOMERS_AFFECTED": "50",
        "REASON": "The loss of supply is to replace power poles and improve the electricity network",
        "STATUS": "Crews working on-site",
        "START": "8:00AM 09 Mar 2025",
        "EST_FIX_TIME": "3:30PM 09 Mar 2025",
        "STREETS": "DREWE ST, HANSON RD, MORGAN ST, ROOKSBY ST, TRANBERG ST",
        "SUBURBS": "GLADSTONE, GLADSTONE CENTRAL"
      }
    }
  ],
  "company": "Ergon",
  "state": "Current",
  "extracted": "1741497001.502565"
}
