{
  "type": "FeatureCollection",
  "name": "PLANNED",
  "features": [
    {
      "type": "Feature",
      "geometry": {
        "type": "Point",
        "coordinates": [
          142.222957,
          -10.577256
        ]
      },
      "properties": {
        "EVENT_ID": "24FN6385",
        "TYPE": "PLANNED",
        "CUSTOMERS_AFFECTED": "76",
        "REASON": "The loss of supply is to allow emergency maintenance of the electricity network",
        "STATUS": "Crews working on-site",
        "START": "9:00AM 02 Jun 2024",
        "EST_FIX_TIME": "6:00PM 02 Jun 2024",
        "STREETS": "LOBAN ST, MAGALA ST, SAILOR CRES, WAIBEN ESP",
        "SUBURBS": "THURSDAY ISLAND"
      }
    },
    {
      "type": "Feature",
      "geometry": {
        "type": "Point",
        "coordinates": [
          146.331519,
          -18.526706
        ]
      },
      "properties": {
        "EVENT_ID": "24NQ7319",
        "TYPE": "PLANNED",
        "CUSTOMERS_AFFECTED": "4",
        "REASON": "The loss of supply is to connect new customers to the electricity network",
        "STATUS": "Crews working on-site",
        "START": "12:30PM 17 May 2024",
        "EST_FIX_TIME": "3:30PM 06 Jun 2024",
        "STREETS": "DUNGENESS RD, KEAST ST",
        "SUBURBS": "LUCINDA"
      }
    },
    {
      "type": "Feature",
      "geometry": {
        "type": "Point",
        "coordinates": [
          151.274913,
          -27.851295
        ]
      },
      "properties": {
        "EVENT_ID": "24SW8802",
        "TYPE": "PLANNED",
        "CUSTOMERS_AFFECTED": "72",
        "REASON": "The loss of supply is to replace power poles and improve the electricity network",
        "STATUS": "Crews working on-site",
        "START": "8:00AM 02 Jun 2024",
        "EST_FIX_TIME": "5:00PM 02 Jun 2024",
        "STREETS": "BRUCE RD, CHARLES ST, CHARLOTTE ST, DOOLEY RD, EDWARD ST, GORE HWY, LINDENMAYERS RD, MARGARET ST, MARY ST, MILL RD, MILLMERRAN CECIL PLAINS RD, WALLACE RD, WALPOLE ST, WEAVER ST",
        "SUBURBS": "MILLMERRAN"
      }
    },
    {
      "type": "Feature",
      "geometry": {
        "type": "Point",
        "coordinates": [
          151.272507,
          -27.875288
        ]
      },
      "properties": {
        "EVENT_ID": "24SW8814",
        "TYPE": "PLANNED",
        "CUSTOMERS_AFFECTED": "4",
        "REASON": "The loss of supply is to replace power poles and improve the electricity network",
        "STATUS": "Crews working on-site",
        "START": "8:05AM 02 Jun 2024",
        "EST_FIX_TIME": "4:00PM 02 Jun 2024",
        "STREETS": "MARY ST",
        "SUBURBS": "MILLMERRAN"
      }
    }
  ],
  "company": "Ergon",
  "state": "Current",
  "extracted": "1717307701.30639"
}
