{
  "type": "FeatureCollection",
  "name": "PLANNED",
  "features": [
    {
      "type": "Feature",
      "geometry": {
        "type": "Point",
        "coordinates": [
          145.920899,
          -17.340051
        ]
      },
      "properties": {
        "EVENT_ID": "24FN4017",
        "TYPE": "PLANNED",
        "CUSTOMERS_AFFECTED": "7",
        "REASON": "The loss of supply is to replace power poles and improve the electricity network",
        "STATUS": "Crews working on-site",
        "START": "11:47AM 12 Apr 2024",
        "EST_FIX_TIME": "4:30PM 12 Apr 2024",
        "STREETS": "PARRY ST",
        "SUBURBS": "BABINDA"
      }
    },
    {
      "type": "Feature",
      "geometry": {
        "type": "Point",
        "coordinates": [
          145.923572,
          -17.334298
        ]
      },
      "properties": {
        "EVENT_ID": "24FN4032",
        "TYPE": "PLANNED",
        "CUSTOMERS_AFFECTED": "2",
        "REASON": "The loss of supply is to replace power poles and improve the electricity network",
        "STATUS": "Crews working on-site",
        "START": "3:20PM 12 Apr 2024",
        "EST_FIX_TIME": "4:30PM 12 Apr 2024",
        "STREETS": "CHRISTIAN ST",
        "SUBURBS": "BABINDA"
      }
    },
    {
      "type": "Feature",
      "geometry": {
        "type": "Point",
        "coordinates": [
          148.809548,
          -21.085813
        ]
      },
      "properties": {
        "EVENT_ID": "24MK3042",
        "TYPE": "PLANNED",
        "CUSTOMERS_AFFECTED": "38",
        "REASON": "The loss of supply is to replace power poles and improve the electricity network",
        "STATUS": "Crews working on-site",
        "START": "9:02AM 12 Apr 2024",
        "EST_FIX_TIME": "5:00PM 12 Apr 2024",
        "STREETS": "COYNES RD, GARNHAM MORROWS RD, MCFAULS RD, MOUNT MARTIN LOOP RD, SUGARLOAF RD",
        "SUBURBS": "MOUNT MARTIN"
      }
    },
    {
      "type": "Feature",
      "geometry": {
        "type": "Point",
        "coordinates": [
          151.655341,
          -27.367122
        ]
      },
      "properties": {
        "EVENT_ID": "24SW6619",
        "TYPE": "PLANNED",
        "CUSTOMERS_AFFECTED": "16",
        "REASON": "The loss of supply is to replace power poles and improve the electricity network",
        "STATUS": "Crews working on-site",
        "START": "8:00AM 12 Apr 2024",
        "EST_FIX_TIME": "4:00PM 12 Apr 2024",
        "STREETS": "DEVON PARK NORTH RD, DEVON PARK RD, JONDARYAN MULDU RD, JONDARYAN SABINE RD, SCHULLS RD, WARREGO HWY",
        "SUBURBS": "DEVON PARK, JONDARYAN, OAKEY"
      }
    }
  ],
  "company": "Ergon",
  "state": "Current",
  "extracted": "1712902504.128194"
}
