{
  "type": "FeatureCollection",
  "name": "PLANNED",
  "features": [
    {
      "type": "Feature",
      "geometry": {
        "type": "Point",
        "coordinates": [
          149.43412,
          -21.716372
        ]
      },
      "properties": {
        "EVENT_ID": "24MK4579",
        "TYPE": "PLANNED",
        "CUSTOMERS_AFFECTED": "2",
        "REASON": "The loss of supply is to connect new customers to the electricity network",
        "STATUS": "Crews working on-site",
        "START": "8:00AM 10 Jun 2024",
        "EST_FIX_TIME": "2:30PM 14 Jun 2024",
        "STREETS": "NOTCH POINT RD",
        "SUBURBS": "ILBILBIE"
      }
    },
    {
      "type": "Feature",
      "geometry": {
        "type": "Point",
        "coordinates": [
          152.609832,
          -25.862604
        ]
      },
      "properties": {
        "EVENT_ID": "24WB5489",
        "TYPE": "PLANNED",
        "CUSTOMERS_AFFECTED": "282",
        "REASON": "The loss of supply is to allow maintenance of the electricity network",
        "STATUS": "Crews working on-site",
        "START": "9:25AM 13 Jun 2024",
        "EST_FIX_TIME": "5:00PM 13 Jun 2024",
        "STREETS": "BAUPLE-WOOLOOGA RD, BRUCE HWY, DANIEL RD, DARWIN RD, DEEPHOUSE RD, EMMA RD, FAINE RD, GOOTCHIE RD, HEMMINGS RD, KEETJE RD, MARTYN RD, MOLTENO RD, MYNTJE RD, PETTIT RD, SHEEHANS RD, STOTTENVILLE RD, VAN HENSBROEK RD",
        "SUBURBS": "BAUPLE, GOOTCHIE, ROSSENDALE"
      }
    }
  ],
  "company": "Ergon",
  "state": "Current",
  "extracted": "1718263200.378813"
}
