{
  "type": "FeatureCollection",
  "name": "PLANNED",
  "features": [
    {
      "type": "Feature",
      "geometry": {
        "type": "Point",
        "coordinates": [
          139.506949,
          -20.700723
        ]
      },
      "properties": {
        "EVENT_ID": "24NQ7533",
        "TYPE": "PLANNED",
        "CUSTOMERS_AFFECTED": "22",
        "REASON": "The loss of supply is to allow emergency maintenance of the electricity network",
        "STATUS": "Crews working on-site",
        "START": "8:49AM 05 May 2024",
        "EST_FIX_TIME": "4:30PM 05 May 2024",
        "STREETS": "ACTIVITY RD, COMMERCIAL RD, ENGINEERING RD, PROGRESS RD, RICHARDSON RD, RYAN RD",
        "SUBURBS": "RYAN"
      }
    }
  ],
  "company": "Ergon",
  "state": "Current",
  "extracted": "1714890301.592392"
}
