{
  "type": "FeatureCollection",
  "name": "PLANNED",
  "features": [
    {
      "type": "Feature",
      "geometry": {
        "type": "Point",
        "coordinates": [
          146.254957,
          -20.072696
        ]
      },
      "properties": {
        "EVENT_ID": "24NQ7468",
        "TYPE": "PLANNED",
        "CUSTOMERS_AFFECTED": "90",
        "REASON": "The loss of supply is to connect new customers to the electricity network",
        "STATUS": "Crews working on-site",
        "START": "8:56AM 04 May 2024",
        "EST_FIX_TIME": "5:00PM 04 May 2024",
        "STREETS": "CHARLOTTE ST, CLARKE ST, ELIZABETH ST, JANE ST, KING ST, MACDONALD ST, MARION ST, PLANT ST, RICHARDS LANE, RUTHERFORD LANE, RUTHERFORD ST, STUBLEY ST",
        "SUBURBS": "CHARTERS TOWERS, CHARTERS TOWERS CITY, RICHMOND HILL"
      }
    }
  ],
  "company": "Ergon",
  "state": "Current",
  "extracted": "1714802701.139491"
}
