{
  "type": "FeatureCollection",
  "name": "PLANNED",
  "features": [
    {
      "type": "Feature",
      "geometry": {
        "type": "Point",
        "coordinates": [
          145.630557,
          -17.473517
        ]
      },
      "properties": {
        "EVENT_ID": "24FN6024",
        "TYPE": "PLANNED",
        "CUSTOMERS_AFFECTED": "43",
        "REASON": "The loss of supply is to replace power poles and improve the electricity network",
        "STATUS": "Crews working on-site",
        "START": "8:30AM 22 May 2024",
        "EST_FIX_TIME": "4:30PM 22 May 2024",
        "STREETS": "ELLINJAA RD, FRASER RD, JUBB RD, MOREGATTA RD, PURCELL RD, THERESA CREEK RD, WOOLLEYS RD",
        "SUBURBS": "MILLAA MILLAA"
      }
    },
    {
      "type": "Feature",
      "geometry": {
        "type": "Point",
        "coordinates": [
          146.331519,
          -18.526706
        ]
      },
      "properties": {
        "EVENT_ID": "24NQ7319",
        "TYPE": "PLANNED",
        "CUSTOMERS_AFFECTED": "4",
        "REASON": "The loss of supply is to connect new customers to the electricity network",
        "STATUS": "Crews working on-site",
        "START": "12:30PM 17 May 2024",
        "EST_FIX_TIME": "3:30PM 30 May 2024",
        "STREETS": "DUNGENESS RD, KEAST ST",
        "SUBURBS": "LUCINDA"
      }
    }
  ],
  "company": "Ergon",
  "state": "Current",
  "extracted": "1716359101.652588"
}
