{
  "type": "FeatureCollection",
  "name": "PLANNED",
  "features": [
    {
      "type": "Feature",
      "geometry": {
        "type": "Point",
        "coordinates": [
          145.400289,
          -16.479128
        ]
      },
      "properties": {
        "EVENT_ID": "24FN4801",
        "TYPE": "PLANNED",
        "CUSTOMERS_AFFECTED": "6",
        "REASON": "The loss of supply is to replace power poles and improve the electricity network",
        "STATUS": "Crews working on-site",
        "START": "8:30AM 03 May 2024",
        "EST_FIX_TIME": "4:00PM 03 May 2024",
        "STREETS": "FRANCIS RD",
        "SUBURBS": "SOUTH MOSSMAN"
      }
    },
    {
      "type": "Feature",
      "geometry": {
        "type": "Point",
        "coordinates": [
          146.843372,
          -19.318496
        ]
      },
      "properties": {
        "EVENT_ID": "24NQ6697",
        "TYPE": "PLANNED",
        "CUSTOMERS_AFFECTED": "2",
        "REASON": "The loss of supply is to allow maintenance of the electricity network",
        "STATUS": "Crews working on-site",
        "START": "8:18AM 03 May 2024",
        "EST_FIX_TIME": "4:00PM 03 May 2024",
        "STREETS": "PENELOPE RD",
        "SUBURBS": "CLUDEN, STUART"
      }
    }
  ],
  "company": "Ergon",
  "state": "Current",
  "extracted": "1714710000.289576"
}
