{
  "type": "FeatureCollection",
  "name": "PLANNED",
  "features": [
    {
      "type": "Feature",
      "geometry": {
        "type": "Point",
        "coordinates": [
          151.957085,
          -27.560581
        ]
      },
      "properties": {
        "EVENT_ID": "24SW5250",
        "TYPE": "PLANNED",
        "CUSTOMERS_AFFECTED": "2",
        "REASON": "The loss of supply is to upgrade equipment to meet customer demand for electricity and to improve reliability of supply in the area",
        "STATUS": "Work scheduled",
        "START": "9:00PM 13 Mar 2024",
        "EST_FIX_TIME": "4:00AM 14 Mar 2024",
        "STREETS": "BELL ST",
        "SUBURBS": "TOOWOOMBA, TOOWOOMBA CITY"
      }
    }
  ],
  "company": "Ergon",
  "state": "Current",
  "extracted": "1710321001.139107"
}
