{
  "type": "FeatureCollection",
  "name": "PLANNED",
  "features": [
    {
      "type": "Feature",
      "geometry": {
        "type": "Point",
        "coordinates": [
          150.50647,
          -23.394891
        ]
      },
      "properties": {
        "EVENT_ID": "24CA7344",
        "TYPE": "PLANNED",
        "CUSTOMERS_AFFECTED": "10",
        "REASON": "The loss of supply is to connect new customers to the electricity network",
        "STATUS": "Crews working on-site",
        "START": "8:00AM 23 Jun 2024",
        "EST_FIX_TIME": "4:00PM 23 Jun 2024",
        "STREETS": "ELIZABETH ST, GLADSTONE RD",
        "SUBURBS": "ALLENSTOWN, ROCKHAMPTON, ROCKHAMPTON CITY"
      }
    },
    {
      "type": "Feature",
      "geometry": {
        "type": "Point",
        "coordinates": [
          146.075906,
          -17.578697
        ]
      },
      "properties": {
        "EVENT_ID": "24FN7304",
        "TYPE": "PLANNED",
        "CUSTOMERS_AFFECTED": "7",
        "REASON": "The loss of supply is to replace power poles and improve the electricity network",
        "STATUS": "Crews working on-site",
        "START": "12:40PM 23 Jun 2024",
        "EST_FIX_TIME": "4:30PM 23 Jun 2024",
        "STREETS": "ETTY BAY RD",
        "SUBURBS": "MOURILYAN"
      }
    },
    {
      "type": "Feature",
      "geometry": {
        "type": "Point",
        "coordinates": [
          151.994188,
          -26.666066
        ]
      },
      "properties": {
        "EVENT_ID": "24WB6031",
        "TYPE": "PLANNED",
        "CUSTOMERS_AFFECTED": "345",
        "REASON": "The loss of supply is to connect new customers to the electricity network",
        "STATUS": "Crews working on-site",
        "START": "8:30AM 23 Jun 2024",
        "EST_FIX_TIME": "4:30PM 23 Jun 2024",
        "STREETS": "BIRDIE ST, BUNKER AVE, CAIRNS ST, CHESTER ST, CLUB CT, D'AGUILAR HWY, DALBY ST, DOWNING ST, DRAYTON ST, EAGLE ST, ELK ST, FAIRWAY DR, FITZROY ST, FLAG ST, GIPPS ST, GREY ST, HAWTHORNE ST, HENRY ST, HOWLETT LANE, KEOGH CT, KINGAROY RD, LEE CT, NORMANBY ST",
        "SUBURBS": "NANANGO"
      }
    }
  ],
  "company": "Ergon",
  "state": "Current",
  "extracted": "1719121202.258407"
}
