{
  "type": "FeatureCollection",
  "name": "PLANNED",
  "features": [
    {
      "type": "Feature",
      "geometry": {
        "type": "Point",
        "coordinates": [
          150.586776,
          -23.724004
        ]
      },
      "properties": {
        "EVENT_ID": "24CA4551",
        "TYPE": "PLANNED",
        "CUSTOMERS_AFFECTED": "175",
        "REASON": "The loss of supply is to replace power poles and improve the electricity network",
        "STATUS": "Crews working on-site",
        "START": "8:30AM 14 Apr 2024",
        "EST_FIX_TIME": "5:30PM 14 Apr 2024",
        "STREETS": "BODERO RD, BRUCE HWY, BULL FROG LANE, BYCROFT RD, COWIE RD, GOODSALL RD, HIGH ST, KIRK RD, MAGAZINE RD, MILL ST, MOUNT HOPEFUL RD, OFF BRUCE HWY, OLD COACH RD, PORT ALMA RD, ROBERTS RD, SCHOOL ST, SISALANA RD, SIX MILE RD, SOUTH ULAM RD, SPRINGS RD, TOONDA RD, TOONDA ST, ULAM CONNECTION RD, UPPER ULAM RD",
        "SUBURBS": "BAJOOL, MARMOR"
      }
    }
  ],
  "company": "Ergon",
  "state": "Current",
  "extracted": "1713078905.124933"
}
