{
  "type": "FeatureCollection",
  "name": "PLANNED",
  "features": [
    {
      "type": "Feature",
      "geometry": {
        "type": "Point",
        "coordinates": [
          139.489293,
          -20.697703
        ]
      },
      "properties": {
        "EVENT_ID": "24NQ7592",
        "TYPE": "PLANNED",
        "CUSTOMERS_AFFECTED": "2",
        "REASON": "The loss of supply is to replace power poles and improve the electricity network",
        "STATUS": "Crews working on-site",
        "START": "3:43PM 05 Jun 2024",
        "EST_FIX_TIME": "5:30PM 05 Jun 2024",
        "STREETS": "ABAU ST",
        "SUBURBS": "SOLDIERS HILL"
      }
    },
    {
      "type": "Feature",
      "geometry": {
        "type": "Point",
        "coordinates": [
          152.836728,
          -25.296603
        ]
      },
      "properties": {
        "EVENT_ID": "24WB5588",
        "TYPE": "PLANNED",
        "CUSTOMERS_AFFECTED": "4",
        "REASON": "The loss of supply is to connect new customers to the electricity network",
        "STATUS": "Crews working on-site",
        "START": "8:30AM 05 Jun 2024",
        "EST_FIX_TIME": "5:30PM 05 Jun 2024",
        "STREETS": "MAIN ST, MCLIVER ST",
        "SUBURBS": "PIALBA"
      }
    }
  ],
  "company": "Ergon",
  "state": "Current",
  "extracted": "1717571703.728279"
}
