{
  "type": "FeatureCollection",
  "name": "PLANNED",
  "features": [
    {
      "type": "Feature",
      "geometry": {
        "type": "Point",
        "coordinates": [
          148.778322,
          -20.897846
        ]
      },
      "properties": {
        "EVENT_ID": "24MK3920",
        "TYPE": "PLANNED",
        "CUSTOMERS_AFFECTED": "5",
        "REASON": "The loss of supply is to allow emergency maintenance of the electricity network",
        "STATUS": "Crews working on-site",
        "START": "8:12AM 23 May 2024",
        "EST_FIX_TIME": "6:00PM 23 May 2024",
        "STREETS": "PRATTS RD, ST HELENS BEACH RD",
        "SUBURBS": "CALEN"
      }
    },
    {
      "type": "Feature",
      "geometry": {
        "type": "Point",
        "coordinates": [
          146.331519,
          -18.526706
        ]
      },
      "properties": {
        "EVENT_ID": "24NQ7319",
        "TYPE": "PLANNED",
        "CUSTOMERS_AFFECTED": "4",
        "REASON": "The loss of supply is to connect new customers to the electricity network",
        "STATUS": "Crews working on-site",
        "START": "12:30PM 17 May 2024",
        "EST_FIX_TIME": "3:30PM 30 May 2024",
        "STREETS": "DUNGENESS RD, KEAST ST",
        "SUBURBS": "LUCINDA"
      }
    }
  ],
  "company": "Ergon",
  "state": "Current",
  "extracted": "1716450601.287994"
}
