{
  "type": "FeatureCollection",
  "name": "PLANNED",
  "features": [
    {
      "type": "Feature",
      "geometry": {
        "type": "Point",
        "coordinates": [
          148.567541,
          -21.058434
        ]
      },
      "properties": {
        "EVENT_ID": "24MK2777",
        "TYPE": "PLANNED",
        "CUSTOMERS_AFFECTED": "37",
        "REASON": "The loss of supply is to remove vegetation growing near powerlines",
        "STATUS": "Crews working on-site",
        "START": "10:00AM 19 Apr 2024",
        "EST_FIX_TIME": "3:30PM 19 Apr 2024",
        "STREETS": "CHELMANS RD, DALRYMPLE RD, FREDRICKSONS RD, SNAKE RD",
        "SUBURBS": "DALRYMPLE HEIGHTS, EUNGELLA"
      }
    },
    {
      "type": "Feature",
      "geometry": {
        "type": "Point",
        "coordinates": [
          146.256023,
          -18.553086
        ]
      },
      "properties": {
        "EVENT_ID": "24NQ6700",
        "TYPE": "PLANNED",
        "CUSTOMERS_AFFECTED": "23",
        "REASON": "The loss of supply is to replace power poles and improve the electricity network",
        "STATUS": "Crews working on-site",
        "START": "8:30AM 19 Apr 2024",
        "EST_FIX_TIME": "4:00PM 19 Apr 2024",
        "STREETS": "BULLOCK PADDOCK RD, CARUSO'S RD, KEMPS RD",
        "SUBURBS": "MACKNADE"
      }
    },
    {
      "type": "Feature",
      "geometry": {
        "type": "Point",
        "coordinates": [
          151.103751,
          -25.538807
        ]
      },
      "properties": {
        "EVENT_ID": "24WB3962",
        "TYPE": "PLANNED",
        "CUSTOMERS_AFFECTED": "52",
        "REASON": "The loss of supply is to allow maintenance of the electricity network",
        "STATUS": "Crews working on-site",
        "START": "9:02AM 19 Apr 2024",
        "EST_FIX_TIME": "3:00PM 19 Apr 2024",
        "STREETS": "A CREEK RD, COONAMBULA EIDSVOLD RD, COONAMBULA RD, COONAMBULA-EIDSVOLD RD, CRISPS RD, MCCORDS RD, PEARLINGA, RIVERLEIGH SCHOOL RD, RIVERLEIGH STATION RD, STANMORE RD",
        "SUBURBS": "COONAMBULA, MUNDUBBERA, O'BIL BIL, RIVERLEIGH"
      }
    }
  ],
  "company": "Ergon",
  "state": "Current",
  "extracted": "1713502500.479638"
}
