{
  "type": "FeatureCollection",
  "name": "PLANNED",
  "features": [
    {
      "type": "Feature",
      "geometry": {
        "type": "Point",
        "coordinates": [
          148.024149,
          -23.532895
        ]
      },
      "properties": {
        "EVENT_ID": "24CA4563",
        "TYPE": "PLANNED",
        "CUSTOMERS_AFFECTED": "14",
        "REASON": "The loss of supply is to allow maintenance of the electricity network",
        "STATUS": "Crews working on-site",
        "START": "8:46AM 24 Apr 2024",
        "EST_FIX_TIME": "5:00PM 24 Apr 2024",
        "STREETS": "CAPRICORN HWY, DENISON RD, FORK LAGOONS RD, MARSHALL RD",
        "SUBURBS": "EMERALD"
      }
    }
  ],
  "company": "Ergon",
  "state": "Current",
  "extracted": "1713939301.91198"
}
