{
  "type": "FeatureCollection",
  "name": "PLANNED",
  "features": [
    {
      "type": "Feature",
      "geometry": {
        "type": "Point",
        "coordinates": [
          146.331519,
          -18.526706
        ]
      },
      "properties": {
        "EVENT_ID": "24NQ7260",
        "TYPE": "PLANNED",
        "CUSTOMERS_AFFECTED": "4",
        "REASON": "The loss of supply is to connect new customers to the electricity network",
        "STATUS": "Crews working on-site",
        "START": "7:42AM 07 May 2024",
        "EST_FIX_TIME": "3:30PM 14 May 2024",
        "STREETS": "DUNGENESS RD, KEAST ST",
        "SUBURBS": "LUCINDA"
      }
    },
    {
      "type": "Feature",
      "geometry": {
        "type": "Point",
        "coordinates": [
          147.458483,
          -19.565935
        ]
      },
      "properties": {
        "EVENT_ID": "24NQ7497",
        "TYPE": "PLANNED",
        "CUSTOMERS_AFFECTED": "68",
        "REASON": "The loss of supply is to replace power poles and improve the electricity network",
        "STATUS": "Crews working on-site",
        "START": "8:32AM 11 May 2024",
        "EST_FIX_TIME": "4:30PM 11 May 2024",
        "STREETS": "BEVILACQUA RD, HOBSON RD, IVANHOE RD, MCALLISTER RD, MINUZZO RD, RITA ISLAND RD, RUDDYS RD, SEAFORTH RD",
        "SUBURBS": "AYR, JARVISFIELD"
      }
    }
  ],
  "company": "Ergon",
  "state": "Current",
  "extracted": "1715409902.647022"
}
