{
  "type": "FeatureCollection",
  "name": "PLANNED",
  "features": [
    {
      "type": "Feature",
      "geometry": {
        "type": "Point",
        "coordinates": [
          145.566437,
          -16.897957
        ]
      },
      "properties": {
        "EVENT_ID": "24FN4222",
        "TYPE": "PLANNED",
        "CUSTOMERS_AFFECTED": "47",
        "REASON": "The loss of supply is to replace power poles and improve the electricity network",
        "STATUS": "Crews working on-site",
        "START": "8:30AM 13 Apr 2024",
        "EST_FIX_TIME": "4:30PM 13 Apr 2024",
        "STREETS": "BRICKWORKS RD, CLOHESY RIVER RD, GRIEVSON RD, KENNEDY HWY, KOAH RD, O'NEIL CL, PALM VALLEY RD",
        "SUBURBS": "CLOHESY RIVER, GROVE CREEK, KOAH, KURANDA"
      }
    }
  ],
  "company": "Ergon",
  "state": "Current",
  "extracted": "1712988601.806065"
}
