{
  "type": "FeatureCollection",
  "name": "PLANNED",
  "features": [
    {
      "type": "Feature",
      "geometry": {
        "type": "Point",
        "coordinates": [
          139.179533,
          -16.66451
        ]
      },
      "properties": {
        "EVENT_ID": "24FN3093",
        "TYPE": "PLANNED",
        "CUSTOMERS_AFFECTED": "6",
        "REASON": "The loss of supply is to replace power poles and improve the electricity network",
        "STATUS": "Crews working on-site",
        "START": "8:30AM 07 Apr 2024",
        "EST_FIX_TIME": "4:00PM 07 Apr 2024",
        "STREETS": "DJINKYA ST, KATHAN KATHAN ST, LARDIL ST",
        "SUBURBS": "GUNUNA"
      }
    }
  ],
  "company": "Ergon",
  "state": "Current",
  "extracted": "1712467501.024247"
}
