{
  "type": "FeatureCollection",
  "name": "PLANNED",
  "features": [
    {
      "type": "Feature",
      "geometry": {
        "type": "Point",
        "coordinates": [
          152.376965,
          -24.865325
        ]
      },
      "properties": {
        "EVENT_ID": "24WB3365",
        "TYPE": "PLANNED",
        "CUSTOMERS_AFFECTED": "29",
        "REASON": "The loss of supply is to replace power poles and improve the electricity network",
        "STATUS": "Crews working on-site",
        "START": "8:01PM 19 Mar 2024",
        "EST_FIX_TIME": "1:00AM 20 Mar 2024",
        "STREETS": "GERRARD ST, STEPTOE ST",
        "SUBURBS": "BUNDABERG, BUNDABERG EAST"
      }
    }
  ],
  "company": "Ergon",
  "state": "Current",
  "extracted": "1710848705.865868"
}
