{
  "type": "FeatureCollection",
  "name": "PLANNED",
  "features": [
    {
      "type": "Feature",
      "geometry": {
        "type": "Point",
        "coordinates": [
          145.471761,
          -17.260672
        ]
      },
      "properties": {
        "EVENT_ID": "24FN3157",
        "TYPE": "PLANNED",
        "CUSTOMERS_AFFECTED": "9",
        "REASON": "The loss of supply is to replace power poles and improve the electricity network",
        "STATUS": "Crews working on-site",
        "START": "10:30AM 11 Mar 2024",
        "EST_FIX_TIME": "3:30PM 11 Mar 2024",
        "STREETS": "CANOPUS CCT",
        "SUBURBS": "ATHERTON"
      }
    }
  ],
  "company": "Ergon",
  "state": "Current",
  "extracted": "1710125401.64642"
}
