{
  "type": "FeatureCollection",
  "name": "PLANNED",
  "features": [
    {
      "type": "Feature",
      "geometry": {
        "type": "Point",
        "coordinates": [
          150.569104,
          -23.724008
        ]
      },
      "properties": {
        "EVENT_ID": "24CA5021",
        "TYPE": "PLANNED",
        "CUSTOMERS_AFFECTED": "132",
        "REASON": "The loss of supply is to replace power poles and improve the electricity network",
        "STATUS": "Crews working on-site",
        "START": "9:31AM 27 Apr 2024",
        "EST_FIX_TIME": "6:30PM 27 Apr 2024",
        "STREETS": "BODERO RD, BRUCE HWY, BULL FROG LANE, BYCROFT RD, COWIE RD, GOODSALL RD, KIRK RD, MILL ST, MOUNT HOPEFUL RD, SCHOOL ST, SIX MILE RD, SOUTH ULAM RD, SPRINGS RD, TOONDA RD, TOONDA ST, ULAM CONNECTION RD, UPPER ULAM RD",
        "SUBURBS": "BAJOOL"
      }
    },
    {
      "type": "Feature",
      "geometry": {
        "type": "Point",
        "coordinates": [
          150.74972,
          -23.109202
        ]
      },
      "properties": {
        "EVENT_ID": "24CA5343",
        "TYPE": "PLANNED",
        "CUSTOMERS_AFFECTED": "12",
        "REASON": "The loss of supply is to replace power poles and improve the electricity network",
        "STATUS": "Crews working on-site",
        "START": "8:30AM 27 Apr 2024",
        "EST_FIX_TIME": "4:30PM 27 Apr 2024",
        "STREETS": "TODD AVE",
        "SUBURBS": "YEPPOON"
      }
    },
    {
      "type": "Feature",
      "geometry": {
        "type": "Point",
        "coordinates": [
          150.749275,
          -23.110291
        ]
      },
      "properties": {
        "EVENT_ID": "24CA5344",
        "TYPE": "PLANNED",
        "CUSTOMERS_AFFECTED": "7",
        "REASON": "The loss of supply is to replace power poles and improve the electricity network",
        "STATUS": "Crews working on-site",
        "START": "8:30AM 27 Apr 2024",
        "EST_FIX_TIME": "4:30PM 27 Apr 2024",
        "STREETS": "CORBETT ST",
        "SUBURBS": "YEPPOON"
      }
    },
    {
      "type": "Feature",
      "geometry": {
        "type": "Point",
        "coordinates": [
          142.75018,
          -20.469853
        ]
      },
      "properties": {
        "EVENT_ID": "24NQ6414",
        "TYPE": "PLANNED",
        "CUSTOMERS_AFFECTED": "4",
        "REASON": "The loss of supply is to replace power poles and improve the electricity network",
        "STATUS": "Crews working on-site",
        "START": "8:30AM 27 Apr 2024",
        "EST_FIX_TIME": "4:30PM 27 Apr 2024",
        "STREETS": "ARTESIAN DOWNS STATION, GRACEDALE STATION, LILYVALE STATION, MORUNGLE STATION",
        "SUBURBS": "MAXWELTON"
      }
    }
  ],
  "company": "Ergon",
  "state": "Current",
  "extracted": "1714197901.270871"
}
