{
  "type": "FeatureCollection",
  "name": "PLANNED",
  "features": [
    {
      "type": "Feature",
      "geometry": {
        "type": "Point",
        "coordinates": [
          150.487288,
          -23.380941
        ]
      },
      "properties": {
        "EVENT_ID": "24CA5618",
        "TYPE": "PLANNED",
        "CUSTOMERS_AFFECTED": "451",
        "REASON": "The loss of supply is to upgrade equipment to meet customer demand for electricity and to improve reliability of supply in the area",
        "STATUS": "Crews working on-site",
        "START": "8:30AM 08 Jun 2024",
        "EST_FIX_TIME": "4:00PM 08 Jun 2024",
        "STREETS": "AGNES ST, BENCKE ST, BOREHAM ST, BRADFORD ST, CANOONA RD, CONSIDINE ST, ETON ST, FENLON ST, FLYNN ST, FOREMAN ST, GORLE ST, HARROW ST, HUNTER ST, HUNTINGTON ST, JARDINE ST, JEFFRIES ST, MELBOURNE ST, MOONIE ST, NORTH EXTD ST, NORTH ST, PARKER ST, PEARSON ST, PENNYCUICK ST, SCHOFIELD ST, STICKLEY ST, VICTORIA ST, WAMBOOL ST, WESTERN ST",
        "SUBURBS": "ROCKHAMPTON, THE RANGE, WANDAL, WEST ROCKHAMPTON"
      }
    },
    {
      "type": "Feature",
      "geometry": {
        "type": "Point",
        "coordinates": [
          142.221918,
          -10.577265
        ]
      },
      "properties": {
        "EVENT_ID": "24FN6538",
        "TYPE": "PLANNED",
        "CUSTOMERS_AFFECTED": "75",
        "REASON": "The loss of supply is to allow emergency maintenance of the electricity network",
        "STATUS": "Crews working on-site",
        "START": "8:00AM 08 Jun 2024",
        "EST_FIX_TIME": "4:00PM 08 Jun 2024",
        "STREETS": "APLIN RD, BOWIE CRES, LOBAN ST, SAILOR CRES, WAIBEN ESP",
        "SUBURBS": "THURSDAY ISLAND"
      }
    },
    {
      "type": "Feature",
      "geometry": {
        "type": "Point",
        "coordinates": [
          149.077601,
          -21.15927
        ]
      },
      "properties": {
        "EVENT_ID": "24MK4250",
        "TYPE": "PLANNED",
        "CUSTOMERS_AFFECTED": "7",
        "REASON": "The loss of supply is to upgrade equipment to meet customer demand for electricity and to improve reliability of supply in the area",
        "STATUS": "Crews working on-site",
        "START": "9:00AM 08 Jun 2024",
        "EST_FIX_TIME": "4:30PM 08 Jun 2024",
        "STREETS": "MACKAY EUNGELLA RD, PALMS RD, PEAK DOWNS HWY",
        "SUBURBS": "WALKERSTON"
      }
    }
  ],
  "company": "Ergon",
  "state": "Current",
  "extracted": "1717826101.557837"
}
