{
  "type": "FeatureCollection",
  "name": "PLANNED",
  "features": [
    {
      "type": "Feature",
      "geometry": {
        "type": "Point",
        "coordinates": [
          145.08827,
          -23.654023
        ]
      },
      "properties": {
        "EVENT_ID": "24CA5224",
        "TYPE": "PLANNED",
        "CUSTOMERS_AFFECTED": "57",
        "REASON": "The loss of supply is to allow maintenance of the electricity network",
        "STATUS": "Crews working on-site",
        "START": "8:28AM 29 Apr 2024",
        "EST_FIX_TIME": "6:00PM 29 Apr 2024",
        "STREETS": "ARAMAC RD, BARCALDINE DOWNS RD, BARCALDINE-ISISFOR RD, BARCALDINE-ISISFORD RD, BARCALDINE-L'REACH RD, BLOODWOOD DR, LANDSBOROUGH HWY, OFF LANDSBOROUGH HWY, SALTERN CREEK RD, SANDALWOOD DR",
        "SUBURBS": "BARCALDINE"
      }
    }
  ],
  "company": "Ergon",
  "state": "Current",
  "extracted": "1714374004.305449"
}
