{
  "type": "FeatureCollection",
  "name": "PLANNED",
  "features": [
    {
      "type": "Feature",
      "geometry": {
        "type": "Point",
        "coordinates": [
          145.750467,
          -16.97637
        ]
      },
      "properties": {
        "EVENT_ID": "24FN4941",
        "TYPE": "PLANNED",
        "CUSTOMERS_AFFECTED": "4",
        "REASON": "The loss of supply is to replace power poles and improve the electricity network",
        "STATUS": "Crews working on-site",
        "START": "12:42PM 28 Apr 2024",
        "EST_FIX_TIME": "4:30PM 28 Apr 2024",
        "STREETS": "KAMBARA ST",
        "SUBURBS": "WHITE ROCK"
      }
    },
    {
      "type": "Feature",
      "geometry": {
        "type": "Point",
        "coordinates": [
          147.43122,
          -19.58881
        ]
      },
      "properties": {
        "EVENT_ID": "24NQ7130",
        "TYPE": "PLANNED",
        "CUSTOMERS_AFFECTED": "19",
        "REASON": "The loss of supply is to replace power poles and improve the electricity network",
        "STATUS": "Crews working on-site",
        "START": "9:05AM 28 Apr 2024",
        "EST_FIX_TIME": "4:00PM 28 Apr 2024",
        "STREETS": "RITA ISLAND RD",
        "SUBURBS": "AYR"
      }
    },
    {
      "type": "Feature",
      "geometry": {
        "type": "Point",
        "coordinates": [
          147.423217,
          -19.58195
        ]
      },
      "properties": {
        "EVENT_ID": "24NQ7131",
        "TYPE": "PLANNED",
        "CUSTOMERS_AFFECTED": "2",
        "REASON": "The loss of supply is to replace power poles and improve the electricity network",
        "STATUS": "Crews working on-site",
        "START": "8:50AM 28 Apr 2024",
        "EST_FIX_TIME": "5:00PM 28 Apr 2024",
        "STREETS": "NORHAM RD, RITA ISLAND RD",
        "SUBURBS": "AYR"
      }
    }
  ],
  "company": "Ergon",
  "state": "Current",
  "extracted": "1714286101.36186"
}
