{
  "type": "FeatureCollection",
  "name": "PLANNED",
  "features": [
    {
      "type": "Feature",
      "geometry": {
        "type": "Point",
        "coordinates": [
          145.922425,
          -17.345151
        ]
      },
      "properties": {
        "EVENT_ID": "24FN4200",
        "TYPE": "PLANNED",
        "CUSTOMERS_AFFECTED": "9",
        "REASON": "The loss of supply is to replace power poles and improve the electricity network",
        "STATUS": "Crews working on-site",
        "START": "7:30AM 13 Apr 2024",
        "EST_FIX_TIME": "4:30PM 13 Apr 2024",
        "STREETS": "EASTWOOD ST",
        "SUBURBS": "BABINDA"
      }
    },
    {
      "type": "Feature",
      "geometry": {
        "type": "Point",
        "coordinates": [
          145.927103,
          -17.343743
        ]
      },
      "properties": {
        "EVENT_ID": "24FN4206",
        "TYPE": "PLANNED",
        "CUSTOMERS_AFFECTED": "14",
        "REASON": "The loss of supply is to replace power poles and improve the electricity network",
        "STATUS": "Crews working on-site",
        "START": "1:55PM 13 Apr 2024",
        "EST_FIX_TIME": "4:30PM 13 Apr 2024",
        "STREETS": "COUNCIL LANE, PEEVER RD",
        "SUBURBS": "BABINDA"
      }
    },
    {
      "type": "Feature",
      "geometry": {
        "type": "Point",
        "coordinates": [
          145.566437,
          -16.897957
        ]
      },
      "properties": {
        "EVENT_ID": "24FN4222",
        "TYPE": "PLANNED",
        "CUSTOMERS_AFFECTED": "47",
        "REASON": "The loss of supply is to replace power poles and improve the electricity network",
        "STATUS": "Crews working on-site",
        "START": "8:30AM 13 Apr 2024",
        "EST_FIX_TIME": "4:30PM 13 Apr 2024",
        "STREETS": "BRICKWORKS RD, CLOHESY RIVER RD, GRIEVSON RD, KENNEDY HWY, KOAH RD, O'NEIL CL, PALM VALLEY RD",
        "SUBURBS": "CLOHESY RIVER, GROVE CREEK, KOAH, KURANDA"
      }
    },
    {
      "type": "Feature",
      "geometry": {
        "type": "Point",
        "coordinates": [
          151.472242,
          -27.300012
        ]
      },
      "properties": {
        "EVENT_ID": "24SW6815",
        "TYPE": "PLANNED",
        "CUSTOMERS_AFFECTED": "267",
        "REASON": "The loss of supply is to replace power poles and improve the electricity network",
        "STATUS": "Crews working on-site",
        "START": "8:06AM 13 Apr 2024",
        "EST_FIX_TIME": "3:00PM 13 Apr 2024",
        "STREETS": "AUCHMAH RD, BARON ST, BLAXLAND RD, BOWDEN RD, BOWENVILLE ACLAND RD, BOWENVILLE MOOLA RD, BOWENVILLE-BLAXLAND RD, BOWENVILLE-IRVINGDALE RD, BOWENVILLE-NORWIN RD, BRYMAROO IRVINGDALE RD, BRYMAROO-IRVINGDALE RD, CARTER RD, COCKBURN ST, DARR RD, DUKE ST, EARL ST, GERAGHTYS RD, GRANT ST, IRVINGDALE POST OFFICE RD, IRVINGDALE RD, IRVINGDALE SOUTH RD, IRVINGDALE ST, IRVINGDALE-BLAXLAND RD, IRVINGDALE-BOWENVILLE RD, JONDARYAN EVANSLEA RD, JONDARYAN NUNGIL RD, JONDARYAN SABINE RD, JONDARYAN ST RUTH RD, LAGOON ST, LEAHY RD, MALU BOWENVILLE RD, MALU RD, MALU-BOWENVILLE RD, MASONS RD, MIRTSCHINS RD, NICHOLSON ST, OAKLEIGH PARK RD, OMARA ST, PROSPECT RD, RAILWAY ST, RICHARDS RD, RUTLEDGE RD, SCOTT RD, SHORT ST, STATION ST, TATES RD, TOOTH ST, WAINUI RD, WAINUI SOLDIERS RD, WARREGO HWY",
        "SUBURBS": "BLAXLAND, BOWENVILLE, DALBY, FORMARTIN, IRVINGDALE, JONDARYAN, MALU"
      }
    }
  ],
  "company": "Ergon",
  "state": "Current",
  "extracted": "1712986501.288179"
}
