{
  "type": "FeatureCollection",
  "name": "PLANNED",
  "features": [
    {
      "type": "Feature",
      "geometry": {
        "type": "Point",
        "coordinates": [
          145.743728,
          -17.019471
        ]
      },
      "properties": {
        "EVENT_ID": "24FN4534",
        "TYPE": "PLANNED",
        "CUSTOMERS_AFFECTED": "21",
        "REASON": "The loss of supply is to upgrade equipment to meet customer demand for electricity and to improve reliability of supply in the area",
        "STATUS": "Work scheduled",
        "START": "11:30PM 11 Apr 2024",
        "EST_FIX_TIME": "5:00AM 12 Apr 2024",
        "STREETS": "BRUCE HWY, GREEN ST, MILL RD",
        "SUBURBS": "EDMONTON"
      }
    },
    {
      "type": "Feature",
      "geometry": {
        "type": "Point",
        "coordinates": [
          149.158724,
          -21.121565
        ]
      },
      "properties": {
        "EVENT_ID": "24MK3032",
        "TYPE": "PLANNED",
        "CUSTOMERS_AFFECTED": "9",
        "REASON": "The loss of supply is to allow maintenance of the electricity network",
        "STATUS": "Crews working on-site",
        "START": "10:00PM 11 Apr 2024",
        "EST_FIX_TIME": "5:00AM 12 Apr 2024",
        "STREETS": "GRANDVIEW DR, MALCOMSON ST",
        "SUBURBS": "MOUNT PLEASANT, NORTH MACKAY"
      }
    },
    {
      "type": "Feature",
      "geometry": {
        "type": "Point",
        "coordinates": [
          148.56082,
          -20.333835
        ]
      },
      "properties": {
        "EVENT_ID": "24MK3263",
        "TYPE": "PLANNED",
        "CUSTOMERS_AFFECTED": "69",
        "REASON": "The loss of supply is to replace power poles and improve the electricity network",
        "STATUS": "Crews working on-site",
        "START": "9:39PM 11 Apr 2024",
        "EST_FIX_TIME": "4:00AM 12 Apr 2024",
        "STREETS": "BLAIR RD, BONNIE SPRINGS RD, BRUCE HWY, DOUGHERTY RD, DOUGHERTYS RD, MORANINO RD, OSSIE DR, PARKINSON RD, SAWMILL DR",
        "SUBURBS": "BLOOMSBURY, CRYSTAL BROOK, FOXDALE, GREGORY, GREGORY RIVER, MYRTLEVALE"
      }
    }
  ],
  "company": "Ergon",
  "state": "Current",
  "extracted": "1712836805.742168"
}
