{
  "type": "FeatureCollection",
  "name": "PLANNED",
  "features": [
    {
      "type": "Feature",
      "geometry": {
        "type": "Point",
        "coordinates": [
          151.244315,
          -23.829121
        ]
      },
      "properties": {
        "EVENT_ID": "23CA17996",
        "TYPE": "PLANNED",
        "CUSTOMERS_AFFECTED": "72",
        "REASON": "The loss of supply is to allow maintenance of the electricity network",
        "STATUS": "Work scheduled",
        "START": "5:00PM 24 Mar 2024",
        "EST_FIX_TIME": "9:00PM 24 Mar 2024",
        "STREETS": "ALF O'ROURKE DR, BRYAN JORDAN DR, LEO ZUSSINO DR, UNMETERED SUPPLY",
        "SUBURBS": "GLADSTONE, GLADSTONE CENTRAL"
      }
    }
  ],
  "company": "Ergon",
  "state": "Current",
  "extracted": "1711262702.978024"
}
