{
  "type": "FeatureCollection",
  "name": "PLANNED",
  "features": [
    {
      "type": "Feature",
      "geometry": {
        "type": "Point",
        "coordinates": [
          138.113789,
          -19.892434
        ]
      },
      "properties": {
        "EVENT_ID": "25NQ2545",
        "TYPE": "PLANNED",
        "CUSTOMERS_AFFECTED": "55",
        "REASON": "The loss of supply is to replace power poles and improve the electricity network",
        "STATUS": "Crews working on-site",
        "START": "8:00AM 06 Mar 2025",
        "EST_FIX_TIME": "5:00PM 06 Mar 2025",
        "STREETS": "AUSTRAL ST, BARKLY HWY, BARKLY ST, BEAUMONT ST, CRONIN ST, FRANCES ST, KENNEDY ST, MORRISON ST, NOWRANIE ST, WONGA ST",
        "SUBURBS": "CAMOOWEAL"
      }
    }
  ],
  "company": "Ergon",
  "state": "Current",
  "extracted": "1741244701.245189"
}
