{
  "type": "FeatureCollection",
  "name": "PLANNED",
  "features": [
    {
      "type": "Feature",
      "geometry": {
        "type": "Point",
        "coordinates": [
          146.708124,
          -19.317408
        ]
      },
      "properties": {
        "EVENT_ID": "24NQ6933",
        "TYPE": "PLANNED",
        "CUSTOMERS_AFFECTED": "252",
        "REASON": "The loss of supply is to allow maintenance of the electricity network",
        "STATUS": "Crews working on-site",
        "START": "9:10AM 01 May 2024",
        "EST_FIX_TIME": "6:00PM 01 May 2024",
        "STREETS": "BECK DR, CHELSEA DR, FAIRWAY CL, GOLF LINKS DR, HERVEY RANGE RD, HERVEYS RANGE RD, NINETEENTH AVE, RIVIERA CCT",
        "SUBURBS": "BOHLE PLAINS, CONDON, KIRWAN"
      }
    },
    {
      "type": "Feature",
      "geometry": {
        "type": "Point",
        "coordinates": [
          152.715274,
          -25.540434
        ]
      },
      "properties": {
        "EVENT_ID": "24WB4862",
        "TYPE": "PLANNED",
        "CUSTOMERS_AFFECTED": "8",
        "REASON": "The loss of supply is to allow maintenance of the electricity network",
        "STATUS": "Crews working on-site",
        "START": "7:06AM 01 May 2024",
        "EST_FIX_TIME": "5:30PM 01 May 2024",
        "STREETS": "CAMBRIDGE ST, GRANVILLE TCE",
        "SUBURBS": "GRANVILLE"
      }
    },
    {
      "type": "Feature",
      "geometry": {
        "type": "Point",
        "coordinates": [
          152.717467,
          -25.54245
        ]
      },
      "properties": {
        "EVENT_ID": "24WB4865",
        "TYPE": "PLANNED",
        "CUSTOMERS_AFFECTED": "17",
        "REASON": "The loss of supply is to allow maintenance of the electricity network",
        "STATUS": "Crews working on-site",
        "START": "7:05AM 01 May 2024",
        "EST_FIX_TIME": "5:30PM 01 May 2024",
        "STREETS": "DUNDAS ST, MAY ST, MIRAMONT ST",
        "SUBURBS": "GRANVILLE"
      }
    },
    {
      "type": "Feature",
      "geometry": {
        "type": "Point",
        "coordinates": [
          152.721514,
          -25.546403
        ]
      },
      "properties": {
        "EVENT_ID": "24WB4870",
        "TYPE": "PLANNED",
        "CUSTOMERS_AFFECTED": "5",
        "REASON": "The loss of supply is to allow maintenance of the electricity network",
        "STATUS": "Crews working on-site",
        "START": "7:04AM 01 May 2024",
        "EST_FIX_TIME": "5:30PM 01 May 2024",
        "STREETS": "HOFFMAN ST, PULLER ST",
        "SUBURBS": "GRANVILLE"
      }
    }
  ],
  "company": "Ergon",
  "state": "Current",
  "extracted": "1714548301.228359"
}
