{
  "type": "FeatureCollection",
  "name": "PLANNED",
  "features": [
    {
      "type": "Feature",
      "geometry": {
        "type": "Point",
        "coordinates": [
          145.630557,
          -17.473518
        ]
      },
      "properties": {
        "EVENT_ID": "24FN3436",
        "TYPE": "PLANNED",
        "CUSTOMERS_AFFECTED": "44",
        "REASON": "The loss of supply is to replace power poles and improve the electricity network",
        "STATUS": "Crews working on-site",
        "START": "8:30AM 16 Mar 2024",
        "EST_FIX_TIME": "4:30PM 16 Mar 2024",
        "STREETS": "ELLINJAA RD, FRASER RD, JUBB RD, MOREGATTA RD, PURCELL RD, THERESA CREEK RD, WOOLLEYS RD",
        "SUBURBS": "MILLAA MILLAA"
      }
    },
    {
      "type": "Feature",
      "geometry": {
        "type": "Point",
        "coordinates": [
          149.141546,
          -21.153971
        ]
      },
      "properties": {
        "EVENT_ID": "24MK2435",
        "TYPE": "PLANNED",
        "CUSTOMERS_AFFECTED": "45",
        "REASON": "The loss of supply is to upgrade equipment to meet customer demand for electricity and to improve reliability of supply in the area",
        "STATUS": "Crews working on-site",
        "START": "9:00AM 16 Mar 2024",
        "EST_FIX_TIME": "4:00PM 16 Mar 2024",
        "STREETS": "GIBSONS RD, HORSE AND JOCKEY RD, LANSDOWNE RD, MEADOWLANDS RD, WALKERS RD",
        "SUBURBS": "RACECOURSE"
      }
    }
  ],
  "company": "Ergon",
  "state": "Current",
  "extracted": "1710567603.549231"
}
