{
  "type": "FeatureCollection",
  "name": "PLANNED",
  "features": [
    {
      "type": "Feature",
      "geometry": {
        "type": "Point",
        "coordinates": [
          146.331519,
          -18.526706
        ]
      },
      "properties": {
        "EVENT_ID": "24NQ7319",
        "TYPE": "PLANNED",
        "CUSTOMERS_AFFECTED": "4",
        "REASON": "The loss of supply is to connect new customers to the electricity network",
        "STATUS": "Crews working on-site",
        "START": "12:30PM 17 May 2024",
        "EST_FIX_TIME": "3:30PM 30 May 2024",
        "STREETS": "DUNGENESS RD, KEAST ST",
        "SUBURBS": "LUCINDA"
      }
    },
    {
      "type": "Feature",
      "geometry": {
        "type": "Point",
        "coordinates": [
          146.761823,
          -19.292452
        ]
      },
      "properties": {
        "EVENT_ID": "24NQ8320",
        "TYPE": "PLANNED",
        "CUSTOMERS_AFFECTED": "147",
        "REASON": "The loss of supply is to upgrade equipment to meet customer demand for electricity and to improve reliability of supply in the area",
        "STATUS": "Work scheduled",
        "START": "9:00PM 27 May 2024",
        "EST_FIX_TIME": "3:00AM 28 May 2024",
        "STREETS": "ACHERON AVE, ARUNTA ST, BIARA ST, BIGGS ST, CARCOOLA ST, CHARLES ST, EVES ST, GOSPER ST, HIVERS ST, ILLOURA ST, NATHAN ST, PASKIN ST, RAYNOR ST, WILLIS ST, WOTTON ST",
        "SUBURBS": "AITKENVALE, CRANBROOK, HEATLEY, VINCENT"
      }
    },
    {
      "type": "Feature",
      "geometry": {
        "type": "Point",
        "coordinates": [
          151.862812,
          -27.543376
        ]
      },
      "properties": {
        "EVENT_ID": "24SW8582",
        "TYPE": "PLANNED",
        "CUSTOMERS_AFFECTED": "15",
        "REASON": "The loss of supply is to allow maintenance of the electricity network",
        "STATUS": "Work scheduled",
        "START": "8:00PM 27 May 2024",
        "EST_FIX_TIME": "12:00AM 28 May 2024",
        "STREETS": "CROCKER CT, HEINEMANN RD, WHEELDON CT",
        "SUBURBS": "WELLCAMP"
      }
    }
  ],
  "company": "Ergon",
  "state": "Current",
  "extracted": "1716799201.428564"
}
