{
  "type": "FeatureCollection",
  "name": "PLANNED",
  "features": [
    {
      "type": "Feature",
      "geometry": {
        "type": "Point",
        "coordinates": [
          148.567541,
          -21.058434
        ]
      },
      "properties": {
        "EVENT_ID": "24MK2777",
        "TYPE": "PLANNED",
        "CUSTOMERS_AFFECTED": "37",
        "REASON": "The loss of supply is to remove vegetation growing near powerlines",
        "STATUS": "Crews working on-site",
        "START": "10:00AM 19 Apr 2024",
        "EST_FIX_TIME": "4:00PM 19 Apr 2024",
        "STREETS": "CHELMANS RD, DALRYMPLE RD, FREDRICKSONS RD, SNAKE RD",
        "SUBURBS": "DALRYMPLE HEIGHTS, EUNGELLA"
      }
    }
  ],
  "company": "Ergon",
  "state": "Current",
  "extracted": "1713508501.331262"
}
