{
  "type": "FeatureCollection",
  "name": "PLANNED",
  "features": [
    {
      "type": "Feature",
      "geometry": {
        "type": "Point",
        "coordinates": [
          150.059767,
          -23.412264
        ]
      },
      "properties": {
        "EVENT_ID": "24CA5453",
        "TYPE": "PLANNED",
        "CUSTOMERS_AFFECTED": "19",
        "REASON": "The loss of supply is to replace power poles and improve the electricity network",
        "STATUS": "Crews working on-site",
        "START": "8:31AM 04 May 2024",
        "EST_FIX_TIME": "2:30PM 04 May 2024",
        "STREETS": "BARRETT RD, COMMANCHE RD, DONOVAN RD, ROSEWOOD RD, STANWELL WAROULA RD, THIRSTY CREEK RD, TOOWARRA RD",
        "SUBURBS": "GOGANGO, KALAPA, MORINISH, MORINISH SOUTH, STANWELL"
      }
    },
    {
      "type": "Feature",
      "geometry": {
        "type": "Point",
        "coordinates": [
          146.254957,
          -20.072696
        ]
      },
      "properties": {
        "EVENT_ID": "24NQ7468",
        "TYPE": "PLANNED",
        "CUSTOMERS_AFFECTED": "90",
        "REASON": "The loss of supply is to connect new customers to the electricity network",
        "STATUS": "Crews working on-site",
        "START": "8:56AM 04 May 2024",
        "EST_FIX_TIME": "2:30PM 04 May 2024",
        "STREETS": "CHARLOTTE ST, CLARKE ST, ELIZABETH ST, JANE ST, KING ST, MACDONALD ST, MARION ST, PLANT ST, RICHARDS LANE, RUTHERFORD LANE, RUTHERFORD ST, STUBLEY ST",
        "SUBURBS": "CHARTERS TOWERS, CHARTERS TOWERS CITY, RICHMOND HILL"
      }
    }
  ],
  "company": "Ergon",
  "state": "Current",
  "extracted": "1714794902.853456"
}
