{
  "type": "FeatureCollection",
  "name": "PLANNED",
  "features": [
    {
      "type": "Feature",
      "geometry": {
        "type": "Point",
        "coordinates": [
          150.638305,
          -23.646863
        ]
      },
      "properties": {
        "EVENT_ID": "24CA5222",
        "TYPE": "PLANNED",
        "CUSTOMERS_AFFECTED": "4",
        "REASON": "The loss of supply is to replace power poles and improve the electricity network",
        "STATUS": "Crews working on-site",
        "START": "5:56PM 27 Apr 2024",
        "EST_FIX_TIME": "6:56PM 27 Apr 2024",
        "STREETS": "HIGH ST, MAGAZINE RD, SIX MILE RD",
        "SUBURBS": "BAJOOL"
      }
    },
    {
      "type": "Feature",
      "geometry": {
        "type": "Point",
        "coordinates": [
          142.75018,
          -20.469853
        ]
      },
      "properties": {
        "EVENT_ID": "24NQ6414",
        "TYPE": "PLANNED",
        "CUSTOMERS_AFFECTED": "4",
        "REASON": "The loss of supply is to replace power poles and improve the electricity network",
        "STATUS": "Crews working on-site",
        "START": "8:30AM 27 Apr 2024",
        "EST_FIX_TIME": "7:00PM 27 Apr 2024",
        "STREETS": "ARTESIAN DOWNS STATION, GRACEDALE STATION, LILYVALE STATION, MORUNGLE STATION",
        "SUBURBS": "MAXWELTON"
      }
    }
  ],
  "company": "Ergon",
  "state": "Current",
  "extracted": "1714206301.747269"
}
