{
  "type": "FeatureCollection",
  "name": "PLANNED",
  "features": [
    {
      "type": "Feature",
      "geometry": {
        "type": "Point",
        "coordinates": [
          149.423949,
          -24.177657
        ]
      },
      "properties": {
        "EVENT_ID": "24CA4685",
        "TYPE": "PLANNED",
        "CUSTOMERS_AFFECTED": "369",
        "REASON": "The loss of supply is to upgrade equipment to meet customer demand for electricity and to improve reliability of supply in the area",
        "STATUS": "Crews working on-site",
        "START": "9:00AM 02 May 2024",
        "EST_FIX_TIME": "6:00PM 02 May 2024",
        "STREETS": "BLAIR ST, BOOTH ST, CARBINE ST, CENTRAL CREEK RD, CRESSBROOK ST, DOOLAN CRES, DOOLEY ST, DOYLE ST, FREEMAN ST, GEORGE CL, GREEN ST, HILL ST, KEMP ST, MATE MATE ST, MIMOSA CK RD, MUNNS DR, OFF MUNNS DR, RANKIN ST, RICHARD CL, RICHARDSON ST, SAUNDERS LANE, SWAIN ST",
        "SUBURBS": "WOORABINDA"
      }
    },
    {
      "type": "Feature",
      "geometry": {
        "type": "Point",
        "coordinates": [
          146.256023,
          -18.553086
        ]
      },
      "properties": {
        "EVENT_ID": "24NQ6757",
        "TYPE": "PLANNED",
        "CUSTOMERS_AFFECTED": "23",
        "REASON": "The loss of supply is to allow maintenance of the electricity network",
        "STATUS": "Crews working on-site",
        "START": "8:31AM 02 May 2024",
        "EST_FIX_TIME": "5:30PM 02 May 2024",
        "STREETS": "BULLOCK PADDOCK RD, CARUSO'S RD, KEMPS RD",
        "SUBURBS": "MACKNADE"
      }
    }
  ],
  "company": "Ergon",
  "state": "Current",
  "extracted": "1714632601.254833"
}
