{
  "type": "FeatureCollection",
  "name": "PLANNED",
  "features": [
    {
      "type": "Feature",
      "geometry": {
        "type": "Point",
        "coordinates": [
          148.593565,
          -20.705943
        ]
      },
      "properties": {
        "EVENT_ID": "24MK3390",
        "TYPE": "PLANNED",
        "CUSTOMERS_AFFECTED": "35",
        "REASON": "The loss of supply is to upgrade equipment to meet customer demand for electricity and to improve reliability of supply in the area",
        "STATUS": "Crews working on-site",
        "START": "8:42AM 21 Apr 2024",
        "EST_FIX_TIME": "5:10PM 21 Apr 2024",
        "STREETS": "BLOOMSBURY BACK RD, BRUCE HWY, DON HAUSKNECHT RD, DOUGHERTYS RD, MIDGE POINT RD, O'DONNELLS RD",
        "SUBURBS": "BLOOMSBURY, MIDGE POINT"
      }
    },
    {
      "type": "Feature",
      "geometry": {
        "type": "Point",
        "coordinates": [
          148.588691,
          -20.714068
        ]
      },
      "properties": {
        "EVENT_ID": "24MK3391",
        "TYPE": "PLANNED",
        "CUSTOMERS_AFFECTED": "8",
        "REASON": "The loss of supply is to upgrade equipment to meet customer demand for electricity and to improve reliability of supply in the area",
        "STATUS": "Crews working on-site",
        "START": "8:30AM 21 Apr 2024",
        "EST_FIX_TIME": "5:10PM 21 Apr 2024",
        "STREETS": "DOUGHERTYS RD, FORBES RD",
        "SUBURBS": "BLOOMSBURY"
      }
    }
  ],
  "company": "Ergon",
  "state": "Current",
  "extracted": "1713681601.198243"
}
