{
  "type": "FeatureCollection",
  "name": "PLANNED",
  "features": [
    {
      "type": "Feature",
      "geometry": {
        "type": "Point",
        "coordinates": [
          139.179775,
          -16.664853
        ]
      },
      "properties": {
        "EVENT_ID": "24FN3093",
        "TYPE": "PLANNED",
        "CUSTOMERS_AFFECTED": "7",
        "REASON": "The loss of supply is to replace power poles and improve the electricity network",
        "STATUS": "Crews working on-site",
        "START": "8:30AM 07 Apr 2024",
        "EST_FIX_TIME": "3:30PM 07 Apr 2024",
        "STREETS": "DJINKYA ST, JINKIYA ST, KATHAN KATHAN ST, LARDIL ST",
        "SUBURBS": "GUNUNA"
      }
    },
    {
      "type": "Feature",
      "geometry": {
        "type": "Point",
        "coordinates": [
          148.235663,
          -20.006367
        ]
      },
      "properties": {
        "EVENT_ID": "24NQ6156",
        "TYPE": "PLANNED",
        "CUSTOMERS_AFFECTED": "312",
        "REASON": "The loss of supply is to allow maintenance of the electricity network",
        "STATUS": "Crews working on-site",
        "START": "8:30AM 07 Apr 2024",
        "EST_FIX_TIME": "3:00PM 07 Apr 2024",
        "STREETS": "ANDERSON AVE, ARTHUR ST, BUNTING ST, CHRISTISON ST, DENISON ST, DON ST, GLENVILLE PL, HERBERT ST, HILL ST, HONEY PL, JOHN ST, JOHNSTON ST, LEICHHARDT LANE, LEICHHARDT ST, LIVINGSTONE ST, MARTIN ST, MITCHELL ST, PILCHER PL, RAYNER ST, REYNOLDS ST, RICHMOND RD, SINCLAIR ST, SPROULE ST, SUNSET CRES, WEST ST, YARDLEY CT",
        "SUBURBS": "BOWEN"
      }
    },
    {
      "type": "Feature",
      "geometry": {
        "type": "Point",
        "coordinates": [
          152.664697,
          -25.807974
        ]
      },
      "properties": {
        "EVENT_ID": "24WB4105",
        "TYPE": "PLANNED",
        "CUSTOMERS_AFFECTED": "114",
        "REASON": "The loss of supply is to allow maintenance of the electricity network",
        "STATUS": "Crews working on-site",
        "START": "8:34AM 07 Apr 2024",
        "EST_FIX_TIME": "3:30PM 07 Apr 2024",
        "STREETS": "ACACIA RD, BAND HALL RD, BANKSIA RD, CASSIA RD, CEDAR RD, COOMBES RD, CYPRESS RD, EUCALYPTUS RD, FORESTRY RD, KEENES RD, MACKELLAR ST, MAHOGANY RD, MEREDITH RD, MESSMATE RD, MILL ST, STOTTENVILLE RD, TALEGALLA DR",
        "SUBURBS": "BAUPLE, TALEGALLA WEIR, TALLAGALLA"
      }
    }
  ],
  "company": "Ergon",
  "state": "Current",
  "extracted": "1712465401.159792"
}
