{
  "type": "FeatureCollection",
  "name": "PLANNED",
  "features": [
    {
      "type": "Feature",
      "geometry": {
        "type": "Point",
        "coordinates": [
          145.881182,
          -17.535992
        ]
      },
      "properties": {
        "EVENT_ID": "24FN4537",
        "TYPE": "PLANNED",
        "CUSTOMERS_AFFECTED": "4",
        "REASON": "The loss of supply is to allow emergency maintenance of the electricity network",
        "STATUS": "Crews working on-site",
        "START": "8:30AM 20 Apr 2024",
        "EST_FIX_TIME": "4:45PM 20 Apr 2024",
        "STREETS": "MARUFF RD",
        "SUBURBS": "NERADA"
      }
    },
    {
      "type": "Feature",
      "geometry": {
        "type": "Point",
        "coordinates": [
          148.964,
          -21.04405
        ]
      },
      "properties": {
        "EVENT_ID": "24MK3025",
        "TYPE": "PLANNED",
        "CUSTOMERS_AFFECTED": "20",
        "REASON": "The loss of supply is to upgrade equipment to meet customer demand for electricity and to improve reliability of supply in the area",
        "STATUS": "Crews working on-site",
        "START": "8:30AM 20 Apr 2024",
        "EST_FIX_TIME": "4:00PM 20 Apr 2024",
        "STREETS": "GIUMELLIS RD, MT JUKES RD, NICOL RD, RUTLANDS RD, YAKAPARI SEAFORTH RD",
        "SUBURBS": "KUTTABUL, SEAFORTH, YAKAPARI"
      }
    }
  ],
  "company": "Ergon",
  "state": "Current",
  "extracted": "1713593401.456506"
}
