{
  "type": "FeatureCollection",
  "name": "PLANNED",
  "features": [
    {
      "type": "Feature",
      "geometry": {
        "type": "Point",
        "coordinates": [
          146.769179,
          -19.189886
        ]
      },
      "properties": {
        "EVENT_ID": "24NQ5103",
        "TYPE": "PLANNED",
        "CUSTOMERS_AFFECTED": "2",
        "REASON": "The loss of supply is to allow maintenance of the electricity network",
        "STATUS": "Crews working on-site",
        "START": "8:30AM 19 Mar 2024",
        "EST_FIX_TIME": "6:00PM 19 Mar 2024",
        "STREETS": "CAPE PALLARENDA RD, MARLOW ST",
        "SUBURBS": "PALLARENDA"
      }
    },
    {
      "type": "Feature",
      "geometry": {
        "type": "Point",
        "coordinates": [
          144.488076,
          -21.516873
        ]
      },
      "properties": {
        "EVENT_ID": "24NQ5484",
        "TYPE": "PLANNED",
        "CUSTOMERS_AFFECTED": "66",
        "REASON": "The loss of supply is to replace power poles and improve the electricity network",
        "STATUS": "Crews working on-site",
        "START": "8:30AM 19 Mar 2024",
        "EST_FIX_TIME": "6:00PM 19 Mar 2024",
        "STREETS": "ARRARA STATION, BANJOURA STATION, BARRAGUNDA STATION, BIBIL STATION, BIRRICANNIA STATION, BRAEMAR STATION, CAMERON DOWNS STATION, EASTFIELD STATION, ELABE STATION, ELWELL STATION, ENSAY STATION, EVANDALE STATION, EVANDALE WEST STATION, GLENARIFF STATION, HOLMLEIGH STATION, HOMELEIGH STATION, HUGHENDEN STATION, INVERESK STATION, IONA STATION, JANEVILLE STATION, JIREENA STATION, KENTLE DNS STATION, LANDSBOROUGH STATION, LUDGATE STATION, MOKANA STATION, MT DEVLIN STATION, MT ETNA STATION, NEEDLEWOOD STATION, PERONNE STATION, REDCLIFFE STATION, STENHOUSE STATION, STRATHROY STATION, THORNTON STATION, WATERVIEW STATION, WEST EVANDALE STATION, ZARA STATION",
        "SUBURBS": "HUGHENDEN, MUTTABURRA, PRAIRIE"
      }
    },
    {
      "type": "Feature",
      "geometry": {
        "type": "Point",
        "coordinates": [
          152.376965,
          -24.865325
        ]
      },
      "properties": {
        "EVENT_ID": "24WB3365",
        "TYPE": "PLANNED",
        "CUSTOMERS_AFFECTED": "29",
        "REASON": "The loss of supply is to replace power poles and improve the electricity network",
        "STATUS": "Work scheduled",
        "START": "8:00PM 19 Mar 2024",
        "EST_FIX_TIME": "1:00AM 20 Mar 2024",
        "STREETS": "GERRARD ST, STEPTOE ST",
        "SUBURBS": "BUNDABERG, BUNDABERG EAST"
      }
    }
  ],
  "company": "Ergon",
  "state": "Current",
  "extracted": "1710833704.572459"
}
