{
  "type": "FeatureCollection",
  "name": "PLANNED",
  "features": [
    {
      "type": "Feature",
      "geometry": {
        "type": "Point",
        "coordinates": [
          149.281379,
          -21.678019
        ]
      },
      "properties": {
        "EVENT_ID": "24MK2457",
        "TYPE": "PLANNED",
        "CUSTOMERS_AFFECTED": "151",
        "REASON": "The loss of supply is to replace power poles and improve the electricity network",
        "STATUS": "Crews working on-site",
        "START": "9:00AM 23 Mar 2024",
        "EST_FIX_TIME": "4:30PM 23 Mar 2024",
        "STREETS": "BRUCE HWY, CAMPBELLS RD, CRAIG RD, HARRIS RD, HATFIELD RD, PRICE RD, R WILLIAMS RD, RAND RD, ROCKY DAM RD, SANGIORGIO RD, SMART RD, TEDLANDS RD, THOMPSON RD, TURNORS PADDOCK RD, WOOD RD",
        "SUBURBS": "KOUMALA, MOUNT CHRISTIAN"
      }
    },
    {
      "type": "Feature",
      "geometry": {
        "type": "Point",
        "coordinates": [
          139.489749,
          -20.697318
        ]
      },
      "properties": {
        "EVENT_ID": "24NQ4971",
        "TYPE": "PLANNED",
        "CUSTOMERS_AFFECTED": "124",
        "REASON": "The loss of supply is to upgrade equipment to meet customer demand for electricity and to improve reliability of supply in the area",
        "STATUS": "Crews working on-site",
        "START": "8:30AM 23 Mar 2024",
        "EST_FIX_TIME": "4:30PM 23 Mar 2024",
        "STREETS": "ABAU ST, BARKLY HWY, DARU ST, ERAP ST, GAZELLE ST, GOROKA ST, URQUHART ST",
        "SUBURBS": "MILES END, SOLDIERS HILL"
      }
    },
    {
      "type": "Feature",
      "geometry": {
        "type": "Point",
        "coordinates": [
          148.243633,
          -20.01218
        ]
      },
      "properties": {
        "EVENT_ID": "24NQ5304",
        "TYPE": "PLANNED",
        "CUSTOMERS_AFFECTED": "10",
        "REASON": "The loss of supply is to replace power poles and improve the electricity network",
        "STATUS": "Crews working on-site",
        "START": "7:48AM 23 Mar 2024",
        "EST_FIX_TIME": "4:00PM 23 Mar 2024",
        "STREETS": "GORDON ST",
        "SUBURBS": "BOWEN"
      }
    },
    {
      "type": "Feature",
      "geometry": {
        "type": "Point",
        "coordinates": [
          151.810007,
          -27.615081
        ]
      },
      "properties": {
        "EVENT_ID": "24SW5840",
        "TYPE": "PLANNED",
        "CUSTOMERS_AFFECTED": "6",
        "REASON": "The loss of supply is to replace power poles and improve the electricity network",
        "STATUS": "Crews working on-site",
        "START": "8:30AM 23 Mar 2024",
        "EST_FIX_TIME": "3:00PM 23 Mar 2024",
        "STREETS": "HOLBROOK RD",
        "SUBURBS": "WESTBROOK"
      }
    }
  ],
  "company": "Ergon",
  "state": "Current",
  "extracted": "1711171805.50951"
}
