{
  "type": "FeatureCollection",
  "name": "PLANNED",
  "features": [
    {
      "type": "Feature",
      "geometry": {
        "type": "Point",
        "coordinates": [
          149.43412,
          -21.716372
        ]
      },
      "properties": {
        "EVENT_ID": "24MK4579",
        "TYPE": "PLANNED",
        "CUSTOMERS_AFFECTED": "2",
        "REASON": "The loss of supply is to connect new customers to the electricity network",
        "STATUS": "Crews working on-site",
        "START": "8:00AM 10 Jun 2024",
        "EST_FIX_TIME": "2:30PM 14 Jun 2024",
        "STREETS": "NOTCH POINT RD",
        "SUBURBS": "ILBILBIE"
      }
    },
    {
      "type": "Feature",
      "geometry": {
        "type": "Point",
        "coordinates": [
          147.801326,
          -20.562816
        ]
      },
      "properties": {
        "EVENT_ID": "24NQ8806",
        "TYPE": "PLANNED",
        "CUSTOMERS_AFFECTED": "2",
        "REASON": "The loss of supply is to replace power poles and improve the electricity network",
        "STATUS": "Crews working on-site",
        "START": "6:00AM 10 Jun 2024",
        "EST_FIX_TIME": "6:00PM 12 Jun 2024",
        "STREETS": "SCOTTVILLE RD",
        "SUBURBS": "COLLINSVILLE"
      }
    }
  ],
  "company": "Ergon",
  "state": "Current",
  "extracted": "1718089203.294018"
}
