{
  "type": "FeatureCollection",
  "name": "PLANNED",
  "features": [
    {
      "type": "Feature",
      "geometry": {
        "type": "Point",
        "coordinates": [
          147.426903,
          -19.613749
        ]
      },
      "properties": {
        "EVENT_ID": "25NQ3030",
        "TYPE": "PLANNED",
        "CUSTOMERS_AFFECTED": "5",
        "REASON": "The loss of supply is to allow maintenance of the electricity network",
        "STATUS": "Crews working on-site",
        "START": "2:17PM 10 Mar 2025",
        "EST_FIX_TIME": "4:00PM 10 Mar 2025",
        "STREETS": "KILRIE RD, MCDESME RD",
        "SUBURBS": "AYR, MCDESME"
      }
    }
  ],
  "company": "Ergon",
  "state": "Current",
  "extracted": "1741584302.667543"
}
