{
  "type": "FeatureCollection",
  "name": "PLANNED",
  "features": [
    {
      "type": "Feature",
      "geometry": {
        "type": "Point",
        "coordinates": [
          149.148686,
          -21.212794
        ]
      },
      "properties": {
        "EVENT_ID": "25MK0915",
        "TYPE": "PLANNED",
        "CUSTOMERS_AFFECTED": "2",
        "REASON": "The loss of supply is to connect new customers to the electricity network",
        "STATUS": "Crews working on-site",
        "START": "7:00AM 08 Mar 2025",
        "EST_FIX_TIME": "5:00PM 08 Mar 2025",
        "STREETS": "MAIN ST",
        "SUBURBS": "BAKERS CREEK"
      }
    }
  ],
  "company": "Ergon",
  "state": "Current",
  "extracted": "1741415101.553209"
}
