{
  "type": "FeatureCollection",
  "name": "PLANNED",
  "features": [
    {
      "type": "Feature",
      "geometry": {
        "type": "Point",
        "coordinates": [
          151.994188,
          -26.666066
        ]
      },
      "properties": {
        "EVENT_ID": "24WB6031",
        "TYPE": "PLANNED",
        "CUSTOMERS_AFFECTED": "345",
        "REASON": "The loss of supply is to connect new customers to the electricity network",
        "STATUS": "Crews working on-site",
        "START": "8:30AM 23 Jun 2024",
        "EST_FIX_TIME": "4:30PM 23 Jun 2024",
        "STREETS": "BIRDIE ST, BUNKER AVE, CAIRNS ST, CHESTER ST, CLUB CT, D'AGUILAR HWY, DALBY ST, DOWNING ST, DRAYTON ST, EAGLE ST, ELK ST, FAIRWAY DR, FITZROY ST, FLAG ST, GIPPS ST, GREY ST, HAWTHORNE ST, HENRY ST, HOWLETT LANE, KEOGH CT, KINGAROY RD, LEE CT, NORMANBY ST",
        "SUBURBS": "NANANGO"
      }
    }
  ],
  "company": "Ergon",
  "state": "Current",
  "extracted": "1719123901.597242"
}
