{
  "type": "FeatureCollection",
  "name": "PLANNED",
  "features": [
    {
      "type": "Feature",
      "geometry": {
        "type": "Point",
        "coordinates": [
          149.198932,
          -21.154724
        ]
      },
      "properties": {
        "EVENT_ID": "24MK2426",
        "TYPE": "PLANNED",
        "CUSTOMERS_AFFECTED": "100",
        "REASON": "The loss of supply is to replace power poles and improve the electricity network",
        "STATUS": "Crews working on-site",
        "START": "11:48AM 15 Mar 2024",
        "EST_FIX_TIME": "5:30PM 15 Mar 2024",
        "STREETS": "BINNINGTON ESP, EVAN ST, HENDERSON ST, HOEY ST, ILUKA CT, WEIR ST",
        "SUBURBS": "EAST MACKAY, MACKAY"
      }
    },
    {
      "type": "Feature",
      "geometry": {
        "type": "Point",
        "coordinates": [
          152.339732,
          -24.882347
        ]
      },
      "properties": {
        "EVENT_ID": "24WB2379",
        "TYPE": "PLANNED",
        "CUSTOMERS_AFFECTED": "2",
        "REASON": "The loss of supply is to allow maintenance of the electricity network",
        "STATUS": "Crews working on-site",
        "START": "7:05AM 15 Mar 2024",
        "EST_FIX_TIME": "5:00PM 15 Mar 2024",
        "STREETS": "SVENSSON ST",
        "SUBURBS": "SVENSSON HEIGHTS"
      }
    },
    {
      "type": "Feature",
      "geometry": {
        "type": "Point",
        "coordinates": [
          152.325984,
          -24.883859
        ]
      },
      "properties": {
        "EVENT_ID": "24WB2839",
        "TYPE": "PLANNED",
        "CUSTOMERS_AFFECTED": "8",
        "REASON": "The loss of supply is to allow maintenance of the electricity network",
        "STATUS": "Crews working on-site",
        "START": "7:06AM 15 Mar 2024",
        "EST_FIX_TIME": "5:00PM 15 Mar 2024",
        "STREETS": "PICKETT ST, RICHARDS ST",
        "SUBURBS": "SVENSSON HEIGHTS"
      }
    },
    {
      "type": "Feature",
      "geometry": {
        "type": "Point",
        "coordinates": [
          152.327202,
          -24.882385
        ]
      },
      "properties": {
        "EVENT_ID": "24WB2841",
        "TYPE": "PLANNED",
        "CUSTOMERS_AFFECTED": "9",
        "REASON": "The loss of supply is to allow maintenance of the electricity network",
        "STATUS": "Crews working on-site",
        "START": "7:05AM 15 Mar 2024",
        "EST_FIX_TIME": "5:00PM 15 Mar 2024",
        "STREETS": "PICKETT ST",
        "SUBURBS": "SVENSSON HEIGHTS"
      }
    }
  ],
  "company": "Ergon",
  "state": "Current",
  "extracted": "1710483305.205432"
}
