{
  "type": "FeatureCollection",
  "name": "PLANNED",
  "features": [
    {
      "type": "Feature",
      "geometry": {
        "type": "Point",
        "coordinates": [
          149.219171,
          -21.124518
        ]
      },
      "properties": {
        "EVENT_ID": "24MK2232",
        "TYPE": "PLANNED",
        "CUSTOMERS_AFFECTED": "21",
        "REASON": "The loss of supply is to upgrade equipment to meet customer demand for electricity and to improve reliability of supply in the area",
        "STATUS": "Crews working on-site",
        "START": "8:33AM 08 Mar 2024",
        "EST_FIX_TIME": "6:00PM 08 Mar 2024",
        "STREETS": "DERIVA CT, EAST POINT DR, SEASHORE CRES, SOL DR",
        "SUBURBS": "MACKAY HARBOUR"
      }
    }
  ],
  "company": "Ergon",
  "state": "Current",
  "extracted": "1709880001.586254"
}
