{
  "type": "FeatureCollection",
  "name": "PLANNED",
  "features": [
    {
      "type": "Feature",
      "geometry": {
        "type": "Point",
        "coordinates": [
          149.085683,
          -21.022174
        ]
      },
      "properties": {
        "EVENT_ID": "24MK3013",
        "TYPE": "PLANNED",
        "CUSTOMERS_AFFECTED": "71",
        "REASON": "The loss of supply is to remove vegetation growing near powerlines",
        "STATUS": "Crews working on-site",
        "START": "8:00AM 05 May 2024",
        "EST_FIX_TIME": "11:00AM 05 May 2024",
        "STREETS": "BARROW HILL RD, GALEA CT, LE GARDES RD, THOMPSON CT",
        "SUBURBS": "HABANA"
      }
    },
    {
      "type": "Feature",
      "geometry": {
        "type": "Point",
        "coordinates": [
          152.098545,
          -27.091975
        ]
      },
      "properties": {
        "EVENT_ID": "24SW7374",
        "TYPE": "PLANNED",
        "CUSTOMERS_AFFECTED": "20",
        "REASON": "The loss of supply is to allow emergency maintenance of the electricity network",
        "STATUS": "Work scheduled",
        "START": "9:00AM 05 May 2024",
        "EST_FIX_TIME": "2:00PM 05 May 2024",
        "STREETS": "ANDURAMBA RANGE RD, BOWEN RD, HAWKINS RD, HEATHER RD, MARSHALL RD, MCGREEVY RD, NUKINENDA RD, PETTIE RD, WATERHOLE GULLY RD",
        "SUBURBS": "ANDURAMBA, CROWS NEST, NUKINENDA, PIERCES CREEK"
      }
    },
    {
      "type": "Feature",
      "geometry": {
        "type": "Point",
        "coordinates": [
          151.956634,
          -27.569932
        ]
      },
      "properties": {
        "EVENT_ID": "24SW7699",
        "TYPE": "PLANNED",
        "CUSTOMERS_AFFECTED": "14",
        "REASON": "The loss of supply is to allow maintenance of the electricity network",
        "STATUS": "Crews working on-site",
        "START": "6:29AM 05 May 2024",
        "EST_FIX_TIME": "12:00PM 05 May 2024",
        "STREETS": "HUME ST, JAMES ST",
        "SUBURBS": "SOUTH TOOWOOMBA"
      }
    }
  ],
  "company": "Ergon",
  "state": "Current",
  "extracted": "1714861805.504974"
}
