{
  "type": "FeatureCollection",
  "name": "PLANNED",
  "features": [
    {
      "type": "Feature",
      "geometry": {
        "type": "Point",
        "coordinates": [
          148.049825,
          -22.004009
        ]
      },
      "properties": {
        "EVENT_ID": "24MK2856",
        "TYPE": "PLANNED",
        "CUSTOMERS_AFFECTED": "127",
        "REASON": "The loss of supply is to upgrade equipment to meet customer demand for electricity and to improve reliability of supply in the area",
        "STATUS": "Crews working on-site",
        "START": "9:59AM 05 Apr 2024",
        "EST_FIX_TIME": "5:00PM 05 Apr 2024",
        "STREETS": "ARCHER DR, BENNETT CT, BURKE DR, FRASER ST, LAWRENCE ST, LAWSON DR, LESLIE DR, MILLS AVE, MORANBAH ACCESS RD, OXLEY DR, REEF DR, TALLON ST",
        "SUBURBS": "MORANBAH"
      }
    }
  ],
  "company": "Ergon",
  "state": "Current",
  "extracted": "1712297704.509035"
}
