{
  "type": "FeatureCollection",
  "name": "PLANNED",
  "features": [
    {
      "type": "Feature",
      "geometry": {
        "type": "Point",
        "coordinates": [
          151.203598,
          -23.971911
        ]
      },
      "properties": {
        "EVENT_ID": "25CA3091",
        "TYPE": "PLANNED",
        "CUSTOMERS_AFFECTED": "29",
        "REASON": "The loss of supply is to replace power poles and improve the electricity network",
        "STATUS": "Crews working on-site",
        "START": "9:07AM 06 Mar 2025",
        "EST_FIX_TIME": "4:00PM 06 Mar 2025",
        "STREETS": "ARTHUR HULME WAY, BRENDONNA RD, BRUCE HWY, OLD COACH RD, TALABA RD, WEEROONA RD",
        "SUBURBS": "BURUA, CALLIOPE"
      }
    },
    {
      "type": "Feature",
      "geometry": {
        "type": "Point",
        "coordinates": [
          148.204001,
          -20.045272
        ]
      },
      "properties": {
        "EVENT_ID": "25NQ1079",
        "TYPE": "PLANNED",
        "CUSTOMERS_AFFECTED": "2",
        "REASON": "The loss of supply is to upgrade equipment to meet customer demand for electricity and to improve reliability of supply in the area",
        "STATUS": "Crews working on-site",
        "START": "8:00AM 03 Mar 2025",
        "EST_FIX_TIME": "2:00PM 07 Mar 2025",
        "STREETS": "BOOTOOLOO RD",
        "SUBURBS": "BOWEN"
      }
    },
    {
      "type": "Feature",
      "geometry": {
        "type": "Point",
        "coordinates": [
          138.113789,
          -19.892434
        ]
      },
      "properties": {
        "EVENT_ID": "25NQ2545",
        "TYPE": "PLANNED",
        "CUSTOMERS_AFFECTED": "55",
        "REASON": "The loss of supply is to replace power poles and improve the electricity network",
        "STATUS": "Crews working on-site",
        "START": "8:00AM 06 Mar 2025",
        "EST_FIX_TIME": "5:00PM 06 Mar 2025",
        "STREETS": "AUSTRAL ST, BARKLY HWY, BARKLY ST, BEAUMONT ST, CRONIN ST, FRANCES ST, KENNEDY ST, MORRISON ST, NOWRANIE ST, WONGA ST",
        "SUBURBS": "CAMOOWEAL"
      }
    },
    {
      "type": "Feature",
      "geometry": {
        "type": "Point",
        "coordinates": [
          148.136253,
          -20.1207
        ]
      },
      "properties": {
        "EVENT_ID": "25NQ2585",
        "TYPE": "PLANNED",
        "CUSTOMERS_AFFECTED": "2",
        "REASON": "The loss of supply is to replace power poles and improve the electricity network",
        "STATUS": "Crews working on-site",
        "START": "8:00AM 06 Mar 2025",
        "EST_FIX_TIME": "3:00PM 06 Mar 2025",
        "STREETS": "MOUNT DANGAR RD",
        "SUBURBS": "BOWEN"
      }
    }
  ],
  "company": "Ergon",
  "state": "Current",
  "extracted": "1741239601.36286"
}
