{
  "type": "FeatureCollection",
  "name": "PLANNED",
  "features": [
    {
      "type": "Feature",
      "geometry": {
        "type": "Point",
        "coordinates": [
          146.331519,
          -18.526706
        ]
      },
      "properties": {
        "EVENT_ID": "24NQ7319",
        "TYPE": "PLANNED",
        "CUSTOMERS_AFFECTED": "4",
        "REASON": "The loss of supply is to connect new customers to the electricity network",
        "STATUS": "Crews working on-site",
        "START": "12:30PM 17 May 2024",
        "EST_FIX_TIME": "3:30PM 06 Jun 2024",
        "STREETS": "DUNGENESS RD, KEAST ST",
        "SUBURBS": "LUCINDA"
      }
    },
    {
      "type": "Feature",
      "geometry": {
        "type": "Point",
        "coordinates": [
          146.809736,
          -19.266423
        ]
      },
      "properties": {
        "EVENT_ID": "24NQ8368",
        "TYPE": "PLANNED",
        "CUSTOMERS_AFFECTED": "2",
        "REASON": "The loss of supply is to upgrade equipment to meet customer demand for electricity and to improve reliability of supply in the area",
        "STATUS": "Crews working on-site",
        "START": "8:36AM 04 Jun 2024",
        "EST_FIX_TIME": "5:30PM 04 Jun 2024",
        "STREETS": "FLINDERS ST",
        "SUBURBS": "TOWNSVILLE CITY"
      }
    },
    {
      "type": "Feature",
      "geometry": {
        "type": "Point",
        "coordinates": [
          139.752538,
          -21.283911
        ]
      },
      "properties": {
        "EVENT_ID": "24NQ8623",
        "TYPE": "PLANNED",
        "CUSTOMERS_AFFECTED": "23",
        "REASON": "The loss of supply is to replace power poles and improve the electricity network",
        "STATUS": "Crews working on-site",
        "START": "8:30AM 04 Jun 2024",
        "EST_FIX_TIME": "4:30PM 04 Jun 2024",
        "STREETS": "ASHOVER STATION, BUSHY PARK STATION, DUCHESS RD, DUKE ST, FLYNN RAIL SDNG, MALBONVALE STATION, MAYFIELD STATION, RIFLE CREEK, RIFLE CREEK STATION, STANBROKE STATION, YAPPO CREEK",
        "SUBURBS": "DUCHESS, MORNINGTON, MOUNT ISA"
      }
    },
    {
      "type": "Feature",
      "geometry": {
        "type": "Point",
        "coordinates": [
          152.641485,
          -25.937272
        ]
      },
      "properties": {
        "EVENT_ID": "24WB5160",
        "TYPE": "PLANNED",
        "CUSTOMERS_AFFECTED": "28",
        "REASON": "The loss of supply is to connect new customers to the electricity network",
        "STATUS": "Crews working on-site",
        "START": "8:30AM 04 Jun 2024",
        "EST_FIX_TIME": "4:30PM 04 Jun 2024",
        "STREETS": "ARBORCRESCENT RD, ARBORFIVE RD",
        "SUBURBS": "GLENWOOD"
      }
    }
  ],
  "company": "Ergon",
  "state": "Current",
  "extracted": "1717482300.377732"
}
