{
  "type": "FeatureCollection",
  "name": "PLANNED",
  "features": [
    {
      "type": "Feature",
      "geometry": {
        "type": "Point",
        "coordinates": [
          148.839517,
          -20.937943
        ]
      },
      "properties": {
        "EVENT_ID": "24MK3920",
        "TYPE": "PLANNED",
        "CUSTOMERS_AFFECTED": "516",
        "REASON": "The loss of supply is to allow emergency maintenance of the electricity network",
        "STATUS": "Crews working on-site",
        "START": "8:12AM 23 May 2024",
        "EST_FIX_TIME": "5:00PM 23 May 2024",
        "STREETS": "AMBRYM ST, BOGGA RD, BRUCE HWY, BUTHURRA STATION RD, CALEN MOUNT CHARLTON RD, CHURCH ST, CLANSIDE RD, CLIFFES RD, CLYDE MCLEANS RD, FAIRCHILDS RD, FERRIS RD, GEEBERGA BUTHURRA RD, GIFFORDS RD, HOLDINGS RD, HOWLANDS RD, J JOHNSONS RD, JANSENS RD, JIM MCLEANS RD, JOHANSENS RDWY, JOHNSONS RD, KOLIJO MT PELION RD, LANDING RD, LITTLE BOGGA RD, LONG MILE RD, MACKENZIES RD, MCDERMOTTS RD, MCINTYRE ST, MCKAYS RD, MCLEANS RD, MIRANI MOUNT OSSA RD, MOUNT OSSA RD, MOUNT OSSA SEAFORTH RD, MOUNT PELION RD, MT OSSA MIRANI RD, MT OSSA SCHOOL RD, MULHERINS RD, MURRAY RD, NARPI RD, OLD BOWEN RD, ONE MILE CREEK RD, PACES RD, PAUL BURGER RD, PRATTS RD, REPULSE ESP, ST HELENS BEACH RD, STARKEYS RD, STOCKERS RD, SURPRISE CREEK RD, TOOMAS RD, TREVEYS RD, WATTS RD, WE WAK RD, WEWAK RD, WILLS RD, WOOTAROO ESP",
        "SUBURBS": "BUTHURRA, CALEN, KOLIJO, KUTTABUL, MACKAY, MIRANI, MOUNT CHARLTON, MOUNT OSSA, MOUNT PELION, SEAFORTH, ST HELENS BEACH"
      }
    },
    {
      "type": "Feature",
      "geometry": {
        "type": "Point",
        "coordinates": [
          146.331519,
          -18.526706
        ]
      },
      "properties": {
        "EVENT_ID": "24NQ7319",
        "TYPE": "PLANNED",
        "CUSTOMERS_AFFECTED": "4",
        "REASON": "The loss of supply is to connect new customers to the electricity network",
        "STATUS": "Crews working on-site",
        "START": "12:30PM 17 May 2024",
        "EST_FIX_TIME": "3:30PM 30 May 2024",
        "STREETS": "DUNGENESS RD, KEAST ST",
        "SUBURBS": "LUCINDA"
      }
    },
    {
      "type": "Feature",
      "geometry": {
        "type": "Point",
        "coordinates": [
          147.130221,
          -26.423308
        ]
      },
      "properties": {
        "EVENT_ID": "24SW8326",
        "TYPE": "PLANNED",
        "CUSTOMERS_AFFECTED": "2",
        "REASON": "The loss of supply is to carry out training for Switching Operators",
        "STATUS": "Crews working on-site",
        "START": "9:01AM 23 May 2024",
        "EST_FIX_TIME": "5:00PM 23 May 2024",
        "STREETS": "HILLGROVE RD",
        "SUBURBS": "MORVEN"
      }
    }
  ],
  "company": "Ergon",
  "state": "Current",
  "extracted": "1716446401.434406"
}
