{
  "type": "FeatureCollection",
  "name": "PLANNED",
  "features": [
    {
      "type": "Feature",
      "geometry": {
        "type": "Point",
        "coordinates": [
          150.725778,
          -23.174192
        ]
      },
      "properties": {
        "EVENT_ID": "24CA3652",
        "TYPE": "PLANNED",
        "CUSTOMERS_AFFECTED": "69",
        "REASON": "The loss of supply is to replace power poles and improve the electricity network",
        "STATUS": "Crews working on-site",
        "START": "9:00AM 12 Mar 2024",
        "EST_FIX_TIME": "3:00PM 12 Mar 2024",
        "STREETS": "COUCOM RD, DARAMBAL RD, HIDDEN VALLEY RD, NEWTONNE RD, TANBY P O RD, TANBY RD",
        "SUBURBS": "HIDDEN VALLEY, TANBY, YEPPOON"
      }
    },
    {
      "type": "Feature",
      "geometry": {
        "type": "Point",
        "coordinates": [
          146.782538,
          -19.265348
        ]
      },
      "properties": {
        "EVENT_ID": "24NQ4976",
        "TYPE": "PLANNED",
        "CUSTOMERS_AFFECTED": "12",
        "REASON": "The loss of supply is to replace power poles and improve the electricity network",
        "STATUS": "Crews working on-site",
        "START": "10:43AM 12 Mar 2024",
        "EST_FIX_TIME": "4:30PM 12 Mar 2024",
        "STREETS": "GORDEN ST",
        "SUBURBS": "GARBUTT"
      }
    },
    {
      "type": "Feature",
      "geometry": {
        "type": "Point",
        "coordinates": [
          151.255342,
          -27.182624
        ]
      },
      "properties": {
        "EVENT_ID": "24SW4838",
        "TYPE": "PLANNED",
        "CUSTOMERS_AFFECTED": "3",
        "REASON": "The loss of supply is to replace power poles and improve the electricity network",
        "STATUS": "Crews working on-site",
        "START": "12:04PM 12 Mar 2024",
        "EST_FIX_TIME": "3:00PM 12 Mar 2024",
        "STREETS": "HIGGINBOTHAM ST, WOOD ST",
        "SUBURBS": "DALBY"
      }
    },
    {
      "type": "Feature",
      "geometry": {
        "type": "Point",
        "coordinates": [
          151.262425,
          -27.192388
        ]
      },
      "properties": {
        "EVENT_ID": "24SW4840",
        "TYPE": "PLANNED",
        "CUSTOMERS_AFFECTED": "4",
        "REASON": "The loss of supply is to replace power poles and improve the electricity network",
        "STATUS": "Crews working on-site",
        "START": "12:04PM 12 Mar 2024",
        "EST_FIX_TIME": "3:00PM 12 Mar 2024",
        "STREETS": "ALFRED ST, WOOD ST",
        "SUBURBS": "DALBY"
      }
    }
  ],
  "company": "Ergon",
  "state": "Current",
  "extracted": "1710214501.822027"
}
