{
  "type": "FeatureCollection",
  "name": "PLANNED",
  "features": [
    {
      "type": "Feature",
      "geometry": {
        "type": "Point",
        "coordinates": [
          149.532494,
          -27.459247
        ]
      },
      "properties": {
        "EVENT_ID": "24SW7211",
        "TYPE": "PLANNED",
        "CUSTOMERS_AFFECTED": "48",
        "REASON": "The loss of supply is to connect new customers to the electricity network",
        "STATUS": "Crews working on-site",
        "START": "9:00AM 23 Apr 2024",
        "EST_FIX_TIME": "4:00PM 24 Apr 2024",
        "STREETS": "GLENEARN RD, HURST RD, MEANDARRA TALWOOD RD, NEW SETTLERS RD, PENFOLDS RD, ROCKY GLEN RD, STUARTS RD, TEELBA RD, TELGAZLIE RD, UNGABILLA RD",
        "SUBURBS": "COOMRITH, FLINTON, GLENMORGAN, INGLESTONE, MEANDARRA, SURAT, TEELBA"
      }
    }
  ],
  "company": "Ergon",
  "state": "Current",
  "extracted": "1713871501.209415"
}
