{
  "type": "FeatureCollection",
  "name": "PLANNED",
  "features": [
    {
      "type": "Feature",
      "geometry": {
        "type": "Point",
        "coordinates": [
          148.128345,
          -28.122533
        ]
      },
      "properties": {
        "EVENT_ID": "24SW4765",
        "TYPE": "PLANNED",
        "CUSTOMERS_AFFECTED": "2837",
        "REASON": "The loss of supply is to upgrade equipment to meet customer demand for electricity and to improve reliability of supply in the area",
        "STATUS": "Work scheduled",
        "START": "10:00PM 18 Mar 2024",
        "EST_FIX_TIME": "11:30PM 18 Mar 2024",
        "STREETS": "ABBATOIR ACCESS RD, ABBIEGLASSIE-BOATMAN RD, ACACIA CT, ALBERT ST, ALDRIDGE ST, ALFRED ST, ANDERSON LANE, ANDREW ST, ANNE ST, ARTHUR ST, BACHAN BYPASS RD, BALLANDOOL RD, BALLANGARRY RD, BALONE HWY, BALONNE HWY, BALONNE ST, BARLEE ST, BARWON HWY, BEARDMORE PL, BEESONS ST, BEGONIA RD, BELMORE ST, BELTANA RD, BIMBLE RD, BOLINS RD, BOLLON DIRRANBANDI RD, BOLLON RD, BOOLIGAR RD, BOOLIGAR ST, BORONIA AVE, BOWEN ST, BOWHAY RD, BROSNAN ST, BUCHANS BYPASS RD, BUCKENBAH RD, BUCKINBAH WEIR RD, BULLAMON ST, BUNDORAN RD, BURKE ST, CANARVON HWY, CARDIFF RD, CARNARVON HWY, CARNATION AVE, CASHEL VALE RD, CASTLEREAGH HWY, CHAMBERS RD, CHARLES ST, CHELMER RD, CHURCH ST, COMMISSIONERS POINT RD, CORACK RD, COWILDI ST, CRESCENT VALE RD, CROTHERS ST, CROTTY RD, CUBBIE RD, CUNNYANA RD, CURRAWILDI ST, CUTLER CT, DALKEITH RD, DAVIRTON RD, DAWES ST, DAYMAR WEENGALLON RD, DAYMAR-THALLON RD, DIAMOND TANK RD, DILQUI RD, DIRRANBANDI-BOLLON RD, DIRRANBANDI-HEBEL RD, DIRRANBANDI-MUNGINDI RD, DIRRANBANDI-ST GEORGE RD, DUNBAR RD, DUNKERRY RD, DUNWINNIE RD, DYBALL ST, EAST GOONDULLA RD, EASTON RD, ELIZABETH ST, EUMERELLA SOUTH RD, EURABA RD, FERNLEE RD, FLINTON RD, GARAH ST, GEORGE ST, GLENCO RD, GOLF COURSE RD, GOLF LINKS RD, GREY ST, GUNNINDADDY RD, HANNAH ST, HEBEL RD, HENRY ST, HERBERT ST, HILL ST, HOCKING ST, HOLLYMOUNT RD, HOMEBOIN-ST GEORGE RD, HONEYMAH LANE, HOOLAVALE RD, HORACE ST, HOWE ST, HUME ST, HUTT ST, IAN PAUL RD, IDA ST, INGABY RD, ISABEL ST, ISLES ST, J E KELLY RD, JAKELWAR GOODOOGA RD, JAKELWAR-GOODOOGA RD, JAMES ST, JANE ST, JE KELLY RD, JHELUM PLAINS RD, JOHNSTON RD, KEMP RD, KENNY LANE, KILCUMMIN RD, KILROY ST, KIRBY ST, KLINGE LANE, KNIGHTS RD, KOOMALAH RD, KOOROON RD, KULKI RD, LIGNUM AVE, LINDORES ST, LITTLETON RD, LOCHNAGAR RD, LOGAN LANE, LOOP RD, LOWER DAYMAR RD, LOWER PLAINS RD, MAIN ST, MARANOA RD, MARGARET ST, MARIE ST, MARY ST, MAUD ST, MAYES ST, MCCARTHY ST, MCDONALD RD, MCDONNELL AVE, MCGAHAN ST, MIDDLE RD, MINNUM RD, MITCHELL BOLLON RD, MITCHELL RD, MITCHELL ST, MITCHELL ST GEORGE RD, MITCHELL-BOLLON RD, MOOLABAH RD, MOONIE HWY, MOORE ST, MULGA DOWNS RD, MUNDA MUNDA RD, MUNDAH RD, MUNDALEE RD, MUNRO RD, MUNRO ST, MURCHISON ST, MURRA MURRA RD, MYALL AVE, NARINE RD, NARLINE RD, NOONDOO MUNGINDI RD, NORTH GRADNA RD, NORTH KULKI RD, NORTH WEENGALLON RD, NULKY RD, OPENBAH RD, PASSMAN ST, PERKINS ST, PHILLIP ST, PINE PARK RD, PINE ST, PINEHILLS RD, POWRUNNA RD, RAILWAY RES, RAILWAY ST, RAMALIS RD, RAMALLI RD, RICHARDSON ST, RIMMER RD, ROBERT ST, ROE ST, ROMA-SOUTHERN RD, RUNNYMEDE RD, RUTHERGLEN RD, SALMON RD, SANDLEWOOD RD, SANDY LANDS RD, SATUR RD, SCHOOL RD, SCOTT ST, SECRET PLAINS RD, SHIRLO RD, SOUTH DAYMAR RD, SOUTHERN RD, SPRINGWELL RD, ST GEORGE RD, ST GEORGE RIVER RD, ST GEORGE-DIRRANBANDI RD, ST GEORGES TCE, STERNS ST, STUBBY LANE, STURT ST, SUNSET VALLEY RD, TALWOOD RD, TAMBINGEY RD, TAYLOR ST, TEELBA RD, THALLON RD, THE TERRACE, THEODORE ST, THOMBY RD, THOMPSONS RD, THUNGABY RD, THURRAGGI ST, TRACKERS CROSSING RD, TRAFALGAR RD, TURVEY CT, ULA ULA RD, UNITY RD, UNKNOWN RD, VICTORIA ST, WAGOO RD, WALLAM ST, WANDIBINDLE RD, WANGANUI RD, WARRIE RD, WATTLE DR, WEATHERALL ST, WERIBONE ST, WEST HARAN RD, WEST OF THREE WAYS RD, WHYENBAH RD, WHYTES RD, WILLIAM ST, WILLOWTHAL RD, WONOLGA RD, WOODBURN RD, WOODLAWN LANE, WOOLERBILLA RD, WOOLERINA RD, YILGANGANDI RD",
        "SUBURBS": "BARGUNYAH, BELINGARA, BOLLON, BOOLBA, CUNNAMULLA, DAREEL, DAYMAR, DIRRANBANDI, FLINTON, GLENMORGAN, HEBEL, MITCHELL, MUNGINDI, NINDIGULLY, ROMA, ST GEORGE, SURAT, TALWOOD, THALLON, WEENGALLON, WESTMAR, WYCOMBE"
      }
    }
  ],
  "company": "Ergon",
  "state": "Current",
  "extracted": "1710755401.202233"
}
