{
  "type": "FeatureCollection",
  "name": "PLANNED",
  "features": [
    {
      "type": "Feature",
      "geometry": {
        "type": "Point",
        "coordinates": [
          147.423217,
          -19.58195
        ]
      },
      "properties": {
        "EVENT_ID": "24NQ7131",
        "TYPE": "PLANNED",
        "CUSTOMERS_AFFECTED": "2",
        "REASON": "The loss of supply is to replace power poles and improve the electricity network",
        "STATUS": "Crews working on-site",
        "START": "8:50AM 28 Apr 2024",
        "EST_FIX_TIME": "5:00PM 28 Apr 2024",
        "STREETS": "NORHAM RD, RITA ISLAND RD",
        "SUBURBS": "AYR"
      }
    }
  ],
  "company": "Ergon",
  "state": "Current",
  "extracted": "1714287001.50442"
}
