{
  "type": "FeatureCollection",
  "name": "PLANNED",
  "features": [
    {
      "type": "Feature",
      "geometry": {
        "type": "Point",
        "coordinates": [
          148.59185,
          -20.751327
        ]
      },
      "properties": {
        "EVENT_ID": "24MK2182",
        "TYPE": "PLANNED",
        "CUSTOMERS_AFFECTED": "22",
        "REASON": "The loss of supply is to upgrade equipment to meet customer demand for electricity and to improve reliability of supply in the area",
        "STATUS": "Crews working on-site",
        "START": "11:00AM 05 Apr 2024",
        "EST_FIX_TIME": "4:00PM 05 Apr 2024",
        "STREETS": "CONSIDINES RD, JEPPESENS RD, OLIVETTAS RD",
        "SUBURBS": "BLOOMSBURY, ELAROO"
      }
    },
    {
      "type": "Feature",
      "geometry": {
        "type": "Point",
        "coordinates": [
          148.049825,
          -22.004009
        ]
      },
      "properties": {
        "EVENT_ID": "24MK2856",
        "TYPE": "PLANNED",
        "CUSTOMERS_AFFECTED": "127",
        "REASON": "The loss of supply is to upgrade equipment to meet customer demand for electricity and to improve reliability of supply in the area",
        "STATUS": "Crews working on-site",
        "START": "9:59AM 05 Apr 2024",
        "EST_FIX_TIME": "4:00PM 05 Apr 2024",
        "STREETS": "ARCHER DR, BENNETT CT, BURKE DR, FRASER ST, LAWRENCE ST, LAWSON DR, LESLIE DR, MILLS AVE, MORANBAH ACCESS RD, OXLEY DR, REEF DR, TALLON ST",
        "SUBURBS": "MORANBAH"
      }
    },
    {
      "type": "Feature",
      "geometry": {
        "type": "Point",
        "coordinates": [
          149.150451,
          -21.201493
        ]
      },
      "properties": {
        "EVENT_ID": "24MK2896",
        "TYPE": "PLANNED",
        "CUSTOMERS_AFFECTED": "57",
        "REASON": "The loss of supply is to upgrade equipment to meet customer demand for electricity and to improve reliability of supply in the area",
        "STATUS": "Crews working on-site",
        "START": "8:00AM 05 Apr 2024",
        "EST_FIX_TIME": "4:30PM 05 Apr 2024",
        "STREETS": "BRUCE HWY, COOKS LANE, FLINDERS CT, MAIN ST, SOUTHLINK DR, TOM THUMB CT",
        "SUBURBS": "BAKERS CREEK"
      }
    },
    {
      "type": "Feature",
      "geometry": {
        "type": "Point",
        "coordinates": [
          146.811395,
          -19.272934
        ]
      },
      "properties": {
        "EVENT_ID": "24NQ5813",
        "TYPE": "PLANNED",
        "CUSTOMERS_AFFECTED": "4",
        "REASON": "The loss of supply is to allow maintenance of the electricity network",
        "STATUS": "Crews working on-site",
        "START": "12:30PM 05 Apr 2024",
        "EST_FIX_TIME": "4:00PM 05 Apr 2024",
        "STREETS": "BOUNDARY ST",
        "SUBURBS": "RAILWAY ESTATE"
      }
    }
  ],
  "company": "Ergon",
  "state": "Current",
  "extracted": "1712296501.05749"
}
