{
  "type": "FeatureCollection",
  "name": "PLANNED",
  "features": [
    {
      "type": "Feature",
      "geometry": {
        "type": "Point",
        "coordinates": [
          148.822647,
          -21.091816
        ]
      },
      "properties": {
        "EVENT_ID": "24MK3412",
        "TYPE": "PLANNED",
        "CUSTOMERS_AFFECTED": "80",
        "REASON": "The loss of supply is to allow maintenance of the electricity network",
        "STATUS": "Crews working on-site",
        "START": "9:00AM 30 Apr 2024",
        "EST_FIX_TIME": "5:00PM 30 Apr 2024",
        "STREETS": "BRADSHAWS RD, COYNES RD, GARNHAM MORROWS RD, GEEBERGA BUTHURRA RD, MCFAULS RD, MORRIS RD, MOUNT MARTIN GAP RD, MOUNT MARTIN LOOP RD, MOUNT MARTIN RD, MOUNT TOBY RD, SUGARLOAF RD",
        "SUBURBS": "KUTTABUL, MOUNT MARTIN"
      }
    },
    {
      "type": "Feature",
      "geometry": {
        "type": "Point",
        "coordinates": [
          139.733528,
          -21.30178
        ]
      },
      "properties": {
        "EVENT_ID": "24NQ6982",
        "TYPE": "PLANNED",
        "CUSTOMERS_AFFECTED": "93",
        "REASON": "The loss of supply is to replace power poles and improve the electricity network",
        "STATUS": "Crews working on-site",
        "START": "8:50AM 30 Apr 2024",
        "EST_FIX_TIME": "5:00PM 30 Apr 2024",
        "STREETS": "ASHOVER STATION, ATNYER ST, BOULIA RD, BUSHY PARK STATION, CARMODY ST, DIAMANTINA DEVELOPMENTAL RD, DILLON ST, DUCHESS RD, DUKE ST, FLYNN RAIL SDNG, LETHAM ST, MALBONVALE STATION, MARK ST, MATHESON ST, MAYFIELD STATION, RIFLE CREEK, RIFLE CREEK STATION, SPORTS PDE, STANBROKE STATION, YAPPO CREEK",
        "SUBURBS": "ALPURRURULAM, DAJARRA, DUCHESS, MORNINGTON, MOUNT ISA"
      }
    }
  ],
  "company": "Ergon",
  "state": "Current",
  "extracted": "1714459504.063537"
}
