{
  "type": "FeatureCollection",
  "name": "PLANNED",
  "features": [
    {
      "type": "Feature",
      "geometry": {
        "type": "Point",
        "coordinates": [
          148.728963,
          -21.198159
        ]
      },
      "properties": {
        "EVENT_ID": "24MK3047",
        "TYPE": "PLANNED",
        "CUSTOMERS_AFFECTED": "231",
        "REASON": "The loss of supply is to replace power poles and improve the electricity network",
        "STATUS": "Crews working on-site",
        "START": "7:33AM 21 Apr 2024",
        "EST_FIX_TIME": "3:30PM 21 Apr 2024",
        "STREETS": "BRADFORDS RD, DUNWOLD CATTLE CREEK RD, ELSIE NASH ST, GARGETT-MIA MIA RD, HEAD MENKINS RD, HEAD VASSALLOS RD, HEADS RD, L SHEWS RD, LUCAS PADDOCK RD, LUSCOMBES RD, MACKAY EUNGELLA RD, MIA MIA ST, NEILSEN OMANDS RD, OMAND NEILSON RD, PINNACLE SEPTIMUS RD, PINNACLE ST, PINNACLE STATION RD, PUP CREEK RD, RAILWAY ST, SCOTTS RD, SEPTIMUS CATTLE CREEK RD, SEPTIMUS RD, WALKER FINNS RD, WILLIAMS RD",
        "SUBURBS": "GARGETT, PINNACLE, SEPTIMUS"
      }
    },
    {
      "type": "Feature",
      "geometry": {
        "type": "Point",
        "coordinates": [
          148.593565,
          -20.705943
        ]
      },
      "properties": {
        "EVENT_ID": "24MK3390",
        "TYPE": "PLANNED",
        "CUSTOMERS_AFFECTED": "35",
        "REASON": "The loss of supply is to upgrade equipment to meet customer demand for electricity and to improve reliability of supply in the area",
        "STATUS": "Crews working on-site",
        "START": "8:42AM 21 Apr 2024",
        "EST_FIX_TIME": "3:00PM 21 Apr 2024",
        "STREETS": "BLOOMSBURY BACK RD, BRUCE HWY, DON HAUSKNECHT RD, DOUGHERTYS RD, MIDGE POINT RD, O'DONNELLS RD",
        "SUBURBS": "BLOOMSBURY, MIDGE POINT"
      }
    },
    {
      "type": "Feature",
      "geometry": {
        "type": "Point",
        "coordinates": [
          148.588691,
          -20.714068
        ]
      },
      "properties": {
        "EVENT_ID": "24MK3391",
        "TYPE": "PLANNED",
        "CUSTOMERS_AFFECTED": "8",
        "REASON": "The loss of supply is to upgrade equipment to meet customer demand for electricity and to improve reliability of supply in the area",
        "STATUS": "Crews working on-site",
        "START": "8:30AM 21 Apr 2024",
        "EST_FIX_TIME": "3:00PM 21 Apr 2024",
        "STREETS": "DOUGHERTYS RD, FORBES RD",
        "SUBURBS": "BLOOMSBURY"
      }
    },
    {
      "type": "Feature",
      "geometry": {
        "type": "Point",
        "coordinates": [
          151.714178,
          -27.422354
        ]
      },
      "properties": {
        "EVENT_ID": "24SW7139",
        "TYPE": "PLANNED",
        "CUSTOMERS_AFFECTED": "35",
        "REASON": "The loss of supply is to replace power poles and improve the electricity network",
        "STATUS": "Crews working on-site",
        "START": "8:17AM 21 Apr 2024",
        "EST_FIX_TIME": "6:00PM 21 Apr 2024",
        "STREETS": "COOYAR RD, FITZPATRICK ST, GAYLE ST, KATRINA ST, ROSS ST",
        "SUBURBS": "OAKEY"
      }
    }
  ],
  "company": "Ergon",
  "state": "Current",
  "extracted": "1713676201.205248"
}
