{
  "type": "FeatureCollection",
  "name": "PLANNED",
  "features": [
    {
      "type": "Feature",
      "geometry": {
        "type": "Point",
        "coordinates": [
          143.359688,
          -20.415797
        ]
      },
      "properties": {
        "EVENT_ID": "24NQ4486",
        "TYPE": "PLANNED",
        "CUSTOMERS_AFFECTED": "31",
        "REASON": "The loss of supply is to replace power poles and improve the electricity network",
        "STATUS": "Crews working on-site",
        "START": "8:01AM 10 Mar 2024",
        "EST_FIX_TIME": "3:00PM 10 Mar 2024",
        "STREETS": "ACTON STATION, BALD HILLS STATION, BURLEIGH STATION, COALBROOK STATION, DONCASTER STATION, FLINDERS HWY, GRAMPIAN VALLEY STATION, LUCERNE STATION, MAADI STATION, OLGA DOWNS STATION, RANMOOR STATION, RICHMOND DOWNS STATION, ROWEENA STATION, SANDHILLS STATION, SHERWOOD DOWNS STATION, STAWELLTON STATION, TORONTO PARK STATION, TOWRI STATION, WALKERS PARK STATION",
        "SUBURBS": "RICHMOND"
      }
    },
    {
      "type": "Feature",
      "geometry": {
        "type": "Point",
        "coordinates": [
          148.572282,
          -25.682816
        ]
      },
      "properties": {
        "EVENT_ID": "24SW1146",
        "TYPE": "PLANNED",
        "CUSTOMERS_AFFECTED": "851",
        "REASON": "The loss of supply is to replace power poles and improve the electricity network",
        "STATUS": "Crews working on-site",
        "START": "9:00AM 10 Mar 2024",
        "EST_FIX_TIME": "3:00PM 10 Mar 2024",
        "STREETS": "AIRPORT RD, ALCURAH RD, ANDERSON RD, ANNANDALE ST, ARCADIA VALLEY RD, ASHNEY RD, BIELBA RD, BLUE LAGOON RD, BONNYDOON RD, BROUGHTON ST, BURTONS RD, BYMOUNT EAST RD, BYMOUNT WEST RD, CAMERONS LANE, CARNARVON DEVELOPMENT HWY, CARNARVON DEVELOPMENT RD, CARNARVON HWY, CARRINGTON RD, CEDARS RD, CORNWALL RD, CORONATION ST, DAISYBANK RD, DANGARFIELD RD, DENTON CT, DUCK CREEK RD, DURHAM DOWNS RD, ELDORADO RD, EMOH RUO RD, EUMINA RD, FAIRVIEW RD, FIFTH AVE, FIRST AVE, FLOWER ST, FORESTVALE RD, FOURTH AVE, GLADSTONE RD, GLEN ARDEN RD, GLEN OLIVE RD, GRAFTON TERRACE RD, GUNNEWIN EAST RD, GUNNEWIN WEST RD, HARTLEY LANE, HUMPHREYS RD, HUTTON ST, INJUNE TAROOM RD, KILLORAN RD, KNAYERS LANE, KOMINE EAST RD, KOMINE WEST RD, KOORAGAN RD, KORCHA RD, LALORS LANE, LEUMEAH LANE, LISTERS RD, MAINTOP RD, MANSFIELDS RD, MAYFIELD RD, MOUNTAIN VIEW RD, MT MOFFATT DEVELOPMENT RD, MT MOFFATT RD, MT SALTBUSH RD, MT TABOR RD, MYALL DOWNS RD, MYRTLEVILLE RD, NIELLA RD, NINDERRA RD, NORTH KOORINGA RD, NORTON RD, NUGENT HILLS RD, NUGGET HILLS RD, ORALLO RD, PERONNE RD, PINE HILLS RD, RACECOURSE RD, RAILWAY PDE, ROCKVALE RD, ROMA TAROOM RD, ROMA-TAROOM RD, RONALD ST, ROSEDALE RD, SADDLER SPRINGS RD, SECOND AVE, SHORT ST, SPRING GULLY RD, SPRING VALE RD, STATION ST, STOCK ROUTE RD, STUARTS CREEK RD, THE BASIN RD, THIRD AVE, TIGER SCRUB RD, UNKNOWN RD, UNNAMED RD, WAIKOLA RD, WALSHS RD, WASHPOOL RD, WEBSTERS RD, WEST MYALL RD, WESTGROVE RD, WHITES RD, WOMBLEBANK GAP RD, WYBARA RD, ZUMPE RD",
        "SUBURBS": "AUGATHELLA, BYMOUNT, EUMAMURRIN, EUROMBAH, EUTHULLA, GUNNEWIN, INJUNE, MITCHELL, ORANGE HILL, ROMA, TAROOM, WALLUMBILLA"
      }
    }
  ],
  "company": "Ergon",
  "state": "Current",
  "extracted": "1710044105.060019"
}
