{
  "type": "FeatureCollection",
  "name": "PLANNED",
  "features": [
    {
      "type": "Feature",
      "geometry": {
        "type": "Point",
        "coordinates": [
          145.924373,
          -17.935617
        ]
      },
      "properties": {
        "EVENT_ID": "24FN5700",
        "TYPE": "PLANNED",
        "CUSTOMERS_AFFECTED": "58",
        "REASON": "The loss of supply is to allow maintenance of the electricity network",
        "STATUS": "Work scheduled",
        "START": "10:00PM 12 Jun 2024",
        "EST_FIX_TIME": "4:00AM 13 Jun 2024",
        "STREETS": "BRYANT ST, BUTLER ST, MILL RES, MILL RESERVE ST, MORRIS ST, WATKINS ST, WRIT LANE",
        "SUBURBS": "TULLY"
      }
    },
    {
      "type": "Feature",
      "geometry": {
        "type": "Point",
        "coordinates": [
          149.43412,
          -21.716372
        ]
      },
      "properties": {
        "EVENT_ID": "24MK4579",
        "TYPE": "PLANNED",
        "CUSTOMERS_AFFECTED": "2",
        "REASON": "The loss of supply is to connect new customers to the electricity network",
        "STATUS": "Crews working on-site",
        "START": "8:00AM 10 Jun 2024",
        "EST_FIX_TIME": "2:30PM 14 Jun 2024",
        "STREETS": "NOTCH POINT RD",
        "SUBURBS": "ILBILBIE"
      }
    },
    {
      "type": "Feature",
      "geometry": {
        "type": "Point",
        "coordinates": [
          147.801326,
          -20.562816
        ]
      },
      "properties": {
        "EVENT_ID": "24NQ8806",
        "TYPE": "PLANNED",
        "CUSTOMERS_AFFECTED": "2",
        "REASON": "The loss of supply is to replace power poles and improve the electricity network",
        "STATUS": "Crews working on-site",
        "START": "6:00AM 10 Jun 2024",
        "EST_FIX_TIME": "7:00PM 12 Jun 2024",
        "STREETS": "SCOTTVILLE RD",
        "SUBURBS": "COLLINSVILLE"
      }
    }
  ],
  "company": "Ergon",
  "state": "Current",
  "extracted": "1718181601.4242"
}
