{
  "type": "FeatureCollection",
  "name": "PLANNED",
  "features": [
    {
      "type": "Feature",
      "geometry": {
        "type": "Point",
        "coordinates": [
          145.881182,
          -17.535992
        ]
      },
      "properties": {
        "EVENT_ID": "24FN4537",
        "TYPE": "PLANNED",
        "CUSTOMERS_AFFECTED": "4",
        "REASON": "The loss of supply is to allow emergency maintenance of the electricity network",
        "STATUS": "Crews working on-site",
        "START": "8:30AM 20 Apr 2024",
        "EST_FIX_TIME": "6:45PM 20 Apr 2024",
        "STREETS": "MARUFF RD",
        "SUBURBS": "NERADA"
      }
    }
  ],
  "company": "Ergon",
  "state": "Current",
  "extracted": "1713599401.414084"
}
