{
  "type": "FeatureCollection",
  "name": "PLANNED",
  "features": [
    {
      "type": "Feature",
      "geometry": {
        "type": "Point",
        "coordinates": [
          146.234783,
          -18.673564
        ]
      },
      "properties": {
        "EVENT_ID": "24NQ8254",
        "TYPE": "PLANNED",
        "CUSTOMERS_AFFECTED": "2",
        "REASON": "The loss of supply is to allow maintenance of the electricity network",
        "STATUS": "Crews working on-site",
        "START": "8:30AM 17 Jun 2024",
        "EST_FIX_TIME": "2:30PM 17 Jun 2024",
        "STREETS": "FORREST BEACH RD",
        "SUBURBS": "VICTORIA ESTATE"
      }
    }
  ],
  "company": "Ergon",
  "state": "Current",
  "extracted": "1718598000.356221"
}
