{
  "type": "FeatureCollection",
  "name": "PLANNED",
  "features": [
    {
      "type": "Feature",
      "geometry": {
        "type": "Point",
        "coordinates": [
          146.807623,
          -19.310786
        ]
      },
      "properties": {
        "EVENT_ID": "24NQ5343",
        "TYPE": "PLANNED",
        "CUSTOMERS_AFFECTED": "16",
        "REASON": "The loss of supply is to connect new customers to the electricity network",
        "STATUS": "Crews working on-site",
        "START": "8:00PM 26 Mar 2024",
        "EST_FIX_TIME": "4:00AM 27 Mar 2024",
        "STREETS": "ABBOTT ST, MERVYN CROSSMAN DR, STUART DR",
        "SUBURBS": "ANNANDALE, IDALIA, OONOONBA"
      }
    },
    {
      "type": "Feature",
      "geometry": {
        "type": "Point",
        "coordinates": [
          146.768421,
          -19.27334
        ]
      },
      "properties": {
        "EVENT_ID": "24NQ5714",
        "TYPE": "PLANNED",
        "CUSTOMERS_AFFECTED": "12",
        "REASON": "The loss of supply is to replace power poles and improve the electricity network",
        "STATUS": "Crews working on-site",
        "START": "10:00PM 26 Mar 2024",
        "EST_FIX_TIME": "4:00AM 27 Mar 2024",
        "STREETS": "BAYSWATER RD, DALRYMPLE RD, VESUVIUS ST",
        "SUBURBS": "GARBUTT"
      }
    },
    {
      "type": "Feature",
      "geometry": {
        "type": "Point",
        "coordinates": [
          146.770919,
          -19.272062
        ]
      },
      "properties": {
        "EVENT_ID": "24NQ5717",
        "TYPE": "PLANNED",
        "CUSTOMERS_AFFECTED": "7",
        "REASON": "The loss of supply is to replace power poles and improve the electricity network",
        "STATUS": "Work scheduled",
        "START": "10:00PM 26 Mar 2024",
        "EST_FIX_TIME": "4:00AM 27 Mar 2024",
        "STREETS": "DALRYMPLE RD",
        "SUBURBS": "GARBUTT"
      }
    },
    {
      "type": "Feature",
      "geometry": {
        "type": "Point",
        "coordinates": [
          146.769482,
          -19.271585
        ]
      },
      "properties": {
        "EVENT_ID": "24NQ6241",
        "TYPE": "PLANNED",
        "CUSTOMERS_AFFECTED": "8",
        "REASON": "The loss of supply is to replace power poles and improve the electricity network",
        "STATUS": "Crews working on-site",
        "START": "10:00PM 26 Mar 2024",
        "EST_FIX_TIME": "4:00AM 27 Mar 2024",
        "STREETS": "MACKLEY ST",
        "SUBURBS": "GARBUTT"
      }
    }
  ],
  "company": "Ergon",
  "state": "Current",
  "extracted": "1711452002.265488"
}
