{
  "type": "FeatureCollection",
  "name": "PLANNED",
  "features": [
    {
      "type": "Feature",
      "geometry": {
        "type": "Point",
        "coordinates": [
          142.223026,
          -10.580694
        ]
      },
      "properties": {
        "EVENT_ID": "24FN6895",
        "TYPE": "PLANNED",
        "CUSTOMERS_AFFECTED": "205",
        "REASON": "The loss of supply is to allow emergency maintenance of the electricity network",
        "STATUS": "Crews working on-site",
        "START": "9:00AM 14 Jun 2024",
        "EST_FIX_TIME": "4:00PM 14 Jun 2024",
        "STREETS": "DOUGLAS ST, HARGRAVE ST, HASTINGS ST, HOCKING PNT, JOHN ST, LOBAN ST, MILMAN ST, SUMMERS ST, VICTORIA PDE",
        "SUBURBS": "THURSDAY ISLAND"
      }
    },
    {
      "type": "Feature",
      "geometry": {
        "type": "Point",
        "coordinates": [
          149.167304,
          -21.064669
        ]
      },
      "properties": {
        "EVENT_ID": "24MK4522",
        "TYPE": "PLANNED",
        "CUSTOMERS_AFFECTED": "141",
        "REASON": "The loss of supply is to upgrade equipment to meet customer demand for electricity and to improve reliability of supply in the area",
        "STATUS": "Crews working on-site",
        "START": "9:17AM 14 Jun 2024",
        "EST_FIX_TIME": "5:30PM 14 Jun 2024",
        "STREETS": "ARECA ST, COOT ST, EXCELSA CCT, JABIRU CCT, PALMETTO CRES, PINDO CCT, RADIATA ST, ROSEWOOD DR",
        "SUBURBS": "RURAL VIEW"
      }
    },
    {
      "type": "Feature",
      "geometry": {
        "type": "Point",
        "coordinates": [
          149.43412,
          -21.716372
        ]
      },
      "properties": {
        "EVENT_ID": "24MK4579",
        "TYPE": "PLANNED",
        "CUSTOMERS_AFFECTED": "2",
        "REASON": "The loss of supply is to connect new customers to the electricity network",
        "STATUS": "Crews working on-site",
        "START": "8:00AM 10 Jun 2024",
        "EST_FIX_TIME": "2:30PM 20 Jun 2024",
        "STREETS": "NOTCH POINT RD",
        "SUBURBS": "ILBILBIE"
      }
    }
  ],
  "company": "Ergon",
  "state": "Current",
  "extracted": "1718343902.029293"
}
