{
  "type": "FeatureCollection",
  "name": "PLANNED",
  "features": [
    {
      "type": "Feature",
      "geometry": {
        "type": "Point",
        "coordinates": [
          145.945567,
          -18.188254
        ]
      },
      "properties": {
        "EVENT_ID": "24FN3342",
        "TYPE": "PLANNED",
        "CUSTOMERS_AFFECTED": "2",
        "REASON": "The loss of supply is to replace power poles and improve the electricity network",
        "STATUS": "Crews working on-site",
        "START": "4:14PM 16 Mar 2024",
        "EST_FIX_TIME": "5:30PM 16 Mar 2024",
        "STREETS": "BRUCE HWY",
        "SUBURBS": "KENNEDY"
      }
    },
    {
      "type": "Feature",
      "geometry": {
        "type": "Point",
        "coordinates": [
          145.630557,
          -17.473518
        ]
      },
      "properties": {
        "EVENT_ID": "24FN3436",
        "TYPE": "PLANNED",
        "CUSTOMERS_AFFECTED": "44",
        "REASON": "The loss of supply is to replace power poles and improve the electricity network",
        "STATUS": "Crews working on-site",
        "START": "8:30AM 16 Mar 2024",
        "EST_FIX_TIME": "4:30PM 16 Mar 2024",
        "STREETS": "ELLINJAA RD, FRASER RD, JUBB RD, MOREGATTA RD, PURCELL RD, THERESA CREEK RD, WOOLLEYS RD",
        "SUBURBS": "MILLAA MILLAA"
      }
    }
  ],
  "company": "Ergon",
  "state": "Current",
  "extracted": "1710570001.644018"
}
