{
  "type": "FeatureCollection",
  "name": "PLANNED",
  "features": [
    {
      "type": "Feature",
      "geometry": {
        "type": "Point",
        "coordinates": [
          149.43412,
          -21.716372
        ]
      },
      "properties": {
        "EVENT_ID": "24MK4579",
        "TYPE": "PLANNED",
        "CUSTOMERS_AFFECTED": "2",
        "REASON": "The loss of supply is to connect new customers to the electricity network",
        "STATUS": "Crews working on-site",
        "START": "8:00AM 10 Jun 2024",
        "EST_FIX_TIME": "2:30PM 20 Jun 2024",
        "STREETS": "NOTCH POINT RD",
        "SUBURBS": "ILBILBIE"
      }
    },
    {
      "type": "Feature",
      "geometry": {
        "type": "Point",
        "coordinates": [
          146.234783,
          -18.673564
        ]
      },
      "properties": {
        "EVENT_ID": "24NQ8254",
        "TYPE": "PLANNED",
        "CUSTOMERS_AFFECTED": "2",
        "REASON": "The loss of supply is to allow maintenance of the electricity network",
        "STATUS": "Crews working on-site",
        "START": "8:30AM 17 Jun 2024",
        "EST_FIX_TIME": "2:30PM 17 Jun 2024",
        "STREETS": "FORREST BEACH RD",
        "SUBURBS": "VICTORIA ESTATE"
      }
    },
    {
      "type": "Feature",
      "geometry": {
        "type": "Point",
        "coordinates": [
          147.14842,
          -25.988327
        ]
      },
      "properties": {
        "EVENT_ID": "24SW9549",
        "TYPE": "PLANNED",
        "CUSTOMERS_AFFECTED": "65",
        "REASON": "The loss of supply is to allow emergency maintenance of the electricity network",
        "STATUS": "Crews working on-site",
        "START": "10:03AM 17 Jun 2024",
        "EST_FIX_TIME": "3:00PM 17 Jun 2024",
        "STREETS": "BOREA RD, CLARA CK RD, KILLARNEY RD, LANDSBOROUGH HWY, MT MARIA RD, MT TABOR RD, NEWFARM RD, NEWSTEAD RD, REDFORD RD, REDFORD-HOGANTHULLA RD, WARREGO HWY, WINNEBA RD",
        "SUBURBS": "AUGATHELLA, MORVEN, MUNGALLALA"
      }
    }
  ],
  "company": "Ergon",
  "state": "Current",
  "extracted": "1718597400.446751"
}
