{
  "type": "FeatureCollection",
  "name": "PLANNED",
  "features": [
    {
      "type": "Feature",
      "geometry": {
        "type": "Point",
        "coordinates": [
          150.754489,
          -23.144929
        ]
      },
      "properties": {
        "EVENT_ID": "24CA3543",
        "TYPE": "PLANNED",
        "CUSTOMERS_AFFECTED": "18",
        "REASON": "The loss of supply is to replace power poles and improve the electricity network",
        "STATUS": "Crews working on-site",
        "START": "7:30AM 14 Mar 2024",
        "EST_FIX_TIME": "4:30PM 14 Mar 2024",
        "STREETS": "DOLPHIN CRES, SWORDFISH AVE",
        "SUBURBS": "TARANGANBA"
      }
    },
    {
      "type": "Feature",
      "geometry": {
        "type": "Point",
        "coordinates": [
          148.69767,
          -20.276837
        ]
      },
      "properties": {
        "EVENT_ID": "24MK2181",
        "TYPE": "PLANNED",
        "CUSTOMERS_AFFECTED": "28",
        "REASON": "The loss of supply is to connect new customers to the electricity network",
        "STATUS": "Crews working on-site",
        "START": "9:58AM 14 Mar 2024",
        "EST_FIX_TIME": "4:20PM 14 Mar 2024",
        "STREETS": "SHUTE HARBOUR RD",
        "SUBURBS": "CANNONVALE"
      }
    },
    {
      "type": "Feature",
      "geometry": {
        "type": "Point",
        "coordinates": [
          149.212439,
          -21.388124
        ]
      },
      "properties": {
        "EVENT_ID": "24MK2195",
        "TYPE": "PLANNED",
        "CUSTOMERS_AFFECTED": "4",
        "REASON": "The loss of supply is to replace power poles and improve the electricity network",
        "STATUS": "Crews working on-site",
        "START": "10:17AM 14 Mar 2024",
        "EST_FIX_TIME": "4:30PM 14 Mar 2024",
        "STREETS": "BRUCE HWY, MALIN RD",
        "SUBURBS": "SARINA"
      }
    },
    {
      "type": "Feature",
      "geometry": {
        "type": "Point",
        "coordinates": [
          148.641447,
          -20.351501
        ]
      },
      "properties": {
        "EVENT_ID": "24MK2379",
        "TYPE": "PLANNED",
        "CUSTOMERS_AFFECTED": "226",
        "REASON": "The loss of supply is to replace power poles and improve the electricity network",
        "STATUS": "Crews working on-site",
        "START": "8:45AM 14 Mar 2024",
        "EST_FIX_TIME": "4:30PM 14 Mar 2024",
        "STREETS": "AITKEN RD, BECK RD, BRANDY CREEK RD, BROWN RD, BUSHRANGER DR, CAMM RD, CATTLEYARD CT, DUVAL RD, FORESTRY RD, JANSEN RD, MOUNT MARLOW RISE, PLEMENUK RD, REMMINGTON CL, RIFLE RANGE RD, SHUTE HARBOUR RD, SWAGMANS LANE, WINCHESTER CT",
        "SUBURBS": "BRANDY CREEK, MOUNT JULIAN, MOUNT MARLOW, PRESTON"
      }
    }
  ],
  "company": "Ergon",
  "state": "Current",
  "extracted": "1710398705.670406"
}
