{
  "type": "FeatureCollection",
  "name": "PLANNED",
  "features": [
    {
      "type": "Feature",
      "geometry": {
        "type": "Point",
        "coordinates": [
          145.87899,
          -17.539553
        ]
      },
      "properties": {
        "EVENT_ID": "24FN4537",
        "TYPE": "PLANNED",
        "CUSTOMERS_AFFECTED": "56",
        "REASON": "The loss of supply is to allow emergency maintenance of the electricity network",
        "STATUS": "Crews working on-site",
        "START": "8:30AM 20 Apr 2024",
        "EST_FIX_TIME": "4:00PM 20 Apr 2024",
        "STREETS": "COOROO LANDS RD, GATTERA RD, MARUFF RD, NERADA RD, PLANTATION RD, PULLOM RD, QUONDONG RD, RANKINE RD, WALTON RD",
        "SUBURBS": "EAST PALMERSTON, NERADA, UPPER DARADGEE"
      }
    },
    {
      "type": "Feature",
      "geometry": {
        "type": "Point",
        "coordinates": [
          148.964,
          -21.04405
        ]
      },
      "properties": {
        "EVENT_ID": "24MK3025",
        "TYPE": "PLANNED",
        "CUSTOMERS_AFFECTED": "20",
        "REASON": "The loss of supply is to upgrade equipment to meet customer demand for electricity and to improve reliability of supply in the area",
        "STATUS": "Crews working on-site",
        "START": "8:30AM 20 Apr 2024",
        "EST_FIX_TIME": "3:00PM 20 Apr 2024",
        "STREETS": "GIUMELLIS RD, MT JUKES RD, NICOL RD, RUTLANDS RD, YAKAPARI SEAFORTH RD",
        "SUBURBS": "KUTTABUL, SEAFORTH, YAKAPARI"
      }
    },
    {
      "type": "Feature",
      "geometry": {
        "type": "Point",
        "coordinates": [
          152.064761,
          -25.395683
        ]
      },
      "properties": {
        "EVENT_ID": "24WB4587",
        "TYPE": "PLANNED",
        "CUSTOMERS_AFFECTED": "137",
        "REASON": "The loss of supply is to allow maintenance of the electricity network",
        "STATUS": "Crews working on-site",
        "START": "9:01AM 20 Apr 2024",
        "EST_FIX_TIME": "3:00PM 20 Apr 2024",
        "STREETS": "ALASCAN RD, ANDERSON ST, BOOYAL DALLARNIL RD, BOOYAL RD, BRANDTS RD, BULLOCK HEAD RD, CHARLOTTE ST, CHILDERS RD, CONALAMAN RD, DALLARNIL RD, EMERYS RD, GOSPEL HALL RD, GRILLS RD, HANN ST, HETHERINGTONS RD, ISIS HWY, LAWGALLS RD, MAIN ST, MOUNT GOONANEMAN RD, OLD RANGE RD, PARADISE DAM RD, QUEEN ST, REPEATER RD, ROBERTSONS RD, ROBINSONS RD, SECCOMBE RD, SMITHS RD, STANTON HARCOURT RD, WOOWOONGA HALL RD, WOOWOONGA RD, WYNFORD RD",
        "SUBURBS": "BIGGENDEN, DALLARNIL, DEGILBO, WOOWOONGA"
      }
    }
  ],
  "company": "Ergon",
  "state": "Current",
  "extracted": "1713587404.446857"
}
