{
  "type": "FeatureCollection",
  "name": "PLANNED",
  "features": [
    {
      "type": "Feature",
      "geometry": {
        "type": "Point",
        "coordinates": [
          148.801043,
          -21.082886
        ]
      },
      "properties": {
        "EVENT_ID": "24MK3042",
        "TYPE": "PLANNED",
        "CUSTOMERS_AFFECTED": "4",
        "REASON": "The loss of supply is to replace power poles and improve the electricity network",
        "STATUS": "Crews working on-site",
        "START": "9:02AM 12 Apr 2024",
        "EST_FIX_TIME": "5:00PM 12 Apr 2024",
        "STREETS": "MCFAULS RD, SUGARLOAF RD",
        "SUBURBS": "MOUNT MARTIN"
      }
    },
    {
      "type": "Feature",
      "geometry": {
        "type": "Point",
        "coordinates": [
          151.655341,
          -27.367122
        ]
      },
      "properties": {
        "EVENT_ID": "24SW6619",
        "TYPE": "PLANNED",
        "CUSTOMERS_AFFECTED": "16",
        "REASON": "The loss of supply is to replace power poles and improve the electricity network",
        "STATUS": "Crews working on-site",
        "START": "8:00AM 12 Apr 2024",
        "EST_FIX_TIME": "5:00PM 12 Apr 2024",
        "STREETS": "DEVON PARK NORTH RD, DEVON PARK RD, JONDARYAN MULDU RD, JONDARYAN SABINE RD, SCHULLS RD, WARREGO HWY",
        "SUBURBS": "DEVON PARK, JONDARYAN, OAKEY"
      }
    }
  ],
  "company": "Ergon",
  "state": "Current",
  "extracted": "1712904901.371796"
}
