{
  "type": "FeatureCollection",
  "name": "PLANNED",
  "features": [
    {
      "type": "Feature",
      "geometry": {
        "type": "Point",
        "coordinates": [
          139.506077,
          -20.697005
        ]
      },
      "properties": {
        "EVENT_ID": "24NQ7533",
        "TYPE": "PLANNED",
        "CUSTOMERS_AFFECTED": "97",
        "REASON": "The loss of supply is to allow emergency maintenance of the electricity network",
        "STATUS": "Crews working on-site",
        "START": "8:49AM 05 May 2024",
        "EST_FIX_TIME": "4:30PM 05 May 2024",
        "STREETS": "ACTIVITY RD, BARNES ST, CAMERON WAY, COMMERCIAL RD, DAVIS RD, ENGINEERING RD, INDUSTRIAL AVE, LANSKEY RD, PROGRESS RD, RICHARDSON RD, RYAN RD",
        "SUBURBS": "LANSKEY, RYAN, SUNSET"
      }
    }
  ],
  "company": "Ergon",
  "state": "Current",
  "extracted": "1714889401.598676"
}
