{
  "type": "FeatureCollection",
  "name": "PLANNED",
  "features": [
    {
      "type": "Feature",
      "geometry": {
        "type": "Point",
        "coordinates": [
          144.047655,
          -9.913036
        ]
      },
      "properties": {
        "EVENT_ID": "24FN0444",
        "TYPE": "PLANNED",
        "CUSTOMERS_AFFECTED": "135",
        "REASON": "The loss of supply is to allow maintenance of the electricity network",
        "STATUS": "Crews working on-site",
        "START": "12:00PM 06 Apr 2024",
        "EST_FIX_TIME": "7:00PM 06 Apr 2024",
        "STREETS": "AIRPORT RD, DOUGLAS ST, MAIN ST, MAROU RD, MAROUGAB RD, MER 3 ST, MER 5 ST, MER SCHOOL OVAL ST, MER SCHOOL ST, PASSI ST, UNKNOWN ST",
        "SUBURBS": "MURRAY ISLAND"
      }
    }
  ],
  "company": "Ergon",
  "state": "Current",
  "extracted": "1712391601.116009"
}
