{
  "type": "FeatureCollection",
  "name": "PLANNED",
  "features": [
    {
      "type": "Feature",
      "geometry": {
        "type": "Point",
        "coordinates": [
          150.861533,
          -23.584401
        ]
      },
      "properties": {
        "EVENT_ID": "24CA3182",
        "TYPE": "PLANNED",
        "CUSTOMERS_AFFECTED": "8",
        "REASON": "The loss of supply is to replace power poles and improve the electricity network",
        "STATUS": "Crews working on-site",
        "START": "8:30AM 12 Mar 2024",
        "EST_FIX_TIME": "2:30PM 12 Mar 2024",
        "STREETS": "PORT ALMA RD",
        "SUBURBS": "BAJOOL"
      }
    },
    {
      "type": "Feature",
      "geometry": {
        "type": "Point",
        "coordinates": [
          150.391449,
          -23.32303
        ]
      },
      "properties": {
        "EVENT_ID": "24CA3601",
        "TYPE": "PLANNED",
        "CUSTOMERS_AFFECTED": "5",
        "REASON": "The loss of supply is to replace power poles and improve the electricity network",
        "STATUS": "Crews working on-site",
        "START": "10:30AM 12 Mar 2024",
        "EST_FIX_TIME": "1:30PM 12 Mar 2024",
        "STREETS": "HUNT RD, WOODFORD RD",
        "SUBURBS": "ALTON DOWNS"
      }
    },
    {
      "type": "Feature",
      "geometry": {
        "type": "Point",
        "coordinates": [
          150.725778,
          -23.174192
        ]
      },
      "properties": {
        "EVENT_ID": "24CA3652",
        "TYPE": "PLANNED",
        "CUSTOMERS_AFFECTED": "69",
        "REASON": "The loss of supply is to replace power poles and improve the electricity network",
        "STATUS": "Crews working on-site",
        "START": "9:00AM 12 Mar 2024",
        "EST_FIX_TIME": "3:00PM 12 Mar 2024",
        "STREETS": "COUCOM RD, DARAMBAL RD, HIDDEN VALLEY RD, NEWTONNE RD, TANBY P O RD, TANBY RD",
        "SUBURBS": "HIDDEN VALLEY, TANBY, YEPPOON"
      }
    },
    {
      "type": "Feature",
      "geometry": {
        "type": "Point",
        "coordinates": [
          146.782538,
          -19.265348
        ]
      },
      "properties": {
        "EVENT_ID": "24NQ4976",
        "TYPE": "PLANNED",
        "CUSTOMERS_AFFECTED": "12",
        "REASON": "The loss of supply is to replace power poles and improve the electricity network",
        "STATUS": "Crews working on-site",
        "START": "10:43AM 12 Mar 2024",
        "EST_FIX_TIME": "4:30PM 12 Mar 2024",
        "STREETS": "GORDEN ST",
        "SUBURBS": "GARBUTT"
      }
    }
  ],
  "company": "Ergon",
  "state": "Current",
  "extracted": "1710208500.484694"
}
