{
  "type": "FeatureCollection",
  "name": "PLANNED",
  "features": [
    {
      "type": "Feature",
      "geometry": {
        "type": "Point",
        "coordinates": [
          149.84562,
          -26.620108
        ]
      },
      "properties": {
        "EVENT_ID": "24SW9162",
        "TYPE": "PLANNED",
        "CUSTOMERS_AFFECTED": "379",
        "REASON": "The loss of supply is to replace power poles and improve the electricity network",
        "STATUS": "Crews working on-site",
        "START": "8:15AM 24 Jun 2024",
        "EST_FIX_TIME": "3:48PM 24 Jun 2024",
        "STREETS": "ALDRIDGE RD, ALFORDS RD, ANZAC AVE, BELL ST, BELLS RD, BESTS RD, BOGANDILLA RD, BURKE ST, BURRADOO RD, BUTLER'S RD, BUTLERS RD, CLARKE CREEK RD, CLARKE'S RD, CLERKE ST, COATES RD, COLSONS RD, CONDAMINE HWY, CORBETTS RD, CROSSROAD'S RD, DEVONCOURT RD, DULACCA GOLF CLUB RD, DULACCA NORTH RD, DULACCA SOUTH RD, DUNNS RD, EDWARD ST, ELLERSLIE RD, EWINGSDALE RD, EY'S RD, EYS RD, FORREST ST, FOUNTAIN CREEK RD, FRIZZELLS RD, FRIZZELS RD, GAZES RD, GLENAUBEN RD, GLENLEA RD, GLYNN AVE, GOONALAH EXTENSION RD, GOONALAH NORTH RD, GOONALAH RD E, GREEN LANE, GREGORY ST, GULLAGIMBI RD, HARRISONS RD, HASLOP'S RD, HOME BUSH RD, HOMEBUSH RD, JACKSON RD, JACKSON WANDOAN RD, JACKSON-WANDOAN RD, JARDINE ST, JUBILEE AVE, KILLARNEY ST, LAMBING FLAT RD, LEICHHARDT HWY, LOCKYER ST, LUCKIES LANE, MANTOVAS RD, MARRA MARRA RD, MATTHEWS RD, MILLRAIN RD, MOORES BICE RD, MT MYRTLE RD, NORTH DULACCA HALL RD, NORTH DULACCA RD, NORTH JACKSON RD, NORTH ST, OXLEY ST, PADDYS CREEK RD, PARK LANE, PEI RD, PINE RIDGE RD, QUEEN ST, RAILWAY ST, ROMA-CONDAMINE RD, SHORT ST, SOUTH DRILLHAM RD, STURT ST, SUMMERFIELD RD, TEMPLE ST, TRARALGON AVE, TRASKS LANE, TRIM'S RD, WAITUNA RD, WALLAN CREEK RD, WANDOAN RD, WARREGO HWY, WILLETS RD, WILLS ST, YAPUNYA RD",
        "SUBURBS": "CONDAMINE, DRILLHAM, DRILLHAM SOUTH, DULACCA, JACKSON, MILES, NORTH DULACCA, NORTH JACKSON, ULIMAROA, YULEBA"
      }
    }
  ],
  "company": "Ergon",
  "state": "Current",
  "extracted": "1719216601.473014"
}
