{
  "type": "FeatureCollection",
  "name": "PLANNED",
  "features": [
    {
      "type": "Feature",
      "geometry": {
        "type": "Point",
        "coordinates": [
          151.244315,
          -23.829121
        ]
      },
      "properties": {
        "EVENT_ID": "23CA17996",
        "TYPE": "PLANNED",
        "CUSTOMERS_AFFECTED": "72",
        "REASON": "The loss of supply is to allow maintenance of the electricity network",
        "STATUS": "Work scheduled",
        "START": "5:00PM 24 Mar 2024",
        "EST_FIX_TIME": "9:00PM 24 Mar 2024",
        "STREETS": "ALF O'ROURKE DR, BRYAN JORDAN DR, LEO ZUSSINO DR, UNMETERED SUPPLY",
        "SUBURBS": "GLADSTONE, GLADSTONE CENTRAL"
      }
    },
    {
      "type": "Feature",
      "geometry": {
        "type": "Point",
        "coordinates": [
          148.101245,
          -23.59037
        ]
      },
      "properties": {
        "EVENT_ID": "24CA4139",
        "TYPE": "PLANNED",
        "CUSTOMERS_AFFECTED": "67",
        "REASON": "The loss of supply is to upgrade equipment to meet customer demand for electricity and to improve reliability of supply in the area",
        "STATUS": "Crews working on-site",
        "START": "8:30AM 24 Mar 2024",
        "EST_FIX_TIME": "4:50PM 24 Mar 2024",
        "STREETS": "DENISON RD, MARSHALL RD, OFF SELMA RD, ROCKHOUND RD, SELMA RD",
        "SUBURBS": "EMERALD, SAPPHIRE CENTRAL"
      }
    }
  ],
  "company": "Ergon",
  "state": "Current",
  "extracted": "1711261201.322568"
}
