{
  "type": "FeatureCollection",
  "name": "PLANNED",
  "features": [
    {
      "type": "Feature",
      "geometry": {
        "type": "Point",
        "coordinates": [
          145.756014,
          -16.934581
        ]
      },
      "properties": {
        "EVENT_ID": "24FN4436",
        "TYPE": "PLANNED",
        "CUSTOMERS_AFFECTED": "370",
        "REASON": "The loss of supply is to replace power poles and improve the electricity network",
        "STATUS": "Crews working on-site",
        "START": "10:31PM 30 May 2024",
        "EST_FIX_TIME": "4:30AM 31 May 2024",
        "STREETS": "ASCOT AVE, BARRETT ST, BROWN ST, EARL ST, EDGAR ST, FREDERICK ST, HANNAM ST, LYONS ST, MULGRAVE RD, SCOTT ST, SPENCE ST, STURT ST, WELLINGTON ST",
        "SUBURBS": "BUNGALOW, CAIRNS, WESTCOURT"
      }
    },
    {
      "type": "Feature",
      "geometry": {
        "type": "Point",
        "coordinates": [
          146.331519,
          -18.526706
        ]
      },
      "properties": {
        "EVENT_ID": "24NQ7319",
        "TYPE": "PLANNED",
        "CUSTOMERS_AFFECTED": "4",
        "REASON": "The loss of supply is to connect new customers to the electricity network",
        "STATUS": "Crews working on-site",
        "START": "12:30PM 17 May 2024",
        "EST_FIX_TIME": "3:30PM 06 Jun 2024",
        "STREETS": "DUNGENESS RD, KEAST ST",
        "SUBURBS": "LUCINDA"
      }
    }
  ],
  "company": "Ergon",
  "state": "Current",
  "extracted": "1717074601.304455"
}
