{
  "type": "FeatureCollection",
  "name": "PLANNED",
  "features": [
    {
      "type": "Feature",
      "geometry": {
        "type": "Point",
        "coordinates": [
          148.797175,
          -21.082168
        ]
      },
      "properties": {
        "EVENT_ID": "24MK3042",
        "TYPE": "PLANNED",
        "CUSTOMERS_AFFECTED": "2",
        "REASON": "The loss of supply is to replace power poles and improve the electricity network",
        "STATUS": "Crews working on-site",
        "START": "9:02AM 12 Apr 2024",
        "EST_FIX_TIME": "5:15PM 12 Apr 2024",
        "STREETS": "SUGARLOAF RD",
        "SUBURBS": "MOUNT MARTIN"
      }
    }
  ],
  "company": "Ergon",
  "state": "Current",
  "extracted": "1712905205.304214"
}
