{
  "type": "FeatureCollection",
  "name": "PLANNED",
  "features": [
    {
      "type": "Feature",
      "geometry": {
        "type": "Point",
        "coordinates": [
          146.331519,
          -18.526706
        ]
      },
      "properties": {
        "EVENT_ID": "24NQ5670",
        "TYPE": "PLANNED",
        "CUSTOMERS_AFFECTED": "4",
        "REASON": "The loss of supply is to allow maintenance of the electricity network",
        "STATUS": "Crews working on-site",
        "START": "9:00AM 15 Apr 2024",
        "EST_FIX_TIME": "3:00PM 19 Apr 2024",
        "STREETS": "DUNGENESS RD, KEAST ST",
        "SUBURBS": "LUCINDA"
      }
    },
    {
      "type": "Feature",
      "geometry": {
        "type": "Point",
        "coordinates": [
          147.406308,
          -19.574162
        ]
      },
      "properties": {
        "EVENT_ID": "24NQ6638",
        "TYPE": "PLANNED",
        "CUSTOMERS_AFFECTED": "19",
        "REASON": "The loss of supply is to allow maintenance of the electricity network",
        "STATUS": "Work scheduled",
        "START": "11:00PM 16 Apr 2024",
        "EST_FIX_TIME": "4:00AM 17 Apr 2024",
        "STREETS": "EDWARDS ST, QUEEN ST",
        "SUBURBS": "AYR"
      }
    }
  ],
  "company": "Ergon",
  "state": "Current",
  "extracted": "1713255901.652313"
}
