{
  "type": "FeatureCollection",
  "name": "PLANNED",
  "features": [
    {
      "type": "Feature",
      "geometry": {
        "type": "Point",
        "coordinates": [
          151.870083,
          -27.569297
        ]
      },
      "properties": {
        "EVENT_ID": "24SW6207",
        "TYPE": "PLANNED",
        "CUSTOMERS_AFFECTED": "73",
        "REASON": "The loss of supply is to upgrade equipment to meet customer demand for electricity and to improve reliability of supply in the area",
        "STATUS": "Crews working on-site",
        "START": "10:03AM 02 Apr 2024",
        "EST_FIX_TIME": "2:00PM 04 Apr 2024",
        "STREETS": "BARKLA RD, BOUNDARY ST, CAROLANN ST, CARYS RD, DEUBLE RD, DEVINE RD, DRAYTON WELLCAMP RD, E DREW RD, EUSTON RD, HARVEY RD, HURSLEY RD, LAURA CT, OESTREICH RD",
        "SUBURBS": "CRANLEY, GLENVALE, TOOWOOMBA, WELLCAMP"
      }
    }
  ],
  "company": "Ergon",
  "state": "Current",
  "extracted": "1712145001.526625"
}
