{
  "type": "FeatureCollection",
  "name": "PLANNED",
  "features": [
    {
      "type": "Feature",
      "geometry": {
        "type": "Point",
        "coordinates": [
          152.695474,
          -25.508335
        ]
      },
      "properties": {
        "EVENT_ID": "24WB3164",
        "TYPE": "PLANNED",
        "CUSTOMERS_AFFECTED": "6",
        "REASON": "The loss of supply is to allow maintenance of the electricity network",
        "STATUS": "Crews working on-site",
        "START": "2:00PM 12 Mar 2024",
        "EST_FIX_TIME": "5:00PM 12 Mar 2024",
        "STREETS": "BLUEGUM CT, GREENWAY CT",
        "SUBURBS": "MARYBOROUGH"
      }
    }
  ],
  "company": "Ergon",
  "state": "Current",
  "extracted": "1710226205.287713"
}
