{
  "type": "FeatureCollection",
  "name": "PLANNED",
  "features": [
    {
      "type": "Feature",
      "geometry": {
        "type": "Point",
        "coordinates": [
          147.154128,
          -19.562146
        ]
      },
      "properties": {
        "EVENT_ID": "23NQ13385",
        "TYPE": "PLANNED",
        "CUSTOMERS_AFFECTED": "4",
        "REASON": "The loss of supply is to connect new customers to the electricity network",
        "STATUS": "Crews working on-site",
        "START": "8:28AM 09 Apr 2024",
        "EST_FIX_TIME": "4:30PM 09 Apr 2024",
        "STREETS": "BRUCE HWY, TOWNSVILLE RD",
        "SUBURBS": "GIRU"
      }
    },
    {
      "type": "Feature",
      "geometry": {
        "type": "Point",
        "coordinates": [
          149.959768,
          -24.719652
        ]
      },
      "properties": {
        "EVENT_ID": "24CA3812",
        "TYPE": "PLANNED",
        "CUSTOMERS_AFFECTED": "44",
        "REASON": "The loss of supply is to connect new customers to the electricity network",
        "STATUS": "Crews working on-site",
        "START": "8:30AM 09 Apr 2024",
        "EST_FIX_TIME": "4:30PM 09 Apr 2024",
        "STREETS": "BECKERS RD, BEHRENDORFFS RD, BURNSIDE-MCLELLANS RD, DAWSON HWY, KIANGA RIVER RD, MALONEYS RD, NIPAN-RIVER RD, RIVER RD, THEODORE BARALABA RD, THEODORE MOURA RD",
        "SUBURBS": "KIANGA, MOURA, THEODORE"
      }
    },
    {
      "type": "Feature",
      "geometry": {
        "type": "Point",
        "coordinates": [
          149.975316,
          -24.578554
        ]
      },
      "properties": {
        "EVENT_ID": "24CA4621",
        "TYPE": "PLANNED",
        "CUSTOMERS_AFFECTED": "421",
        "REASON": "The loss of supply is to replace power poles and improve the electricity network",
        "STATUS": "Crews working on-site",
        "START": "9:00AM 09 Apr 2024",
        "EST_FIX_TIME": "5:00PM 09 Apr 2024",
        "STREETS": "AUSTIN CRES, BECKER ST, BURNHAM ST, CHILTON ST, CLARKE CL, ELLIOTT ST, ENGEL ST, HAYDEN PL, HERTZOG ST, HOMER ST, LANG ST, LEDERHOSE ST, MCARTHUR ST, MCDOWELL ST, MINOGUE ST, NOBBS ST, NOTT ST, STEPHENSON ST, WENCK ST, WIDDERICK ST, WIDT ST",
        "SUBURBS": "MOURA"
      }
    },
    {
      "type": "Feature",
      "geometry": {
        "type": "Point",
        "coordinates": [
          151.957392,
          -27.542557
        ]
      },
      "properties": {
        "EVENT_ID": "24SW6561",
        "TYPE": "PLANNED",
        "CUSTOMERS_AFFECTED": "156",
        "REASON": "The loss of supply is to replace power poles and improve the electricity network",
        "STATUS": "Work scheduled",
        "START": "9:00PM 09 Apr 2024",
        "EST_FIX_TIME": "4:00AM 10 Apr 2024",
        "STREETS": "ABELIA ST, ELWORTHY ST, EUGENIA ST, HUME ST, KOOMBARRA ST, NORTH ST, RUTHVEN ST, VENTURE ST, WOLSELEY ST",
        "SUBURBS": "HARLAXTON, NORTH TOOWOOMBA, TOOWOOMBA"
      }
    }
  ],
  "company": "Ergon",
  "state": "Current",
  "extracted": "1712643901.435891"
}
