{
  "type": "FeatureCollection",
  "name": "PLANNED",
  "features": [
    {
      "type": "Feature",
      "geometry": {
        "type": "Point",
        "coordinates": [
          149.423949,
          -24.177657
        ]
      },
      "properties": {
        "EVENT_ID": "24CA4685",
        "TYPE": "PLANNED",
        "CUSTOMERS_AFFECTED": "369",
        "REASON": "The loss of supply is to upgrade equipment to meet customer demand for electricity and to improve reliability of supply in the area",
        "STATUS": "Crews working on-site",
        "START": "9:00AM 02 May 2024",
        "EST_FIX_TIME": "4:00PM 02 May 2024",
        "STREETS": "BLAIR ST, BOOTH ST, CARBINE ST, CENTRAL CREEK RD, CRESSBROOK ST, DOOLAN CRES, DOOLEY ST, DOYLE ST, FREEMAN ST, GEORGE CL, GREEN ST, HILL ST, KEMP ST, MATE MATE ST, MIMOSA CK RD, MUNNS DR, OFF MUNNS DR, RANKIN ST, RICHARD CL, RICHARDSON ST, SAUNDERS LANE, SWAIN ST",
        "SUBURBS": "WOORABINDA"
      }
    },
    {
      "type": "Feature",
      "geometry": {
        "type": "Point",
        "coordinates": [
          145.325512,
          -19.004541
        ]
      },
      "properties": {
        "EVENT_ID": "24NQ6646",
        "TYPE": "PLANNED",
        "CUSTOMERS_AFFECTED": "128",
        "REASON": "The loss of supply is to replace power poles and improve the electricity network",
        "STATUS": "Crews working on-site",
        "START": "8:55AM 02 May 2024",
        "EST_FIX_TIME": "3:30PM 02 May 2024",
        "STREETS": "BLOODWOOD RD, BLUE RANGE STATION, BOUNDARY RD, CAMEL CREEK STATION, CHRISTMAS CREEK STATION, CHURCH RD, CONJUBOY STATION, CRAIGLEE STATION, CRAIGS POCKET STATION, DEPOT RD, GADARA STATION, GILLDALE STATION, GRANTS RD, GREENVALE STATION, GREGORY DEVELOPMENTAL RD, JERVOISE STATION, JESSIE SPRINGS RD, KANGAROO HILLS STATION, KILCLOONEY STATION, KNUCKLEDOWN RD, KYLEE CT, LAVA PLAINS STATION, LINCOLN SPRINGS STATION, LUCKY DOWNS RD, LUCKY DOWNS STATION, LUCKY SPRINGS STATION, LYND HWY, MARIONVALE STATION, MELALEUCA CT, MOUNT FOX RD, MT FULLSTOP STATION, MT OWEENEE STATION, OAK HILLS RD, OAK HILLS STATION, PADDIES DAM STATION, PANDANUS STATION, POISON LAKE RD, PORPHRY STATION, REDBANK DR, REEDYBROOK STATION, RHONELLA PARK STATION, SILVER WATTLE RD, VALLEY LAGOONS, VEENEE STATION, WATTS RD, WYANDOTTE STATION",
        "SUBURBS": "BLUEWATER SPRINGS, CHARTERS TOWERS, CLARKE RIVER, GREENVALE, MOUNT FOX, MOUNT GARNET"
      }
    },
    {
      "type": "Feature",
      "geometry": {
        "type": "Point",
        "coordinates": [
          146.256023,
          -18.553086
        ]
      },
      "properties": {
        "EVENT_ID": "24NQ6757",
        "TYPE": "PLANNED",
        "CUSTOMERS_AFFECTED": "23",
        "REASON": "The loss of supply is to allow maintenance of the electricity network",
        "STATUS": "Crews working on-site",
        "START": "8:31AM 02 May 2024",
        "EST_FIX_TIME": "4:00PM 02 May 2024",
        "STREETS": "BULLOCK PADDOCK RD, CARUSO'S RD, KEMPS RD",
        "SUBURBS": "MACKNADE"
      }
    }
  ],
  "company": "Ergon",
  "state": "Current",
  "extracted": "1714628100.612421"
}
