{
  "type": "FeatureCollection",
  "name": "PLANNED",
  "features": [
    {
      "type": "Feature",
      "geometry": {
        "type": "Point",
        "coordinates": [
          149.0517,
          -21.023147
        ]
      },
      "properties": {
        "EVENT_ID": "24MK3903",
        "TYPE": "PLANNED",
        "CUSTOMERS_AFFECTED": "272",
        "REASON": "The loss of supply is to allow maintenance of the electricity network",
        "STATUS": "Crews working on-site",
        "START": "8:20AM 17 May 2024",
        "EST_FIX_TIME": "5:00PM 17 May 2024",
        "STREETS": "ABELA CT, ATTARDS RD, BARROW HILL RD, BAYVIEW DR, BOBONGIES RD, DANMAAR DR, FRIEDMANS RD, GARDINERS RD, HABANA WHARF RD, HABANA WOODS CT, MEZIN RD, MOOHINS RD, OLLETTS RD, SHADY LANE, SUMMERHILL RISE, YAKAPARI HABANA RD",
        "SUBURBS": "HABANA"
      }
    },
    {
      "type": "Feature",
      "geometry": {
        "type": "Point",
        "coordinates": [
          146.331519,
          -18.526706
        ]
      },
      "properties": {
        "EVENT_ID": "24NQ7319",
        "TYPE": "PLANNED",
        "CUSTOMERS_AFFECTED": "4",
        "REASON": "The loss of supply is to connect new customers to the electricity network",
        "STATUS": "Crews working on-site",
        "START": "12:30PM 17 May 2024",
        "EST_FIX_TIME": "3:30PM 30 May 2024",
        "STREETS": "DUNGENESS RD, KEAST ST",
        "SUBURBS": "LUCINDA"
      }
    }
  ],
  "company": "Ergon",
  "state": "Current",
  "extracted": "1715927101.757419"
}
