{
  "type": "FeatureCollection",
  "name": "PLANNED",
  "features": [
    {
      "type": "Feature",
      "geometry": {
        "type": "Point",
        "coordinates": [
          145.743239,
          -16.916769
        ]
      },
      "properties": {
        "EVENT_ID": "24FN6610",
        "TYPE": "PLANNED",
        "CUSTOMERS_AFFECTED": "242",
        "REASON": "The loss of supply is to replace power poles and improve the electricity network",
        "STATUS": "Work scheduled",
        "START": "10:30PM 20 Jun 2024",
        "EST_FIX_TIME": "5:30AM 21 Jun 2024",
        "STREETS": "ANDERSON ST, MAYERS ST, PATIENCE ST",
        "SUBURBS": "MANOORA, MANUNDA"
      }
    },
    {
      "type": "Feature",
      "geometry": {
        "type": "Point",
        "coordinates": [
          151.953113,
          -25.4056
        ]
      },
      "properties": {
        "EVENT_ID": "24WB5697",
        "TYPE": "PLANNED",
        "CUSTOMERS_AFFECTED": "38",
        "REASON": "The loss of supply is to upgrade equipment to meet customer demand for electricity and to improve reliability of supply in the area",
        "STATUS": "Crews working on-site",
        "START": "8:30AM 20 Jun 2024",
        "EST_FIX_TIME": "4:30PM 20 Jun 2024",
        "STREETS": "BIGGENDEN-GOOROOLBA RD, CORINGA HILLS RD, CORINGA RD, CURTIS RUSSELLS RD, JUMP UP RD, MOUNT SHAMROCK RD, NULLA CREEK RD",
        "SUBURBS": "BIGGENDEN, CORINGA"
      }
    }
  ],
  "company": "Ergon",
  "state": "Current",
  "extracted": "1718867100.399767"
}
