{
  "type": "FeatureCollection",
  "name": "PLANNED",
  "features": [
    {
      "type": "Feature",
      "geometry": {
        "type": "Point",
        "coordinates": [
          145.743239,
          -16.916769
        ]
      },
      "properties": {
        "EVENT_ID": "24FN6610",
        "TYPE": "PLANNED",
        "CUSTOMERS_AFFECTED": "242",
        "REASON": "The loss of supply is to replace power poles and improve the electricity network",
        "STATUS": "Work scheduled",
        "START": "10:30PM 20 Jun 2024",
        "EST_FIX_TIME": "5:30AM 21 Jun 2024",
        "STREETS": "ANDERSON ST, MAYERS ST, PATIENCE ST",
        "SUBURBS": "MANOORA, MANUNDA"
      }
    }
  ],
  "company": "Ergon",
  "state": "Current",
  "extracted": "1718884501.57318"
}
