{
  "type": "FeatureCollection",
  "name": "PLANNED",
  "features": [
    {
      "type": "Feature",
      "geometry": {
        "type": "Point",
        "coordinates": [
          145.471599,
          -17.273592
        ]
      },
      "properties": {
        "EVENT_ID": "24FN5281",
        "TYPE": "PLANNED",
        "CUSTOMERS_AFFECTED": "2",
        "REASON": "The loss of supply is to replace power poles and improve the electricity network",
        "STATUS": "Crews working on-site",
        "START": "2:04PM 07 May 2024",
        "EST_FIX_TIME": "3:30PM 07 May 2024",
        "STREETS": "WEAVER ST",
        "SUBURBS": "ATHERTON"
      }
    },
    {
      "type": "Feature",
      "geometry": {
        "type": "Point",
        "coordinates": [
          147.408299,
          -19.568983
        ]
      },
      "properties": {
        "EVENT_ID": "24NQ6836",
        "TYPE": "PLANNED",
        "CUSTOMERS_AFFECTED": "85",
        "REASON": "The loss of supply is to allow maintenance of the electricity network",
        "STATUS": "Crews working on-site",
        "START": "9:27AM 07 May 2024",
        "EST_FIX_TIME": "4:00PM 07 May 2024",
        "STREETS": "CAMERON ST, CHIPPENDALE ST, COX ST, MUNRO ST, ROSSITER ST, SPILLER ST, WILMINGTON ST",
        "SUBURBS": "AYR"
      }
    },
    {
      "type": "Feature",
      "geometry": {
        "type": "Point",
        "coordinates": [
          146.331519,
          -18.526706
        ]
      },
      "properties": {
        "EVENT_ID": "24NQ7260",
        "TYPE": "PLANNED",
        "CUSTOMERS_AFFECTED": "4",
        "REASON": "The loss of supply is to connect new customers to the electricity network",
        "STATUS": "Crews working on-site",
        "START": "7:42AM 07 May 2024",
        "EST_FIX_TIME": "3:30PM 08 May 2024",
        "STREETS": "DUNGENESS RD, KEAST ST",
        "SUBURBS": "LUCINDA"
      }
    },
    {
      "type": "Feature",
      "geometry": {
        "type": "Point",
        "coordinates": [
          146.182856,
          -26.49326
        ]
      },
      "properties": {
        "EVENT_ID": "24SW7354",
        "TYPE": "PLANNED",
        "CUSTOMERS_AFFECTED": "27",
        "REASON": "The loss of supply is to remove vegetation growing near powerlines",
        "STATUS": "Crews working on-site",
        "START": "12:20PM 07 May 2024",
        "EST_FIX_TIME": "4:00PM 07 May 2024",
        "STREETS": "BANNERMAN'S RD, CHARLEVILLE-WYANDRA RD, CROXDALE RD, MITCHELL HWY, QUILPIE RD",
        "SUBURBS": "CHARLEVILLE"
      }
    }
  ],
  "company": "Ergon",
  "state": "Current",
  "extracted": "1715059501.491784"
}
