{
  "type": "FeatureCollection",
  "name": "PLANNED",
  "features": [
    {
      "type": "Feature",
      "geometry": {
        "type": "Point",
        "coordinates": [
          148.770746,
          -21.143954
        ]
      },
      "properties": {
        "EVENT_ID": "25MK0392",
        "TYPE": "PLANNED",
        "CUSTOMERS_AFFECTED": "26",
        "REASON": "The loss of supply is to connect new customers to the electricity network",
        "STATUS": "Crews working on-site",
        "START": "8:30AM 07 Mar 2025",
        "EST_FIX_TIME": "4:30PM 07 Mar 2025",
        "STREETS": "CAPPELLOS RD, DUNWOLD LUMBURRA RD, GARGETT DUMP RD, MACKAY EUNGELLA RD, OWENS CREEK RD",
        "SUBURBS": "GARGETT, OWENS CREEK"
      }
    }
  ],
  "company": "Ergon",
  "state": "Current",
  "extracted": "1741329601.633408"
}
