{
  "type": "FeatureCollection",
  "name": "PLANNED",
  "features": [
    {
      "type": "Feature",
      "geometry": {
        "type": "Point",
        "coordinates": [
          146.331519,
          -18.526706
        ]
      },
      "properties": {
        "EVENT_ID": "24NQ7260",
        "TYPE": "PLANNED",
        "CUSTOMERS_AFFECTED": "4",
        "REASON": "The loss of supply is to connect new customers to the electricity network",
        "STATUS": "Crews working on-site",
        "START": "7:42AM 07 May 2024",
        "EST_FIX_TIME": "3:30PM 15 May 2024",
        "STREETS": "DUNGENESS RD, KEAST ST",
        "SUBURBS": "LUCINDA"
      }
    },
    {
      "type": "Feature",
      "geometry": {
        "type": "Point",
        "coordinates": [
          152.716161,
          -25.534776
        ]
      },
      "properties": {
        "EVENT_ID": "24WB5149",
        "TYPE": "PLANNED",
        "CUSTOMERS_AFFECTED": "10",
        "REASON": "The loss of supply is to allow maintenance of the electricity network",
        "STATUS": "Crews working on-site",
        "START": "7:04AM 14 May 2024",
        "EST_FIX_TIME": "6:00PM 14 May 2024",
        "STREETS": "ARNAUD ST, BANANA ST, RAGLAN ST, ST MUNGO ST, WOLSELEY ST",
        "SUBURBS": "GRANVILLE"
      }
    }
  ],
  "company": "Ergon",
  "state": "Current",
  "extracted": "1715671501.342693"
}
