{
  "type": "FeatureCollection",
  "name": "PLANNED",
  "features": [
    {
      "type": "Feature",
      "geometry": {
        "type": "Point",
        "coordinates": [
          145.748428,
          -16.914592
        ]
      },
      "properties": {
        "EVENT_ID": "24FN4359",
        "TYPE": "PLANNED",
        "CUSTOMERS_AFFECTED": "2",
        "REASON": "The loss of supply is to allow maintenance of the electricity network",
        "STATUS": "Crews working on-site",
        "START": "6:41AM 10 Apr 2024",
        "EST_FIX_TIME": "7:30AM 11 Apr 2024",
        "STREETS": "ANDERSON ST",
        "SUBURBS": "MANUNDA"
      }
    },
    {
      "type": "Feature",
      "geometry": {
        "type": "Point",
        "coordinates": [
          139.551552,
          -20.715318
        ]
      },
      "properties": {
        "EVENT_ID": "24NQ6423",
        "TYPE": "PLANNED",
        "CUSTOMERS_AFFECTED": "6",
        "REASON": "The loss of supply is to upgrade equipment to meet customer demand for electricity and to improve reliability of supply in the area",
        "STATUS": "Crews working on-site",
        "START": "8:03AM 10 Apr 2024",
        "EST_FIX_TIME": "5:00PM 10 Apr 2024",
        "STREETS": "BARKLY HWY",
        "SUBURBS": "MOUNT ISA"
      }
    }
  ],
  "company": "Ergon",
  "state": "Current",
  "extracted": "1712732101.176728"
}
