{
  "type": "FeatureCollection",
  "name": "PLANNED",
  "features": [
    {
      "type": "Feature",
      "geometry": {
        "type": "Point",
        "coordinates": [
          146.712651,
          -23.5022
        ]
      },
      "properties": {
        "EVENT_ID": "24CA7204",
        "TYPE": "PLANNED",
        "CUSTOMERS_AFFECTED": "445",
        "REASON": "The loss of supply is to upgrade equipment to meet customer demand for electricity and to improve reliability of supply in the area",
        "STATUS": "Crews working on-site",
        "START": "9:01AM 16 Jun 2024",
        "EST_FIX_TIME": "5:00PM 16 Jun 2024",
        "STREETS": "ALBRO RD, ALPHA-CLERMONT RD, ALPHA-TAMBO RD, BURNS ST, BYRON ST, CAPRICORN HWY, CLERMONT RD, CRAVEN RD, DEGULLA RD, DERWENT WATER RD, DRYDEN ST, DUNNING ST, FORRESTER-HOBARTVL RD, GOLDSTON ST, GORDON ST, HOOPER ST, KILCOOL RD, MACKELLAR ST, MILTON ST, MONKLANDS RD, MOORE ST, NAROUNYAH RD, OFF ALBRO RD, OFF ALPHA-CLERMONT RD, OFF CAPRICORN HWY, OFF FORRESTER RD, OFF MOORE ST, OFF STAR DOWNS RD, OFF TAMBO RD, PINE HILL RD, PORT WINE RD, PORTWINE RD, RAILWAY RES, SCOTT ST, SHAKESPEARE ST, STAR DOWNS RD, SWINBURNE ST, TAMBO RD, TENNYSON ST, UNKNOWN ST",
        "SUBURBS": "ALPHA, CLERMONT, JERICHO"
      }
    },
    {
      "type": "Feature",
      "geometry": {
        "type": "Point",
        "coordinates": [
          149.43412,
          -21.716372
        ]
      },
      "properties": {
        "EVENT_ID": "24MK4579",
        "TYPE": "PLANNED",
        "CUSTOMERS_AFFECTED": "2",
        "REASON": "The loss of supply is to connect new customers to the electricity network",
        "STATUS": "Crews working on-site",
        "START": "8:00AM 10 Jun 2024",
        "EST_FIX_TIME": "2:30PM 20 Jun 2024",
        "STREETS": "NOTCH POINT RD",
        "SUBURBS": "ILBILBIE"
      }
    },
    {
      "type": "Feature",
      "geometry": {
        "type": "Point",
        "coordinates": [
          149.149039,
          -21.201204
        ]
      },
      "properties": {
        "EVENT_ID": "24MK4670",
        "TYPE": "PLANNED",
        "CUSTOMERS_AFFECTED": "35",
        "REASON": "The loss of supply is to allow maintenance of the electricity network",
        "STATUS": "Crews working on-site",
        "START": "8:30AM 16 Jun 2024",
        "EST_FIX_TIME": "4:30PM 16 Jun 2024",
        "STREETS": "BRUCE HWY, COOKS LANE, FLINDERS CT, MAIN ST, TOM THUMB CT",
        "SUBURBS": "BAKERS CREEK"
      }
    },
    {
      "type": "Feature",
      "geometry": {
        "type": "Point",
        "coordinates": [
          151.923115,
          -27.581709
        ]
      },
      "properties": {
        "EVENT_ID": "24SW9190",
        "TYPE": "PLANNED",
        "CUSTOMERS_AFFECTED": "63",
        "REASON": "The loss of supply is to connect new customers to the electricity network",
        "STATUS": "Crews working on-site",
        "START": "9:24AM 16 Jun 2024",
        "EST_FIX_TIME": "4:30PM 16 Jun 2024",
        "STREETS": "ALDERLEY ST, ANZAC AVE, CONDAMINE ST, CROFT CRES, GIBBS ST, SPALDING ST, WALTERS DR",
        "SUBURBS": "HARRISTOWN, TOOWOOMBA"
      }
    }
  ],
  "company": "Ergon",
  "state": "Current",
  "extracted": "1718519101.230212"
}
