{
  "type": "FeatureCollection",
  "name": "PLANNED",
  "features": [
    {
      "type": "Feature",
      "geometry": {
        "type": "Point",
        "coordinates": [
          151.561352,
          -24.328116
        ]
      },
      "properties": {
        "EVENT_ID": "24CA7340",
        "TYPE": "PLANNED",
        "CUSTOMERS_AFFECTED": "7",
        "REASON": "The loss of supply is to connect new customers to the electricity network",
        "STATUS": "Crews working on-site",
        "START": "9:00AM 18 Jun 2024",
        "EST_FIX_TIME": "4:00PM 18 Jun 2024",
        "STREETS": "BLOMFIELD ST, BLOOMFIELD ST, ROE ST",
        "SUBURBS": "MIRIAM VALE"
      }
    },
    {
      "type": "Feature",
      "geometry": {
        "type": "Point",
        "coordinates": [
          152.083221,
          -27.142323
        ]
      },
      "properties": {
        "EVENT_ID": "24SW9016",
        "TYPE": "PLANNED",
        "CUSTOMERS_AFFECTED": "175",
        "REASON": "The loss of supply is to replace power poles and improve the electricity network",
        "STATUS": "Crews working on-site",
        "START": "8:31AM 18 Jun 2024",
        "EST_FIX_TIME": "5:30PM 18 Jun 2024",
        "STREETS": "ANDURAMBA RANGE RD, ANDURAMBA RD, ANGER RD, AUSTIN RD, BACK CREEK RD, BARKER LANE, BARNES RD, BAUSCH RD, BLUFF RD, BOWEN RD, BYER RD, BYERS RD, DEVONCOURT LANE, DEVONCOURT RD, FITCH RD, HAWKINS RD, HEATHER RD, JONES GULLY RD, MARIA CREEK RD, MARSHALL RD, MCGREEVY RD, MIDDLE RD, NUKINENDA RD, PETTIE RD, PIERCES CREEK RD, PIT RD, TIGELL RD, VOLL RD, VONHOFF RD, WATERHOLE GULLY RD, WOODLEA CT",
        "SUBURBS": "ANDURAMBA, CROWS NEST, JONES GULLY, NUKINENDA, PIERCES CREEK, PINELANDS, VIRGINIA"
      }
    },
    {
      "type": "Feature",
      "geometry": {
        "type": "Point",
        "coordinates": [
          152.18073,
          -25.330587
        ]
      },
      "properties": {
        "EVENT_ID": "24WB5836",
        "TYPE": "PLANNED",
        "CUSTOMERS_AFFECTED": "64",
        "REASON": "The loss of supply is to upgrade equipment to meet customer demand for electricity and to improve reliability of supply in the area",
        "STATUS": "Crews working on-site",
        "START": "9:01AM 18 Jun 2024",
        "EST_FIX_TIME": "5:30PM 18 Jun 2024",
        "STREETS": "AGNESVALE RD, BERRIES RD, BIGGENDEN RD, EUREKA RD, FAINTS RD, ISIS HWY, NORTH SOUTH RD, RENDALLS RD, SAWMILL RD",
        "SUBURBS": "APPLE TREE CREEK, CHILDERS, EUREKA, GOLDEN FLEECE, ISIS CENTRAL, KULLOGUM"
      }
    },
    {
      "type": "Feature",
      "geometry": {
        "type": "Point",
        "coordinates": [
          152.144261,
          -25.292038
        ]
      },
      "properties": {
        "EVENT_ID": "24WB5837",
        "TYPE": "PLANNED",
        "CUSTOMERS_AFFECTED": "19",
        "REASON": "The loss of supply is to upgrade equipment to meet customer demand for electricity and to improve reliability of supply in the area",
        "STATUS": "Crews working on-site",
        "START": "1:32PM 18 Jun 2024",
        "EST_FIX_TIME": "5:30PM 18 Jun 2024",
        "STREETS": "EUREKA STATION RD, GUPPYS RD, RENDALLS RD",
        "SUBURBS": "EUREKA"
      }
    }
  ],
  "company": "Ergon",
  "state": "Current",
  "extracted": "1718692500.358159"
}
