{
  "type": "FeatureCollection",
  "name": "PLANNED",
  "features": [
    {
      "type": "Feature",
      "geometry": {
        "type": "Point",
        "coordinates": [
          149.077601,
          -21.15927
        ]
      },
      "properties": {
        "EVENT_ID": "24MK4250",
        "TYPE": "PLANNED",
        "CUSTOMERS_AFFECTED": "7",
        "REASON": "The loss of supply is to upgrade equipment to meet customer demand for electricity and to improve reliability of supply in the area",
        "STATUS": "Crews working on-site",
        "START": "9:00AM 08 Jun 2024",
        "EST_FIX_TIME": "4:30PM 08 Jun 2024",
        "STREETS": "MACKAY EUNGELLA RD, PALMS RD, PEAK DOWNS HWY",
        "SUBURBS": "WALKERSTON"
      }
    }
  ],
  "company": "Ergon",
  "state": "Current",
  "extracted": "1717829105.295099"
}
