{
  "type": "FeatureCollection",
  "name": "PLANNED",
  "features": [
    {
      "type": "Feature",
      "geometry": {
        "type": "Point",
        "coordinates": [
          150.182777,
          -25.294544
        ]
      },
      "properties": {
        "EVENT_ID": "24CA3936",
        "TYPE": "PLANNED",
        "CUSTOMERS_AFFECTED": "17",
        "REASON": "The loss of supply is to allow maintenance of the electricity network",
        "STATUS": "Crews working on-site",
        "START": "9:00AM 08 Apr 2024",
        "EST_FIX_TIME": "3:00PM 08 Apr 2024",
        "STREETS": "CRACOW RD, GYRANDA RD",
        "SUBURBS": "CRACOW, THEODORE"
      }
    },
    {
      "type": "Feature",
      "geometry": {
        "type": "Point",
        "coordinates": [
          146.816485,
          -19.260927
        ]
      },
      "properties": {
        "EVENT_ID": "24NQ4482",
        "TYPE": "PLANNED",
        "CUSTOMERS_AFFECTED": "29",
        "REASON": "The loss of supply is to allow maintenance of the electricity network",
        "STATUS": "Crews working on-site",
        "START": "8:29AM 08 Apr 2024",
        "EST_FIX_TIME": "4:00PM 08 Apr 2024",
        "STREETS": "FLINDERS ST, HANRAN ST, OGDEN ST, STOKES ST",
        "SUBURBS": "TOWNSVILLE CITY"
      }
    }
  ],
  "company": "Ergon",
  "state": "Current",
  "extracted": "1712553000.499013"
}
