{
  "type": "FeatureCollection",
  "name": "PLANNED",
  "features": [
    {
      "type": "Feature",
      "geometry": {
        "type": "Point",
        "coordinates": [
          148.247607,
          -20.004567
        ]
      },
      "properties": {
        "EVENT_ID": "24NQ5330",
        "TYPE": "PLANNED",
        "CUSTOMERS_AFFECTED": "7",
        "REASON": "The loss of supply is to replace power poles and improve the electricity network",
        "STATUS": "Crews working on-site",
        "START": "7:45AM 25 Mar 2024",
        "EST_FIX_TIME": "4:00PM 25 Mar 2024",
        "STREETS": "COWAN LANE, KING ST, MORRILL ST",
        "SUBURBS": "BOWEN"
      }
    },
    {
      "type": "Feature",
      "geometry": {
        "type": "Point",
        "coordinates": [
          148.236761,
          -20.015823
        ]
      },
      "properties": {
        "EVENT_ID": "24NQ5333",
        "TYPE": "PLANNED",
        "CUSTOMERS_AFFECTED": "8",
        "REASON": "The loss of supply is to replace power poles and improve the electricity network",
        "STATUS": "Crews working on-site",
        "START": "8:40AM 25 Mar 2024",
        "EST_FIX_TIME": "4:00PM 25 Mar 2024",
        "STREETS": "GORDON ST",
        "SUBURBS": "BOWEN"
      }
    },
    {
      "type": "Feature",
      "geometry": {
        "type": "Point",
        "coordinates": [
          151.953063,
          -27.560459
        ]
      },
      "properties": {
        "EVENT_ID": "24SW5239",
        "TYPE": "PLANNED",
        "CUSTOMERS_AFFECTED": "11",
        "REASON": "The loss of supply is to upgrade equipment to meet customer demand for electricity and to improve reliability of supply in the area",
        "STATUS": "Work scheduled",
        "START": "10:00PM 25 Mar 2024",
        "EST_FIX_TIME": "3:00AM 26 Mar 2024",
        "STREETS": "MARGARET ST, RUTHVEN ST",
        "SUBURBS": "TOOWOOMBA, TOOWOOMBA CITY"
      }
    },
    {
      "type": "Feature",
      "geometry": {
        "type": "Point",
        "coordinates": [
          152.449616,
          -24.881577
        ]
      },
      "properties": {
        "EVENT_ID": "24WB3785",
        "TYPE": "PLANNED",
        "CUSTOMERS_AFFECTED": "21",
        "REASON": "The loss of supply is to upgrade equipment to meet customer demand for electricity and to improve reliability of supply in the area",
        "STATUS": "Crews working on-site",
        "START": "9:00AM 25 Mar 2024",
        "EST_FIX_TIME": "2:30PM 25 Mar 2024",
        "STREETS": "ELLIOTT HEADS RD, INNES PARK RD, SPRINGFIELD RD, ZINKS RD",
        "SUBURBS": "INNES PARK, WOONGARRA"
      }
    }
  ],
  "company": "Ergon",
  "state": "Current",
  "extracted": "1711343703.691559"
}
