{
  "type": "FeatureCollection",
  "name": "PLANNED",
  "features": [
    {
      "type": "Feature",
      "geometry": {
        "type": "Point",
        "coordinates": [
          152.348693,
          -24.871258
        ]
      },
      "properties": {
        "EVENT_ID": "24WB5710",
        "TYPE": "PLANNED",
        "CUSTOMERS_AFFECTED": "26",
        "REASON": "The loss of supply is to allow maintenance of the electricity network",
        "STATUS": "Work scheduled",
        "START": "10:30PM 07 Jun 2024",
        "EST_FIX_TIME": "2:30AM 08 Jun 2024",
        "STREETS": "ELECTRA ST, GEORGE ST, MARYBOROUGH ST",
        "SUBURBS": "BUNDABERG, BUNDABERG CENTRAL"
      }
    }
  ],
  "company": "Ergon",
  "state": "Current",
  "extracted": "1717750501.195431"
}
