{
  "type": "FeatureCollection",
  "name": "PLANNED",
  "features": [
    {
      "type": "Feature",
      "geometry": {
        "type": "Point",
        "coordinates": [
          150.725981,
          -23.320138
        ]
      },
      "properties": {
        "EVENT_ID": "24CA6661",
        "TYPE": "PLANNED",
        "CUSTOMERS_AFFECTED": "40",
        "REASON": "The loss of supply is to replace power poles and improve the electricity network",
        "STATUS": "Crews working on-site",
        "START": "8:30AM 31 May 2024",
        "EST_FIX_TIME": "3:30PM 31 May 2024",
        "STREETS": "COBB AND CO RD, HOFFMANS RD, MARRIES RD, WHITINGS RD",
        "SUBURBS": "COOWONGA, TUNGAMULL"
      }
    },
    {
      "type": "Feature",
      "geometry": {
        "type": "Point",
        "coordinates": [
          146.331519,
          -18.526706
        ]
      },
      "properties": {
        "EVENT_ID": "24NQ7319",
        "TYPE": "PLANNED",
        "CUSTOMERS_AFFECTED": "4",
        "REASON": "The loss of supply is to connect new customers to the electricity network",
        "STATUS": "Crews working on-site",
        "START": "12:30PM 17 May 2024",
        "EST_FIX_TIME": "3:30PM 06 Jun 2024",
        "STREETS": "DUNGENESS RD, KEAST ST",
        "SUBURBS": "LUCINDA"
      }
    },
    {
      "type": "Feature",
      "geometry": {
        "type": "Point",
        "coordinates": [
          142.570643,
          -21.80267
        ]
      },
      "properties": {
        "EVENT_ID": "24NQ8239",
        "TYPE": "PLANNED",
        "CUSTOMERS_AFFECTED": "3",
        "REASON": "The loss of supply is to replace power poles and improve the electricity network",
        "STATUS": "Crews working on-site",
        "START": "9:44AM 31 May 2024",
        "EST_FIX_TIME": "4:00PM 31 May 2024",
        "STREETS": "WONGAN STATION, WYBENIA STATION",
        "SUBURBS": "WINTON"
      }
    }
  ],
  "company": "Ergon",
  "state": "Current",
  "extracted": "1717133101.766723"
}
