{
  "type": "FeatureCollection",
  "name": "PLANNED",
  "features": [
    {
      "type": "Feature",
      "geometry": {
        "type": "Point",
        "coordinates": [
          148.6833,
          -21.189802
        ]
      },
      "properties": {
        "EVENT_ID": "24MK3047",
        "TYPE": "PLANNED",
        "CUSTOMERS_AFFECTED": "30",
        "REASON": "The loss of supply is to replace power poles and improve the electricity network",
        "STATUS": "Crews working on-site",
        "START": "7:33AM 21 Apr 2024",
        "EST_FIX_TIME": "5:50PM 21 Apr 2024",
        "STREETS": "LUCAS PADDOCK RD, WALKER FINNS RD",
        "SUBURBS": "PINNACLE"
      }
    }
  ],
  "company": "Ergon",
  "state": "Current",
  "extracted": "1713684301.581812"
}
