{
  "type": "FeatureCollection",
  "name": "PLANNED",
  "features": [
    {
      "type": "Feature",
      "geometry": {
        "type": "Point",
        "coordinates": [
          149.959768,
          -24.719652
        ]
      },
      "properties": {
        "EVENT_ID": "24CA2668",
        "TYPE": "PLANNED",
        "CUSTOMERS_AFFECTED": "44",
        "REASON": "The loss of supply is to connect new customers to the electricity network",
        "STATUS": "Crews working on-site",
        "START": "8:30AM 24 Apr 2024",
        "EST_FIX_TIME": "4:30PM 24 Apr 2024",
        "STREETS": "BECKERS RD, BEHRENDORFFS RD, BURNSIDE-MCLELLANS RD, DAWSON HWY, KIANGA RIVER RD, MALONEYS RD, NIPAN-RIVER RD, RIVER RD, THEODORE BARALABA RD, THEODORE MOURA RD",
        "SUBURBS": "KIANGA, MOURA, THEODORE"
      }
    },
    {
      "type": "Feature",
      "geometry": {
        "type": "Point",
        "coordinates": [
          148.024149,
          -23.532895
        ]
      },
      "properties": {
        "EVENT_ID": "24CA4563",
        "TYPE": "PLANNED",
        "CUSTOMERS_AFFECTED": "14",
        "REASON": "The loss of supply is to allow maintenance of the electricity network",
        "STATUS": "Crews working on-site",
        "START": "8:46AM 24 Apr 2024",
        "EST_FIX_TIME": "5:00PM 24 Apr 2024",
        "STREETS": "CAPRICORN HWY, DENISON RD, FORK LAGOONS RD, MARSHALL RD",
        "SUBURBS": "EMERALD"
      }
    },
    {
      "type": "Feature",
      "geometry": {
        "type": "Point",
        "coordinates": [
          145.748428,
          -16.914592
        ]
      },
      "properties": {
        "EVENT_ID": "24FN4955",
        "TYPE": "PLANNED",
        "CUSTOMERS_AFFECTED": "2",
        "REASON": "The loss of supply is to allow maintenance of the electricity network",
        "STATUS": "Work scheduled",
        "START": "4:00PM 24 Apr 2024",
        "EST_FIX_TIME": "5:00PM 24 Apr 2024",
        "STREETS": "ANDERSON ST",
        "SUBURBS": "MANUNDA"
      }
    },
    {
      "type": "Feature",
      "geometry": {
        "type": "Point",
        "coordinates": [
          151.204717,
          -27.443763
        ]
      },
      "properties": {
        "EVENT_ID": "24SW5977",
        "TYPE": "PLANNED",
        "CUSTOMERS_AFFECTED": "14",
        "REASON": "The loss of supply is to replace power poles and improve the electricity network",
        "STATUS": "Crews working on-site",
        "START": "8:30AM 24 Apr 2024",
        "EST_FIX_TIME": "4:30PM 24 Apr 2024",
        "STREETS": "BOKELMAN RD, DALBY-CECIL PLAINS RD, MISS JURGS RD, NEVILLE RD, PERCY JURGS RD, TED JURGS RD, TIPTON HORRANE RD",
        "SUBURBS": "CECIL PLAINS, TIPTON"
      }
    }
  ],
  "company": "Ergon",
  "state": "Current",
  "extracted": "1713938100.776924"
}
