{
  "type": "FeatureCollection",
  "name": "PLANNED",
  "features": [
    {
      "type": "Feature",
      "geometry": {
        "type": "Point",
        "coordinates": [
          147.408299,
          -19.568983
        ]
      },
      "properties": {
        "EVENT_ID": "24NQ6836",
        "TYPE": "PLANNED",
        "CUSTOMERS_AFFECTED": "85",
        "REASON": "The loss of supply is to allow maintenance of the electricity network",
        "STATUS": "Crews working on-site",
        "START": "9:27AM 07 May 2024",
        "EST_FIX_TIME": "4:00PM 07 May 2024",
        "STREETS": "CAMERON ST, CHIPPENDALE ST, COX ST, MUNRO ST, ROSSITER ST, SPILLER ST, WILMINGTON ST",
        "SUBURBS": "AYR"
      }
    },
    {
      "type": "Feature",
      "geometry": {
        "type": "Point",
        "coordinates": [
          146.331519,
          -18.526706
        ]
      },
      "properties": {
        "EVENT_ID": "24NQ7260",
        "TYPE": "PLANNED",
        "CUSTOMERS_AFFECTED": "4",
        "REASON": "The loss of supply is to connect new customers to the electricity network",
        "STATUS": "Crews working on-site",
        "START": "7:42AM 07 May 2024",
        "EST_FIX_TIME": "3:30PM 08 May 2024",
        "STREETS": "DUNGENESS RD, KEAST ST",
        "SUBURBS": "LUCINDA"
      }
    }
  ],
  "company": "Ergon",
  "state": "Current",
  "extracted": "1715060100.995518"
}
