{
  "type": "FeatureCollection",
  "name": "PLANNED",
  "features": [
    {
      "type": "Feature",
      "geometry": {
        "type": "Point",
        "coordinates": [
          148.24635,
          -20.012359
        ]
      },
      "properties": {
        "EVENT_ID": "24NQ5563",
        "TYPE": "PLANNED",
        "CUSTOMERS_AFFECTED": "28",
        "REASON": "The loss of supply is to allow maintenance of the electricity network",
        "STATUS": "Work scheduled",
        "START": "10:00PM 20 Mar 2024",
        "EST_FIX_TIME": "3:00AM 21 Mar 2024",
        "STREETS": "HERBERT ST, POWELL ST, WILLIAMS ST",
        "SUBURBS": "BOWEN"
      }
    }
  ],
  "company": "Ergon",
  "state": "Current",
  "extracted": "1710934801.272292"
}
