{
  "type": "FeatureCollection",
  "name": "PLANNED",
  "features": [
    {
      "type": "Feature",
      "geometry": {
        "type": "Point",
        "coordinates": [
          152.18073,
          -25.330587
        ]
      },
      "properties": {
        "EVENT_ID": "24WB5836",
        "TYPE": "PLANNED",
        "CUSTOMERS_AFFECTED": "64",
        "REASON": "The loss of supply is to upgrade equipment to meet customer demand for electricity and to improve reliability of supply in the area",
        "STATUS": "Crews working on-site",
        "START": "9:01AM 18 Jun 2024",
        "EST_FIX_TIME": "6:00PM 18 Jun 2024",
        "STREETS": "AGNESVALE RD, BERRIES RD, BIGGENDEN RD, EUREKA RD, FAINTS RD, ISIS HWY, NORTH SOUTH RD, RENDALLS RD, SAWMILL RD",
        "SUBURBS": "APPLE TREE CREEK, CHILDERS, EUREKA, GOLDEN FLEECE, ISIS CENTRAL, KULLOGUM"
      }
    }
  ],
  "company": "Ergon",
  "state": "Current",
  "extracted": "1718696703.885105"
}
