{
  "type": "FeatureCollection",
  "name": "PLANNED",
  "features": [
    {
      "type": "Feature",
      "geometry": {
        "type": "Point",
        "coordinates": [
          149.148686,
          -21.212794
        ]
      },
      "properties": {
        "EVENT_ID": "25MK0915",
        "TYPE": "PLANNED",
        "CUSTOMERS_AFFECTED": "2",
        "REASON": "The loss of supply is to connect new customers to the electricity network",
        "STATUS": "Crews working on-site",
        "START": "7:00AM 08 Mar 2025",
        "EST_FIX_TIME": "4:00PM 08 Mar 2025",
        "STREETS": "MAIN ST",
        "SUBURBS": "BAKERS CREEK"
      }
    },
    {
      "type": "Feature",
      "geometry": {
        "type": "Point",
        "coordinates": [
          149.194828,
          -21.14899
        ]
      },
      "properties": {
        "EVENT_ID": "25MK1203",
        "TYPE": "PLANNED",
        "CUSTOMERS_AFFECTED": "173",
        "REASON": "The loss of supply is to connect new customers to the electricity network",
        "STATUS": "Crews working on-site",
        "START": "8:31AM 08 Mar 2025",
        "EST_FIX_TIME": "3:00PM 08 Mar 2025",
        "STREETS": "GOLD ST, GOLDSMITH ST, HAGUE ST, KATE ST, MACROSSAN ST, PARK ST, RAE ST, SHAKESPEARE ST",
        "SUBURBS": "EAST MACKAY, MACKAY"
      }
    },
    {
      "type": "Feature",
      "geometry": {
        "type": "Point",
        "coordinates": [
          145.280891,
          -19.484062
        ]
      },
      "properties": {
        "EVENT_ID": "25NQ1101",
        "TYPE": "PLANNED",
        "CUSTOMERS_AFFECTED": "3",
        "REASON": "The loss of supply is to replace power poles and improve the electricity network",
        "STATUS": "Crews working on-site",
        "START": "9:13AM 08 Mar 2025",
        "EST_FIX_TIME": "2:30PM 08 Mar 2025",
        "STREETS": "MARYVALE STATION, NIALL STATION",
        "SUBURBS": "BLUEWATER SPRINGS"
      }
    },
    {
      "type": "Feature",
      "geometry": {
        "type": "Point",
        "coordinates": [
          146.71967,
          -19.330951
        ]
      },
      "properties": {
        "EVENT_ID": "25NQ3029",
        "TYPE": "PLANNED",
        "CUSTOMERS_AFFECTED": "10",
        "REASON": "The loss of supply is to replace power poles and improve the electricity network",
        "STATUS": "Crews working on-site",
        "START": "8:09AM 08 Mar 2025",
        "EST_FIX_TIME": "3:00PM 08 Mar 2025",
        "STREETS": "TOUCAN CRES",
        "SUBURBS": "CONDON"
      }
    }
  ],
  "company": "Ergon",
  "state": "Current",
  "extracted": "1741407305.26592"
}
