{
  "type": "FeatureCollection",
  "name": "PLANNED",
  "features": [
    {
      "type": "Feature",
      "geometry": {
        "type": "Point",
        "coordinates": [
          139.179775,
          -16.664853
        ]
      },
      "properties": {
        "EVENT_ID": "24FN3093",
        "TYPE": "PLANNED",
        "CUSTOMERS_AFFECTED": "7",
        "REASON": "The loss of supply is to replace power poles and improve the electricity network",
        "STATUS": "Crews working on-site",
        "START": "8:30AM 07 Apr 2024",
        "EST_FIX_TIME": "3:30PM 07 Apr 2024",
        "STREETS": "DJINKYA ST, JINKIYA ST, KATHAN KATHAN ST, LARDIL ST",
        "SUBURBS": "GUNUNA"
      }
    },
    {
      "type": "Feature",
      "geometry": {
        "type": "Point",
        "coordinates": [
          152.664697,
          -25.807974
        ]
      },
      "properties": {
        "EVENT_ID": "24WB4105",
        "TYPE": "PLANNED",
        "CUSTOMERS_AFFECTED": "114",
        "REASON": "The loss of supply is to allow maintenance of the electricity network",
        "STATUS": "Crews working on-site",
        "START": "8:34AM 07 Apr 2024",
        "EST_FIX_TIME": "3:30PM 07 Apr 2024",
        "STREETS": "ACACIA RD, BAND HALL RD, BANKSIA RD, CASSIA RD, CEDAR RD, COOMBES RD, CYPRESS RD, EUCALYPTUS RD, FORESTRY RD, KEENES RD, MACKELLAR ST, MAHOGANY RD, MEREDITH RD, MESSMATE RD, MILL ST, STOTTENVILLE RD, TALEGALLA DR",
        "SUBURBS": "BAUPLE, TALEGALLA WEIR, TALLAGALLA"
      }
    }
  ],
  "company": "Ergon",
  "state": "Current",
  "extracted": "1712466301.717715"
}
