{
  "type": "FeatureCollection",
  "name": "PLANNED",
  "features": [
    {
      "type": "Feature",
      "geometry": {
        "type": "Point",
        "coordinates": [
          150.698527,
          -23.147434
        ]
      },
      "properties": {
        "EVENT_ID": "24CA7352",
        "TYPE": "PLANNED",
        "CUSTOMERS_AFFECTED": "163",
        "REASON": "The loss of supply is to upgrade equipment to meet customer demand for electricity and to improve reliability of supply in the area",
        "STATUS": "Crews working on-site",
        "START": "9:01AM 19 Jun 2024",
        "EST_FIX_TIME": "5:30PM 19 Jun 2024",
        "STREETS": "AZTEC CT, BARMARYEE RD, COBRABALL RD, COTTONS RD, DIVINE ST, DOWLINGS RD, FORRESTER WAY, MARK RD, NEILS RD, SERENGETI CT, SERENGETTI CT, SUNLANDER CL",
        "SUBURBS": "BARMARYEE, BONDOOLA, YEPPOON"
      }
    },
    {
      "type": "Feature",
      "geometry": {
        "type": "Point",
        "coordinates": [
          149.085778,
          -21.167472
        ]
      },
      "properties": {
        "EVENT_ID": "24MK4422",
        "TYPE": "PLANNED",
        "CUSTOMERS_AFFECTED": "117",
        "REASON": "The loss of supply is to upgrade equipment to meet customer demand for electricity and to improve reliability of supply in the area",
        "STATUS": "Crews working on-site",
        "START": "9:16AM 19 Jun 2024",
        "EST_FIX_TIME": "5:00PM 19 Jun 2024",
        "STREETS": "ALEXANDRIA RD, CREEK ST, HOMEBUSH RD, LORNE RD, MACKAY EUNGELLA RD, PALMS RD, PEAK DOWNS HWY, TIDEMANN ST, WALKERSTON HOMEBUSH RD, WEIGANDS RD",
        "SUBURBS": "ALEXANDRA, MACKAY, PALMYRA, WALKERSTON"
      }
    },
    {
      "type": "Feature",
      "geometry": {
        "type": "Point",
        "coordinates": [
          144.189299,
          -20.842525
        ]
      },
      "properties": {
        "EVENT_ID": "24NQ9050",
        "TYPE": "PLANNED",
        "CUSTOMERS_AFFECTED": "65",
        "REASON": "The loss of supply is to replace power poles and improve the electricity network",
        "STATUS": "Crews working on-site",
        "START": "8:30AM 19 Jun 2024",
        "EST_FIX_TIME": "5:00PM 19 Jun 2024",
        "STREETS": "BETTS ST, CHURCHILL ST, CORNEY ST, FLINDERS DAIRY STATION, FLINDERS HWY, HARDWICKE ST, MARATHON ST, MOWBRAY ST, RICHMOND HILL DR, RICHMOND RD",
        "SUBURBS": "HUGHENDEN"
      }
    },
    {
      "type": "Feature",
      "geometry": {
        "type": "Point",
        "coordinates": [
          145.006606,
          -28.03002
        ]
      },
      "properties": {
        "EVENT_ID": "24SW8926",
        "TYPE": "PLANNED",
        "CUSTOMERS_AFFECTED": "1478",
        "REASON": "The loss of supply is to allow maintenance of the electricity network",
        "STATUS": "Work scheduled",
        "START": "10:30PM 19 Jun 2024",
        "EST_FIX_TIME": "12:30AM 20 Jun 2024",
        "STREETS": "AIRPORT RD, ALDVILLE RD, ALICE ST, ARCHERNAR ST, ARTHUR ST, BALONNE HWY, BEARDMORE ST, BEDFORD ST, BLACK CROW PDE, BLACKGATE RD, BLUE BONNET BVD, BLUFF RD, BOOBIALLA ST, BORONIA ST, BOUGANVILLEA ST, BOWER ST, BOWRA ST, BROAD ST, BULLAWARRA STATION RD, BULLOO DEVELOPMENTAL RD, BULLOO RIVER RD, BUNDEENA RD, CAMDEN RD, CANOPUS ST, CEDAR LANE, CHALE ST, CHARLEVILLE-BOLLON RD, CHARLEVILLE-WYANDRA RD, COONGOOLA LANE, CORELLA ST, CRYSTAL LANE, CUTTABURRA RD, DEVELOPMENTAL RD, DOWLING ST, EASTON DR, ECCLES ST, ECHIDNA ST, ELMINA RD, EMMA ST, EMU ST, EULO ST, EULO-HUNGERFORD RD, FITZWALTER ST, FLORENCE ST, FRANCIS ST, FREW ST, GAMARREN RD, GARDEN ST, GIDYEA CL, GILMOUR ST, GLENTUCKIE RD, HANSON ST, HARLEQUIN DR, HICKLING ST, HUMEBURN RD, HUNGERFORD RD, IVAN ST, JACKSON RD, JANE ST, JOBS GATE RD, JOHN ST, KING ST, KOONAWARRA RD, LEO ST, LINDEN-NEBINE RD, LITTLE BEDFORD ST, LOUISE ST, LOWER CEMETERY RD, MABEL ST, MACK ST, MACKS ST, MARY ST, MATRIX DR, MCGREGOR ST, MIDDLETON RD, MITCHELL HWY, MOODY ST, MOORE ST, MOUNT ALFRED RD, MT ALFRED-QUILPIE RD, MULGA ST, MUNDA MUNDA RD, MURRA MURRA RD, MURRAY ST, NANCY BIRD WALTON WAY, NINGALING RD, NORTH ST, OLD BOURKE RD, OLD CHARLEVILLE RD, OPAL ST, PARK LANE, PAROO ST, PITHERTY RD, POWELL ST, QUILPIE-THARGOMINDAH RD, RAILWAY ST, ROBINA DOWNS RD, ROCKWELL RD, ROSEVALE RD, SAMS ST, SOMMERFIELD RD, SPEEDY ST, STAFFORD ST, STOCKYARD ST, TALBAREA RD, TERALDON RD, THARGOMINDAH RD, THARGOMINDAH-HUNGERFORD RD, THURULGOONA RD, TOOMPINE RD, TORRENCE PDE, UNKNOWN RD, WARREGO ST, WATSON ST, WATTS ST, WAVERLY-MINTAKA RD, WEIR RD, WERAI PARK RD, WERENILKE RD, WESTERN WARREGO RD, WHITEWOOD DR, WICKS ST, WIDGEEGOARA RD, WILLIAM ST, WOMBULA-YENLORA RD, WREN LANE, YERREL RD, YOWAH RD",
        "SUBURBS": "BOLLON, CHARLEVILLE, CUNNAMULLA, EULO, HUNGERFORD, MORVEN, QUILPIE, THARGOMINDAH, WYANDRA, YOWAH"
      }
    }
  ],
  "company": "Ergon",
  "state": "Current",
  "extracted": "1718779201.244792"
}
