{
  "type": "FeatureCollection",
  "name": "PLANNED",
  "features": [
    {
      "type": "Feature",
      "geometry": {
        "type": "Point",
        "coordinates": [
          145.606606,
          -16.849052
        ]
      },
      "properties": {
        "EVENT_ID": "24FN4229",
        "TYPE": "PLANNED",
        "CUSTOMERS_AFFECTED": "12",
        "REASON": "The loss of supply is to replace power poles and improve the electricity network",
        "STATUS": "Crews working on-site",
        "START": "8:33AM 15 Apr 2024",
        "EST_FIX_TIME": "4:30PM 15 Apr 2024",
        "STREETS": "KENNEDY HWY, MOUNT HAREN RD, UNKNOWN ST, WINDY HOLLOW RD",
        "SUBURBS": "KURANDA, MOUNT HAREN"
      }
    },
    {
      "type": "Feature",
      "geometry": {
        "type": "Point",
        "coordinates": [
          145.753663,
          -16.969518
        ]
      },
      "properties": {
        "EVENT_ID": "24FN4343",
        "TYPE": "PLANNED",
        "CUSTOMERS_AFFECTED": "13",
        "REASON": "The loss of supply is to replace power poles and improve the electricity network",
        "STATUS": "Crews working on-site",
        "START": "7:30AM 15 Apr 2024",
        "EST_FIX_TIME": "4:30PM 15 Apr 2024",
        "STREETS": "BURTON CL",
        "SUBURBS": "WHITE ROCK"
      }
    },
    {
      "type": "Feature",
      "geometry": {
        "type": "Point",
        "coordinates": [
          146.331519,
          -18.526706
        ]
      },
      "properties": {
        "EVENT_ID": "24NQ5670",
        "TYPE": "PLANNED",
        "CUSTOMERS_AFFECTED": "4",
        "REASON": "The loss of supply is to allow maintenance of the electricity network",
        "STATUS": "Crews working on-site",
        "START": "9:00AM 15 Apr 2024",
        "EST_FIX_TIME": "3:00PM 19 Apr 2024",
        "STREETS": "DUNGENESS RD, KEAST ST",
        "SUBURBS": "LUCINDA"
      }
    },
    {
      "type": "Feature",
      "geometry": {
        "type": "Point",
        "coordinates": [
          142.74617,
          -20.571677
        ]
      },
      "properties": {
        "EVENT_ID": "24NQ6408",
        "TYPE": "PLANNED",
        "CUSTOMERS_AFFECTED": "9",
        "REASON": "The loss of supply is to replace power poles and improve the electricity network",
        "STATUS": "Crews working on-site",
        "START": "8:31AM 15 Apr 2024",
        "EST_FIX_TIME": "4:30PM 15 Apr 2024",
        "STREETS": "ARTESIAN DOWNS STATION, GRACEDALE STATION, HARROGATE STATION, HOPEVALE STATION, LILYVALE STATION, MAJUBA STATION, MOLESWORTH STATION, MORUNGLE STATION, OBAN STATION",
        "SUBURBS": "MAXWELTON, RICHMOND"
      }
    }
  ],
  "company": "Ergon",
  "state": "Current",
  "extracted": "1713160802.110406"
}
