{
  "type": "FeatureCollection",
  "name": "PLANNED",
  "features": [
    {
      "type": "Feature",
      "geometry": {
        "type": "Point",
        "coordinates": [
          145.924373,
          -17.935617
        ]
      },
      "properties": {
        "EVENT_ID": "24FN5698",
        "TYPE": "PLANNED",
        "CUSTOMERS_AFFECTED": "58",
        "REASON": "The loss of supply is to allow maintenance of the electricity network",
        "STATUS": "Work scheduled",
        "START": "10:00PM 28 May 2024",
        "EST_FIX_TIME": "4:00AM 29 May 2024",
        "STREETS": "BRYANT ST, BUTLER ST, MILL RES, MILL RESERVE ST, MORRIS ST, WATKINS ST, WRIT LANE",
        "SUBURBS": "TULLY"
      }
    },
    {
      "type": "Feature",
      "geometry": {
        "type": "Point",
        "coordinates": [
          146.331519,
          -18.526706
        ]
      },
      "properties": {
        "EVENT_ID": "24NQ7319",
        "TYPE": "PLANNED",
        "CUSTOMERS_AFFECTED": "4",
        "REASON": "The loss of supply is to connect new customers to the electricity network",
        "STATUS": "Crews working on-site",
        "START": "12:30PM 17 May 2024",
        "EST_FIX_TIME": "3:30PM 30 May 2024",
        "STREETS": "DUNGENESS RD, KEAST ST",
        "SUBURBS": "LUCINDA"
      }
    },
    {
      "type": "Feature",
      "geometry": {
        "type": "Point",
        "coordinates": [
          146.795174,
          -19.292558
        ]
      },
      "properties": {
        "EVENT_ID": "24NQ8322",
        "TYPE": "PLANNED",
        "CUSTOMERS_AFFECTED": "151",
        "REASON": "The loss of supply is to upgrade equipment to meet customer demand for electricity and to improve reliability of supply in the area",
        "STATUS": "Work scheduled",
        "START": "9:00PM 28 May 2024",
        "EST_FIX_TIME": "3:00AM 29 May 2024",
        "STREETS": "BENT ST, BOWEN RD, CAMP ST, CHARTERS TOWERS RD, CROSS ST, HALLORAN ST, JAMESON ST, QUEENS RD, ROSS RIVER RD, SWEET ST",
        "SUBURBS": "HERMIT PARK, MUNDINGBURRA, MYSTERTON"
      }
    },
    {
      "type": "Feature",
      "geometry": {
        "type": "Point",
        "coordinates": [
          146.79463,
          -19.29184
        ]
      },
      "properties": {
        "EVENT_ID": "24NQ8323",
        "TYPE": "PLANNED",
        "CUSTOMERS_AFFECTED": "28",
        "REASON": "The loss of supply is to replace power poles and improve the electricity network",
        "STATUS": "Work scheduled",
        "START": "9:00PM 28 May 2024",
        "EST_FIX_TIME": "3:00AM 29 May 2024",
        "STREETS": "CHARTERS TOWERS RD, ROSS RIVER RD",
        "SUBURBS": "MUNDINGBURRA, MYSTERTON"
      }
    }
  ],
  "company": "Ergon",
  "state": "Current",
  "extracted": "1716893109.795961"
}
