{
  "type": "FeatureCollection",
  "name": "PLANNED",
  "features": [
    {
      "type": "Feature",
      "geometry": {
        "type": "Point",
        "coordinates": [
          149.066136,
          -23.581595
        ]
      },
      "properties": {
        "EVENT_ID": "24CA6763",
        "TYPE": "PLANNED",
        "CUSTOMERS_AFFECTED": "3",
        "REASON": "The loss of supply is to replace power poles and improve the electricity network",
        "STATUS": "Crews working on-site",
        "START": "10:51AM 05 Jun 2024",
        "EST_FIX_TIME": "4:30PM 05 Jun 2024",
        "STREETS": "MAIN ST",
        "SUBURBS": "BLUFF"
      }
    },
    {
      "type": "Feature",
      "geometry": {
        "type": "Point",
        "coordinates": [
          148.24806,
          -20.013673
        ]
      },
      "properties": {
        "EVENT_ID": "24NQ8947",
        "TYPE": "PLANNED",
        "CUSTOMERS_AFFECTED": "5",
        "REASON": "The loss of supply is to replace power poles and improve the electricity network",
        "STATUS": "Crews working on-site",
        "START": "11:49AM 05 Jun 2024",
        "EST_FIX_TIME": "4:00PM 05 Jun 2024",
        "STREETS": "GEORGE ST, HERBERT ST",
        "SUBURBS": "BOWEN"
      }
    }
  ],
  "company": "Ergon",
  "state": "Current",
  "extracted": "1717562703.310275"
}
