{
  "type": "FeatureCollection",
  "name": "PLANNED",
  "features": [
    {
      "type": "Feature",
      "geometry": {
        "type": "Point",
        "coordinates": [
          148.840067,
          -21.008125
        ]
      },
      "properties": {
        "EVENT_ID": "24MK3563",
        "TYPE": "PLANNED",
        "CUSTOMERS_AFFECTED": "90",
        "REASON": "The loss of supply is to replace power poles and improve the electricity network",
        "STATUS": "Crews working on-site",
        "START": "8:30AM 10 May 2024",
        "EST_FIX_TIME": "3:30PM 10 May 2024",
        "STREETS": "BRUCE HWY, BUTHURRA STATION RD, FAIRCHILDS RD, GEEBERGA BUTHURRA RD, GIFFORDS RD, MCKAYS RD, MCLEANS RD, NARPI RD, PACES RD, STARKEYS RD, WATTS RD",
        "SUBURBS": "BUTHURRA, KUTTABUL, MACKAY, MOUNT CHARLTON, MOUNT OSSA"
      }
    },
    {
      "type": "Feature",
      "geometry": {
        "type": "Point",
        "coordinates": [
          146.331519,
          -18.526706
        ]
      },
      "properties": {
        "EVENT_ID": "24NQ7260",
        "TYPE": "PLANNED",
        "CUSTOMERS_AFFECTED": "4",
        "REASON": "The loss of supply is to connect new customers to the electricity network",
        "STATUS": "Crews working on-site",
        "START": "7:42AM 07 May 2024",
        "EST_FIX_TIME": "3:30PM 14 May 2024",
        "STREETS": "DUNGENESS RD, KEAST ST",
        "SUBURBS": "LUCINDA"
      }
    }
  ],
  "company": "Ergon",
  "state": "Current",
  "extracted": "1715321101.249594"
}
