{
  "type": "FeatureCollection",
  "name": "PLANNED",
  "features": [
    {
      "type": "Feature",
      "geometry": {
        "type": "Point",
        "coordinates": [
          151.93011,
          -27.562697
        ]
      },
      "properties": {
        "EVENT_ID": "24SW9234",
        "TYPE": "PLANNED",
        "CUSTOMERS_AFFECTED": "7",
        "REASON": "The loss of supply is to upgrade equipment to meet customer demand for electricity and to improve reliability of supply in the area",
        "STATUS": "Crews working on-site",
        "START": "8:30AM 09 Jun 2024",
        "EST_FIX_TIME": "4:30PM 09 Jun 2024",
        "STREETS": "ANZAC AVE, HURSLEY RD",
        "SUBURBS": "NEWTOWN"
      }
    }
  ],
  "company": "Ergon",
  "state": "Current",
  "extracted": "1717917001.672077"
}
