{
  "type": "FeatureCollection",
  "name": "PLANNED",
  "features": [
    {
      "type": "Feature",
      "geometry": {
        "type": "Point",
        "coordinates": [
          150.745343,
          -23.112349
        ]
      },
      "properties": {
        "EVENT_ID": "24CA5340",
        "TYPE": "PLANNED",
        "CUSTOMERS_AFFECTED": "2",
        "REASON": "The loss of supply is to replace power poles and improve the electricity network",
        "STATUS": "Crews working on-site",
        "START": "1:57PM 26 Apr 2024",
        "EST_FIX_TIME": "4:30PM 26 Apr 2024",
        "STREETS": "GREER ST",
        "SUBURBS": "MEIKLEVILLE HILL"
      }
    },
    {
      "type": "Feature",
      "geometry": {
        "type": "Point",
        "coordinates": [
          148.822647,
          -21.091816
        ]
      },
      "properties": {
        "EVENT_ID": "24MK3411",
        "TYPE": "PLANNED",
        "CUSTOMERS_AFFECTED": "80",
        "REASON": "The loss of supply is to allow maintenance of the electricity network",
        "STATUS": "Crews working on-site",
        "START": "9:00AM 26 Apr 2024",
        "EST_FIX_TIME": "5:00PM 26 Apr 2024",
        "STREETS": "BRADSHAWS RD, COYNES RD, GARNHAM MORROWS RD, GEEBERGA BUTHURRA RD, MCFAULS RD, MORRIS RD, MOUNT MARTIN GAP RD, MOUNT MARTIN LOOP RD, MOUNT MARTIN RD, MOUNT TOBY RD, SUGARLOAF RD",
        "SUBURBS": "KUTTABUL, MOUNT MARTIN"
      }
    }
  ],
  "company": "Ergon",
  "state": "Current",
  "extracted": "1714111801.299639"
}
